Workbook

Sheet Lançamentos
A1: CONTROLO DE ADIANTAMENTOS / EMPRÉSTIMOS DO SÓCIO – ARRANQUE DE ATIVIDADES
A2: École Consulaire du Congo (Brazzaville) de Luanda • Registo de entradas de capital e despesas de arranque
A3: Amarelo = preencher | Verde = calculado | Nº Interno Doc. = número a escrever na fatura física
A5: RESUMO FINANCEIRO
A6: Total Entradas (Empréstimos) | B6: =SUMIF(H12:H200,"Entrada",I12:I200) -> 4988379.9 | C6: KZ
A7: Total Despesas Lançadas | B7: =SUMIF(H12:H200,"Despesa",I12:I200) -> 4988379.9 | C7: KZ
A8: TOTAL A REEMBOLSAR | B8: =B6 -> 4988379.9 | C8: KZ
A9: Saldo (Entradas − Despesas) | B9: =B6-B7 -> 0 | C9: KZ
A10: Nota: Nº e Nº Interno Doc. são automáticos e contínuos. Escreva o Nº Interno (FAT-001…) na fatura física. Se o Nº Fatura Fornecedor ou a combinação Fornecedor+Fatura se repetir, a célula fica vermelha e aparece alerta em "Alerta Duplicado".
A11: Nº | B11: Data | C11: Categoria | D11: Descrição / Detalhe | E11: Fornecedor | F11: Nº Fatura Fornecedor | G11: Nº Interno Doc. | H11: Tipo | I11: Valor (KZ) | J11: Forma de Pagamento | K11: Observações | L11: Alerta Duplicado
A12: =IF(B12="","",COUNTA($B$12:B12)) -> 1 | B12: 46187 | C12: Empréstimo Sócio | D12: Entrada de capital do sócio (total das despesas de arranque) | G12: =IF(B12="","","FAT-"&TEXT(COUNTA($B$12:B12),"000")) -> FAT-001 | H12: Entrada | I12: 4988379.9 | J12: Transferência | L12: =IF(B12="","",IF(AND(F12<>"",COUNTIF($F$12:$F$200,F12)>1),"⚠ FATURA DUPLICADA",IF(AND(E12<>"",F12<>"",COUNTIFS($E$12:$E$200,E12,$F$12:$F$200,F12)>1),"⚠ DUPLICADO","")))
A13: =IF(B13="","",COUNTA($B$12:B13)) -> 2 | B13: 46187 | C13: Pintura Exterior | D13: Tinta para pintura exterior | E13: Achour - Comércio Geral | F13: 829 | G13: =IF(B13="","","FAT-"&TEXT(COUNTA($B$12:B13),"000")) -> FAT-002 | H13: Despesa | I13: 265000 | J13: Cartão Multicaixa | L13: =IF(B13="","",IF(AND(F13<>"",COUNTIF($F$12:$F$200,F13)>1),"⚠ FATURA DUPLICADA",IF(AND(E13<>"",F13<>"",COUNTIFS($E$12:$E$200,E13,$F$12:$F$200,F13)>1),"⚠ DUPLICADO","")))
A14: =IF(B14="","",COUNTA($B$12:B14)) -> 3 | B14: 46198 | C14: Internet / Telefone | D14: Telemóvel secretaria | E14: Mobismart | F14: ´202606251721242870014 | G14: =IF(B14="","","FAT-"&TEXT(COUNTA($B$12:B14),"000")) -> FAT-003 | H14: Despesa | I14: 106000 | J14: Cartão Multicaixa | L14: =IF(B14="","",IF(AND(F14<>"",COUNTIF($F$12:$F$200,F14)>1),"⚠ FATURA DUPLICADA",IF(AND(E14<>"",F14<>"",COUNTIFS($E$12:$E$200,E14,$F$12:$F$200,F14)>1),"⚠ DUPLICADO","")))
A15: =IF(B15="","",COUNTA($B$12:B15)) -> 4 | B15: 46198 | C15: Internet / Telefone | D15: Telemóvel direcção pedagógica | E15: Mobismart | F15: ´202606251717116930013 | G15: =IF(B15="","","FAT-"&TEXT(COUNTA($B$12:B15),"000")) -> FAT-004 | H15: Despesa | I15: 106000 | J15: Cartão Multicaixa | L15: =IF(B15="","",IF(AND(F15<>"",COUNTIF($F$12:$F$200,F15)>1),"⚠ FATURA DUPLICADA",IF(AND(E15<>"",F15<>"",COUNTIFS($E$12:$E$200,E15,$F$12:$F$200,F15)>1),"⚠ DUPLICADO","")))
A16: =IF(B16="","",COUNTA($B$12:B16)) -> 5 | B16: 46198 | C16: Internet / Telefone | D16: Cartão SIM 945402542 | E16: Unitel | F16: FR4426S42818N/174541 | G16: =IF(B16="","","FAT-"&TEXT(COUNTA($B$12:B16),"000")) -> FAT-005 | H16: Despesa | I16: 250.01 | J16: Cartão Multicaixa | L16: =IF(B16="","",IF(AND(F16<>"",COUNTIF($F$12:$F$200,F16)>1),"⚠ FATURA DUPLICADA",IF(AND(E16<>"",F16<>"",COUNTIFS($E$12:$E$200,E16,$F$12:$F$200,F16)>1),"⚠ DUPLICADO","")))
A17: =IF(B17="","",COUNTA($B$12:B17)) -> 6 | B17: 46198 | C17: Internet / Telefone | D17: Cartões SIM (3 números) | E17: Unitel | F17: FR4426S42818N/174538 | G17: =IF(B17="","","FAT-"&TEXT(COUNTA($B$12:B17),"000")) -> FAT-006 | H17: Despesa | I17: 750.03 | J17: Cartão Multicaixa | L17: =IF(B17="","",IF(AND(F17<>"",COUNTIF($F$12:$F$200,F17)>1),"⚠ FATURA DUPLICADA",IF(AND(E17<>"",F17<>"",COUNTIFS($E$12:$E$200,E17,$F$12:$F$200,F17)>1),"⚠ DUPLICADO","")))
A18: =IF(B18="","",COUNTA($B$12:B18)) -> 7 | B18: 46198 | C18: Material de Escritório | D18: Material de escritório | E18: KERO | F18: FR8326S25915N/6523 | G18: =IF(B18="","","FAT-"&TEXT(COUNTA($B$12:B18),"000")) -> FAT-007 | H18: Despesa | I18: 17253 | J18: Cartão Multicaixa | L18: =IF(B18="","",IF(AND(F18<>"",COUNTIF($F$12:$F$200,F18)>1),"⚠ FATURA DUPLICADA",IF(AND(E18<>"",F18<>"",COUNTIFS($E$12:$E$200,E18,$F$12:$F$200,F18)>1),"⚠ DUPLICADO","")))
A19: =IF(B19="","",COUNTA($B$12:B19)) -> 8 | B19: 46199 | C19: Equipamentos | D19: 4 tinteiros HP Officejet Pro 7740 | E19: NCR | F19: FR4726S809N/35071 | G19: =IF(B19="","","FAT-"&TEXT(COUNTA($B$12:B19),"000")) -> FAT-008 | H19: Despesa | I19: 158189.82 | J19: Cartão Multicaixa | L19: =IF(B19="","",IF(AND(F19<>"",COUNTIF($F$12:$F$200,F19)>1),"⚠ FATURA DUPLICADA",IF(AND(E19<>"",F19<>"",COUNTIFS($E$12:$E$200,E19,$F$12:$F$200,F19)>1),"⚠ DUPLICADO","")))
A20: =IF(B20="","",COUNTA($B$12:B20)) -> 9 | B20: 46199 | C20: Outras Despesas | D20: 2 fechaduras | E20: Sahal Trading - Imp. & Exp. | F20: RTJ2026/1157 | G20: =IF(B20="","","FAT-"&TEXT(COUNTA($B$12:B20),"000")) -> FAT-009 | H20: Despesa | I20: 13100 | J20: Transferência Express | L20: =IF(B20="","",IF(AND(F20<>"",COUNTIF($F$12:$F$200,F20)>1),"⚠ FATURA DUPLICADA",IF(AND(E20<>"",F20<>"",COUNTIFS($E$12:$E$200,E20,$F$12:$F$200,F20)>1),"⚠ DUPLICADO","")))
A21: =IF(B21="","",COUNTA($B$12:B21)) -> 10 | B21: 46204 | C21: Pintura Exterior | D21: Tintas exterior e material construção | E21: Comércio Geral - Imp. & Exp. | F21: 1083 | G21: =IF(B21="","","FAT-"&TEXT(COUNTA($B$12:B21),"000")) -> FAT-010 | H21: Despesa | I21: 58500 | J21: Transferência | L21: =IF(B21="","",IF(AND(F21<>"",COUNTIF($F$12:$F$200,F21)>1),"⚠ FATURA DUPLICADA",IF(AND(E21<>"",F21<>"",COUNTIFS($E$12:$E$200,E21,$F$12:$F$200,F21)>1),"⚠ DUPLICADO","")))
A22: =IF(B22="","",COUNTA($B$12:B22)) -> 11 | B22: 46206 | C22: Outras Despesas | D22: Estuque e lixas | E22: M.N.A. SD. RAHMA | G22: =IF(B22="","","FAT-"&TEXT(COUNTA($B$12:B22),"000")) -> FAT-011 | H22: Despesa | I22: 31000 | J22: Transferência | L22: =IF(B22="","",IF(AND(F22<>"",COUNTIF($F$12:$F$200,F22)>1),"⚠ FATURA DUPLICADA",IF(AND(E22<>"",F22<>"",COUNTIFS($E$12:$E$200,E22,$F$12:$F$200,F22)>1),"⚠ DUPLICADO","")))
A23: =IF(B23="","",COUNTA($B$12:B23)) -> 12 | B23: 46211 | C23: Pintura Exterior | D23: Tintas e material de pintura | E23: Achour - Comércio Geral | F23: 805 | G23: =IF(B23="","","FAT-"&TEXT(COUNTA($B$12:B23),"000")) -> FAT-012 | H23: Despesa | I23: 128000 | J23: Cartão Multicaixa | L23: =IF(B23="","",IF(AND(F23<>"",COUNTIF($F$12:$F$200,F23)>1),"⚠ FATURA DUPLICADA",IF(AND(E23<>"",F23<>"",COUNTIFS($E$12:$E$200,E23,$F$12:$F$200,F23)>1),"⚠ DUPLICADO","")))
A24: =IF(B24="","",COUNTA($B$12:B24)) -> 13 | B24: 46211 | C24: Publicidade Exterior | D24: Impressão lona pesada 300x900 | E24: Gráfica TAMACO | F24: AFA7F84768594FCA | G24: =IF(B24="","","FAT-"&TEXT(COUNTA($B$12:B24),"000")) -> FAT-013 | H24: Despesa | I24: 85000 | J24: Cartão Multicaixa | L24: =IF(B24="","",IF(AND(F24<>"",COUNTIF($F$12:$F$200,F24)>1),"⚠ FATURA DUPLICADA",IF(AND(E24<>"",F24<>"",COUNTIFS($E$12:$E$200,E24,$F$12:$F$200,F24)>1),"⚠ DUPLICADO","")))
A25: =IF(B25="","",COUNTA($B$12:B25)) -> 14 | B25: 46214 | C25: Panfletos / Publicidade | D25: Impressão 500 panfletos A5 | E25: Gráfica TAMACO | G25: =IF(B25="","","FAT-"&TEXT(COUNTA($B$12:B25),"000")) -> FAT-014 | H25: Despesa | I25: 100000 | J25: Transferência | L25: =IF(B25="","",IF(AND(F25<>"",COUNTIF($F$12:$F$200,F25)>1),"⚠ FATURA DUPLICADA",IF(AND(E25<>"",F25<>"",COUNTIFS($E$12:$E$200,E25,$F$12:$F$200,F25)>1),"⚠ DUPLICADO","")))
A26: =IF(B26="","",COUNTA($B$12:B26)) -> 15 | B26: 46220 | C26: Equipamentos | D26: 8 lâmpadas fluorescentes + arrancadores | E26: DDH - Comércio Geral | F26: 2441 | G26: =IF(B26="","","FAT-"&TEXT(COUNTA($B$12:B26),"000")) -> FAT-015 | H26: Despesa | I26: 13600 | J26: Transferência Express | L26: =IF(B26="","",IF(AND(F26<>"",COUNTIF($F$12:$F$200,F26)>1),"⚠ FATURA DUPLICADA",IF(AND(E26<>"",F26<>"",COUNTIFS($E$12:$E$200,E26,$F$12:$F$200,F26)>1),"⚠ DUPLICADO","")))
A27: =IF(B27="","",COUNTA($B$12:B27)) -> 16 | B27: 46220 | C27: Material Serralharia | D27: Material para serralharia | E27: DKJF | F27: ´029 | G27: =IF(B27="","","FAT-"&TEXT(COUNTA($B$12:B27),"000")) -> FAT-016 | H27: Despesa | I27: 365000 | J27: Cartão Multicaixa | L27: =IF(B27="","",IF(AND(F27<>"",COUNTIF($F$12:$F$200,F27)>1),"⚠ FATURA DUPLICADA",IF(AND(E27<>"",F27<>"",COUNTIFS($E$12:$E$200,E27,$F$12:$F$200,F27)>1),"⚠ DUPLICADO","")))
A28: =IF(B28="","",COUNTA($B$12:B28)) -> 17 | B28: 46221 | C28: Equipamentos | D28: 5 garrafões gasóleo 20L | E28: Sonangol Distribuidora | F28: FR 202655/21059 | G28: =IF(B28="","","FAT-"&TEXT(COUNTA($B$12:B28),"000")) -> FAT-017 | H28: Despesa | I28: 42000 | J28: Dinheiro | L28: =IF(B28="","",IF(AND(F28<>"",COUNTIF($F$12:$F$200,F28)>1),"⚠ FATURA DUPLICADA",IF(AND(E28<>"",F28<>"",COUNTIFS($E$12:$E$200,E28,$F$12:$F$200,F28)>1),"⚠ DUPLICADO","")))
A29: =IF(B29="","",COUNTA($B$12:B29)) -> 18 | B29: 46222 | C29: Publicidade Exterior | D29: Impressão vinil 150x350 | E29: Gráfica TAMACO | F29: 7101738663 | G29: =IF(B29="","","FAT-"&TEXT(COUNTA($B$12:B29),"000")) -> FAT-018 | H29: Despesa | I29: 30000 | J29: Transferência | L29: =IF(B29="","",IF(AND(F29<>"",COUNTIF($F$12:$F$200,F29)>1),"⚠ FATURA DUPLICADA",IF(AND(E29<>"",F29<>"",COUNTIFS($E$12:$E$200,E29,$F$12:$F$200,F29)>1),"⚠ DUPLICADO","")))
A30: =IF(B30="","",COUNTA($B$12:B30)) -> 19 | B30: 46224 | C30: Outras Despesas | D30: Corrente + cadeado grande | E30: Praça | F30: 0279716 | G30: =IF(B30="","","FAT-"&TEXT(COUNTA($B$12:B30),"000")) -> FAT-019 | H30: Despesa | I30: 19000 | J30: Dinheiro | L30: =IF(B30="","",IF(AND(F30<>"",COUNTIF($F$12:$F$200,F30)>1),"⚠ FATURA DUPLICADA",IF(AND(E30<>"",F30<>"",COUNTIFS($E$12:$E$200,E30,$F$12:$F$200,F30)>1),"⚠ DUPLICADO","")))
A31: =IF(B31="","",COUNTA($B$12:B31)) -> 20 | B31: 46225 | C31: Equipamentos | D31: Material manutenção gerador | E31: Beledear Comércio Geral | F31: FT 2026/1862 | G31: =IF(B31="","","FAT-"&TEXT(COUNTA($B$12:B31),"000")) -> FAT-020 | H31: Despesa | I31: 348500.02 | J31: Transferência | L31: =IF(B31="","",IF(AND(F31<>"",COUNTIF($F$12:$F$200,F31)>1),"⚠ FATURA DUPLICADA",IF(AND(E31<>"",F31<>"",COUNTIFS($E$12:$E$200,E31,$F$12:$F$200,F31)>1),"⚠ DUPLICADO","")))
A32: =IF(B32="","",COUNTA($B$12:B32)) -> 21 | B32: 46226 | C32: Outras Despesas | D32: 20m rede para sombra | E32: Comércio Geral - Imp. & Exp. | F32: 1254 | G32: =IF(B32="","","FAT-"&TEXT(COUNTA($B$12:B32),"000")) -> FAT-021 | H32: Despesa | I32: 50000 | J32: Transferência Express | L32: =IF(B32="","",IF(AND(F32<>"",COUNTIF($F$12:$F$200,F32)>1),"⚠ FATURA DUPLICADA",IF(AND(E32<>"",F32<>"",COUNTIFS($E$12:$E$200,E32,$F$12:$F$200,F32)>1),"⚠ DUPLICADO","")))
A33: =IF(B33="","",COUNTA($B$12:B33)) -> 22 | B33: 46226 | C33: Equipamentos | D33: Conserto bomba injetora gerador | G33: =IF(B33="","","FAT-"&TEXT(COUNTA($B$12:B33),"000")) -> FAT-022 | H33: Despesa | I33: 25000 | J33: Transferência Express | L33: =IF(B33="","",IF(AND(F33<>"",COUNTIF($F$12:$F$200,F33)>1),"⚠ FATURA DUPLICADA",IF(AND(E33<>"",F33<>"",COUNTIFS($E$12:$E$200,E33,$F$12:$F$200,F33)>1),"⚠ DUPLICADO","")))
A34: =IF(B34="","",COUNTA($B$12:B34)) -> 23 | B34: 46226 | C34: Pintura Exterior | D34: 3 baldes tinta Coelho amarelo | E34: Bouke Salem | F34: 367 | G34: =IF(B34="","","FAT-"&TEXT(COUNTA($B$12:B34),"000")) -> FAT-023 | H34: Despesa | I34: 150000 | J34: Transferência | L34: =IF(B34="","",IF(AND(F34<>"",COUNTIF($F$12:$F$200,F34)>1),"⚠ FATURA DUPLICADA",IF(AND(E34<>"",F34<>"",COUNTIFS($E$12:$E$200,E34,$F$12:$F$200,F34)>1),"⚠ DUPLICADO","")))
A35: =IF(B35="","",COUNTA($B$12:B35)) -> 24 | B35: 46226 | C35: Pintura Exterior | D35: Tintas de óleo para decoração exterior | G35: =IF(B35="","","FAT-"&TEXT(COUNTA($B$12:B35),"000")) -> FAT-024 | H35: Despesa | I35: 97000 | J35: Transferência Express | L35: =IF(B35="","",IF(AND(F35<>"",COUNTIF($F$12:$F$200,F35)>1),"⚠ FATURA DUPLICADA",IF(AND(E35<>"",F35<>"",COUNTIFS($E$12:$E$200,E35,$F$12:$F$200,F35)>1),"⚠ DUPLICADO","")))
A36: =IF(B36="","",COUNTA($B$12:B36)) -> 25 | B36: 46226 | C36: Transporte s/ Fatura | D36: Táxi funcionário (Pedro Pintor) | G36: =IF(B36="","","FAT-"&TEXT(COUNTA($B$12:B36),"000")) -> FAT-025 | H36: Despesa | I36: 2000 | J36: Cartão Multicaixa | L36: =IF(B36="","",IF(AND(F36<>"",COUNTIF($F$12:$F$200,F36)>1),"⚠ FATURA DUPLICADA",IF(AND(E36<>"",F36<>"",COUNTIFS($E$12:$E$200,E36,$F$12:$F$200,F36)>1),"⚠ DUPLICADO","")))
A37: =IF(B37="","",COUNTA($B$12:B37)) -> 26 | B37: 46226 | C37: Transporte s/ Fatura | D37: Táxi funcionário (Ribeiro) | G37: =IF(B37="","","FAT-"&TEXT(COUNTA($B$12:B37),"000")) -> FAT-026 | H37: Despesa | I37: 2000 | J37: Transferência | L37: =IF(B37="","",IF(AND(F37<>"",COUNTIF($F$12:$F$200,F37)>1),"⚠ FATURA DUPLICADA",IF(AND(E37<>"",F37<>"",COUNTIFS($E$12:$E$200,E37,$F$12:$F$200,F37)>1),"⚠ DUPLICADO","")))
A38: =IF(B38="","",COUNTA($B$12:B38)) -> 27 | B38: 46226 | C38: Publicidade Exterior | D38: Impressão 3 peças vinil exterior | G38: =IF(B38="","","FAT-"&TEXT(COUNTA($B$12:B38),"000")) -> FAT-027 | H38: Despesa | I38: 16200 | J38: Transferência | L38: =IF(B38="","",IF(AND(F38<>"",COUNTIF($F$12:$F$200,F38)>1),"⚠ FATURA DUPLICADA",IF(AND(E38<>"",F38<>"",COUNTIFS($E$12:$E$200,E38,$F$12:$F$200,F38)>1),"⚠ DUPLICADO","")))
A39: =IF(B39="","",COUNTA($B$12:B39)) -> 28 | B39: 46226 | C39: Serralharia | D39: Mão de obra serralheiro | G39: =IF(B39="","","FAT-"&TEXT(COUNTA($B$12:B39),"000")) -> FAT-028 | H39: Despesa | I39: 50000 | J39: Transferência Express | L39: =IF(B39="","",IF(AND(F39<>"",COUNTIF($F$12:$F$200,F39)>1),"⚠ FATURA DUPLICADA",IF(AND(E39<>"",F39<>"",COUNTIFS($E$12:$E$200,E39,$F$12:$F$200,F39)>1),"⚠ DUPLICADO","")))
A40: =IF(B40="","",COUNTA($B$12:B40)) -> 29 | B40: 46226 | C40: Mão de Obra | D40: Mão de obra mecânico | G40: =IF(B40="","","FAT-"&TEXT(COUNTA($B$12:B40),"000")) -> FAT-029 | H40: Despesa | I40: 45000 | J40: Transferência Express | L40: =IF(B40="","",IF(AND(F40<>"",COUNTIF($F$12:$F$200,F40)>1),"⚠ FATURA DUPLICADA",IF(AND(E40<>"",F40<>"",COUNTIFS($E$12:$E$200,E40,$F$12:$F$200,F40)>1),"⚠ DUPLICADO","")))
A41: =IF(B41="","",COUNTA($B$12:B41)) -> 30 | B41: 46227 | C41: Serralharia | D41: Trabalhos de serralharia + transporte | E41: Serralheiro | G41: =IF(B41="","","FAT-"&TEXT(COUNTA($B$12:B41),"000")) -> FAT-030 | H41: Despesa | I41: 360000 | J41: Transferência Express | L41: =IF(B41="","",IF(AND(F41<>"",COUNTIF($F$12:$F$200,F41)>1),"⚠ FATURA DUPLICADA",IF(AND(E41<>"",F41<>"",COUNTIFS($E$12:$E$200,E41,$F$12:$F$200,F41)>1),"⚠ DUPLICADO","")))
A42: =IF(B42="","",COUNTA($B$12:B42)) -> 31 | B42: 46227 | C42: Transporte s/ Fatura | D42: Táxi serralheiro | E42: Táxi | G42: =IF(B42="","","FAT-"&TEXT(COUNTA($B$12:B42),"000")) -> FAT-031 | H42: Despesa | I42: 5000 | J42: Transferência Express | L42: =IF(B42="","",IF(AND(F42<>"",COUNTIF($F$12:$F$200,F42)>1),"⚠ FATURA DUPLICADA",IF(AND(E42<>"",F42<>"",COUNTIFS($E$12:$E$200,E42,$F$12:$F$200,F42)>1),"⚠ DUPLICADO","")))
A43: =IF(B43="","",COUNTA($B$12:B43)) -> 32 | B43: 46227 | C43: Equipamentos | D43: Manutenção do gerador | E43: Técnico Gerador | G43: =IF(B43="","","FAT-"&TEXT(COUNTA($B$12:B43),"000")) -> FAT-032 | H43: Despesa | I43: 90000 | J43: Transferência Express | L43: =IF(B43="","",IF(AND(F43<>"",COUNTIF($F$12:$F$200,F43)>1),"⚠ FATURA DUPLICADA",IF(AND(E43<>"",F43<>"",COUNTIFS($E$12:$E$200,E43,$F$12:$F$200,F43)>1),"⚠ DUPLICADO","")))
A44: =IF(B44="","",COUNTA($B$12:B44)) -> 33 | B44: 46228 | C44: Outras Despesas | D44: 20m rede para sombra | G44: =IF(B44="","","FAT-"&TEXT(COUNTA($B$12:B44),"000")) -> FAT-033 | H44: Despesa | I44: 50000 | L44: =IF(B44="","",IF(AND(F44<>"",COUNTIF($F$12:$F$200,F44)>1),"⚠ FATURA DUPLICADA",IF(AND(E44<>"",F44<>"",COUNTIFS($E$12:$E$200,E44,$F$12:$F$200,F44)>1),"⚠ DUPLICADO","")))
A45: =IF(B45="","",COUNTA($B$12:B45)) -> 34 | B45: 46228 | C45: Pintura Exterior | D45: Tintas para decoração | E45: Novo Ango P.S.E. | F45: 1038 | G45: =IF(B45="","","FAT-"&TEXT(COUNTA($B$12:B45),"000")) -> FAT-034 | H45: Despesa | I45: 86000 | J45: Transferência Express | L45: =IF(B45="","",IF(AND(F45<>"",COUNTIF($F$12:$F$200,F45)>1),"⚠ FATURA DUPLICADA",IF(AND(E45<>"",F45<>"",COUNTIFS($E$12:$E$200,E45,$F$12:$F$200,F45)>1),"⚠ DUPLICADO","")))
A46: =IF(B46="","",COUNTA($B$12:B46)) -> 35 | B46: 46228 | C46: Pintura Exterior | D46: Tinta para decoração | E46: Marpeluza | F46: 73 | G46: =IF(B46="","","FAT-"&TEXT(COUNTA($B$12:B46),"000")) -> FAT-035 | H46: Despesa | I46: 14000 | J46: Transferência Express | L46: =IF(B46="","",IF(AND(F46<>"",COUNTIF($F$12:$F$200,F46)>1),"⚠ FATURA DUPLICADA",IF(AND(E46<>"",F46<>"",COUNTIFS($E$12:$E$200,E46,$F$12:$F$200,F46)>1),"⚠ DUPLICADO","")))
A47: =IF(B47="","",COUNTA($B$12:B47)) -> 36 | B47: 46229 | C47: Material Serralharia | D47: Ferros e material serralharia | E47: Primedine - Com. Geral Lda | F47: 29 | G47: =IF(B47="","","FAT-"&TEXT(COUNTA($B$12:B47),"000")) -> FAT-036 | H47: Despesa | I47: 197500 | J47: Cartão Multicaixa | L47: =IF(B47="","",IF(AND(F47<>"",COUNTIF($F$12:$F$200,F47)>1),"⚠ FATURA DUPLICADA",IF(AND(E47<>"",F47<>"",COUNTIFS($E$12:$E$200,E47,$F$12:$F$200,F47)>1),"⚠ DUPLICADO","")))
A48: =IF(B48="","",COUNTA($B$12:B48)) -> 37 | B48: 46231 | C48: Publicidade Exterior | D48: Impressão 2 lonas | E48: Gráfca Capuca | F48: 255 | G48: =IF(B48="","","FAT-"&TEXT(COUNTA($B$12:B48),"000")) -> FAT-037 | H48: Despesa | I48: 154000 | J48: Transferência | L48: =IF(B48="","",IF(AND(F48<>"",COUNTIF($F$12:$F$200,F48)>1),"⚠ FATURA DUPLICADA",IF(AND(E48<>"",F48<>"",COUNTIFS($E$12:$E$200,E48,$F$12:$F$200,F48)>1),"⚠ DUPLICADO","")))
A49: =IF(B49="","",COUNTA($B$12:B49)) -> 38 | B49: 46231 | C49: Pintura Exterior | D49: Material para reparos e pintura | E49: YEHDIH | F49: ´0981 | G49: =IF(B49="","","FAT-"&TEXT(COUNTA($B$12:B49),"000")) -> FAT-038 | H49: Despesa | I49: 27000 | J49: Transferência Express | L49: =IF(B49="","",IF(AND(F49<>"",COUNTIF($F$12:$F$200,F49)>1),"⚠ FATURA DUPLICADA",IF(AND(E49<>"",F49<>"",COUNTIFS($E$12:$E$200,E49,$F$12:$F$200,F49)>1),"⚠ DUPLICADO","")))
A50: =IF(B50="","",COUNTA($B$12:B50)) -> 39 | B50: 46233 | C50: Serralharia | D50: Mão de obra serralheiro (trabalho 1) | E50: Organizações Bom Preço | F50: 95 | G50: =IF(B50="","","FAT-"&TEXT(COUNTA($B$12:B50),"000")) -> FAT-039 | H50: Despesa | I50: 415000 | J50: Transferência | L50: =IF(B50="","",IF(AND(F50<>"",COUNTIF($F$12:$F$200,F50)>1),"⚠ FATURA DUPLICADA",IF(AND(E50<>"",F50<>"",COUNTIFS($E$12:$E$200,E50,$F$12:$F$200,F50)>1),"⚠ DUPLICADO","")))
A51: =IF(B51="","",COUNTA($B$12:B51)) -> 40 | B51: 46234 | C51: Pintura Exterior | D51: Tintas e rolos pintura exterior | E51: Ana De Jesus Albino | G51: =IF(B51="","","FAT-"&TEXT(COUNTA($B$12:B51),"000")) -> FAT-040 | H51: Despesa | I51: 5730 | J51: Transferência Express | L51: =IF(B51="","",IF(AND(F51<>"",COUNTIF($F$12:$F$200,F51)>1),"⚠ FATURA DUPLICADA",IF(AND(E51<>"",F51<>"",COUNTIFS($E$12:$E$200,E51,$F$12:$F$200,F51)>1),"⚠ DUPLICADO","")))
A52: =IF(B52="","",COUNTA($B$12:B52)) -> 41 | B52: 46234 | C52: Material de Escritório | D52: Material de escritório | E52: Kero | F52: FR8326S25932N/23890 | G52: =IF(B52="","","FAT-"&TEXT(COUNTA($B$12:B52),"000")) -> FAT-041 | H52: Despesa | I52: 363313 | J52: Cartão Multicaixa | L52: =IF(B52="","",IF(AND(F52<>"",COUNTIF($F$12:$F$200,F52)>1),"⚠ FATURA DUPLICADA",IF(AND(E52<>"",F52<>"",COUNTIFS($E$12:$E$200,E52,$F$12:$F$200,F52)>1),"⚠ DUPLICADO","")))
A53: =IF(B53="","",COUNTA($B$12:B53)) -> 42 | B53: 46234 | C53: Pintura Exterior | D53: Tintas e material de pintura | E53: Novo Ango P.S.E. | F53: 1039 | G53: =IF(B53="","","FAT-"&TEXT(COUNTA($B$12:B53),"000")) -> FAT-042 | H53: Despesa | I53: 51500 | J53: Transferência | L53: =IF(B53="","",IF(AND(F53<>"",COUNTIF($F$12:$F$200,F53)>1),"⚠ FATURA DUPLICADA",IF(AND(E53<>"",F53<>"",COUNTIFS($E$12:$E$200,E53,$F$12:$F$200,F53)>1),"⚠ DUPLICADO","")))
A54: =IF(B54="","",COUNTA($B$12:B54)) -> 43 | B54: 46234 | C54: Limpeza / Higiene | D54: Material de limpeza | E54: Kero | F54: FR8326S25932N/23892 | G54: =IF(B54="","","FAT-"&TEXT(COUNTA($B$12:B54),"000")) -> FAT-043 | H54: Despesa | I54: 2994 | J54: Cartão Multicaixa | L54: =IF(B54="","",IF(AND(F54<>"",COUNTIF($F$12:$F$200,F54)>1),"⚠ FATURA DUPLICADA",IF(AND(E54<>"",F54<>"",COUNTIFS($E$12:$E$200,E54,$F$12:$F$200,F54)>1),"⚠ DUPLICADO","")))
A55: =IF(B55="","",COUNTA($B$12:B55)) -> 44 | B55: 46235 | C55: Serralharia | D55: Material para serralharia | E55: DKJF | F55: 46 | G55: =IF(B55="","","FAT-"&TEXT(COUNTA($B$12:B55),"000")) -> FAT-044 | H55: Despesa | I55: 263000 | J55: Transferência | L55: =IF(B55="","",IF(AND(F55<>"",COUNTIF($F$12:$F$200,F55)>1),"⚠ FATURA DUPLICADA",IF(AND(E55<>"",F55<>"",COUNTIFS($E$12:$E$200,E55,$F$12:$F$200,F55)>1),"⚠ DUPLICADO","")))
A56: =IF(B56="","",COUNTA($B$12:B56)) -> 45 | B56: 46235 | C56: Material Serralharia | D56: Eléctrodos e discos serralharia | E56: DKJF | F56: 50 | G56: =IF(B56="","","FAT-"&TEXT(COUNTA($B$12:B56),"000")) -> FAT-045 | H56: Despesa | I56: 30000 | J56: Transferência | L56: =IF(B56="","",IF(AND(F56<>"",COUNTIF($F$12:$F$200,F56)>1),"⚠ FATURA DUPLICADA",IF(AND(E56<>"",F56<>"",COUNTIFS($E$12:$E$200,E56,$F$12:$F$200,F56)>1),"⚠ DUPLICADO","")))
A57: =IF(B57="","",COUNTA($B$12:B57)) -> 46 | B57: 46237 | C57: Serralharia | D57: Mão de obra serralheiro (trabalho 2) | E57: Organizações Bom Preço | F57: 93 | G57: =IF(B57="","","FAT-"&TEXT(COUNTA($B$12:B57),"000")) -> FAT-046 | H57: Despesa | I57: 120000 | J57: Transferência | L57: =IF(B57="","",IF(AND(F57<>"",COUNTIF($F$12:$F$200,F57)>1),"⚠ FATURA DUPLICADA",IF(AND(E57<>"",F57<>"",COUNTIFS($E$12:$E$200,E57,$F$12:$F$200,F57)>1),"⚠ DUPLICADO","")))
A58: =IF(B58="","",COUNTA($B$12:B58)) -> 47 | B58: 46238 | C58: Pintura Exterior | D58: Mão de obra de pintura | E58: Pintor | G58: =IF(B58="","","FAT-"&TEXT(COUNTA($B$12:B58),"000")) -> FAT-047 | H58: Despesa | I58: 132000 | J58: Transferência Express | L58: =IF(B58="","",IF(AND(F58<>"",COUNTIF($F$12:$F$200,F58)>1),"⚠ FATURA DUPLICADA",IF(AND(E58<>"",F58<>"",COUNTIFS($E$12:$E$200,E58,$F$12:$F$200,F58)>1),"⚠ DUPLICADO","")))
A59: =IF(B59="","",COUNTA($B$12:B59)) -> 48 | B59: 46238 | C59: Pintura Exterior | D59: 2 baldes tinta branca 20L + táxi | E59: Pintor | G59: =IF(B59="","","FAT-"&TEXT(COUNTA($B$12:B59),"000")) -> FAT-048 | H59: Despesa | I59: 36000 | J59: Transferência Express | L59: =IF(B59="","",IF(AND(F59<>"",COUNTIF($F$12:$F$200,F59)>1),"⚠ FATURA DUPLICADA",IF(AND(E59<>"",F59<>"",COUNTIFS($E$12:$E$200,E59,$F$12:$F$200,F59)>1),"⚠ DUPLICADO","")))
A60: =IF(B60="","",COUNTA($B$12:B60)) -> 49 | B60: 46238 | C60: Pintura Exterior | D60: Tintas e rolos pintura exterior | E60: Novo Ango P.S.E. | F60: 1040 | G60: =IF(B60="","","FAT-"&TEXT(COUNTA($B$12:B60),"000")) -> FAT-049 | H60: Despesa | I60: 43000 | J60: Transferência Express | L60: =IF(B60="","",IF(AND(F60<>"",COUNTIF($F$12:$F$200,F60)>1),"⚠ FATURA DUPLICADA",IF(AND(E60<>"",F60<>"",COUNTIFS($E$12:$E$200,E60,$F$12:$F$200,F60)>1),"⚠ DUPLICADO","")))
A61: =IF(B61="","",COUNTA($B$12:B61)) -> 50 | B61: 46240 | C61: Panfletos / Publicidade | D61: Impressão 500 panfletos A5 | E61: Gráfica TAMACO | F61: 98D9EF0E92DDC968A0000006900200 | G61: =IF(B61="","","FAT-"&TEXT(COUNTA($B$12:B61),"000")) -> FAT-050 | H61: Despesa | I61: 100000 | J61: Cartão Multicaixa | L61: =IF(B61="","",IF(AND(F61<>"",COUNTIF($F$12:$F$200,F61)>1),"⚠ FATURA DUPLICADA",IF(AND(E61<>"",F61<>"",COUNTIFS($E$12:$E$200,E61,$F$12:$F$200,F61)>1),"⚠ DUPLICADO","")))
A62: =IF(B62="","",COUNTA($B$12:B62)) -> 51 | B62: 46240 | C62: Salários | D62: Pagamento de 2 salários de Julho/26 | E62: Teresa, Adelaide | F62: N/A | G62: =IF(B62="","","FAT-"&TEXT(COUNTA($B$12:B62),"000")) -> FAT-051 | H62: Despesa | I62: 90000 | J62: Dinheiro | K62: Pagamento de 1/2 salário 2 func. limpeza | L62: =IF(B62="","",IF(AND(F62<>"",COUNTIF($F$12:$F$200,F62)>1),"⚠ FATURA DUPLICADA",IF(AND(E62<>"",F62<>"",COUNTIFS($E$12:$E$200,E62,$F$12:$F$200,F62)>1),"⚠ DUPLICADO","")))
A63: =IF(B63="","",COUNTA($B$12:B63)) -> 52 | B63: 46247 | C63: Despesas de Representação | D63: Almoço de negócio para o colégio | E63: Restaurante Convés | F63: FR 22026/28686 | G63: =IF(B63="","","FAT-"&TEXT(COUNTA($B$12:B63),"000")) -> FAT-052 | H63: Despesa | I63: 28000 | J63: Cartão Multicaixa | K63: Almoço de negócio – 13/08/2026 | L63: =IF(B63="","",IF(AND(F63<>"",COUNTIF($F$12:$F$200,F63)>1),"⚠ FATURA DUPLICADA",IF(AND(E63<>"",F63<>"",COUNTIFS($E$12:$E$200,E63,$F$12:$F$200,F63)>1),"⚠ DUPLICADO","")))
A64: =IF(B64="","",COUNTA($B$12:B64)) | G64: =IF(B64="","","FAT-"&TEXT(COUNTA($B$12:B64),"000")) | L64: =IF(B64="","",IF(AND(F64<>"",COUNTIF($F$12:$F$200,F64)>1),"⚠ FATURA DUPLICADA",IF(AND(E64<>"",F64<>"",COUNTIFS($E$12:$E$200,E64,$F$12:$F$200,F64)>1),"⚠ DUPLICADO","")))
A65: =IF(B65="","",COUNTA($B$12:B65)) | G65: =IF(B65="","","FAT-"&TEXT(COUNTA($B$12:B65),"000")) | L65: =IF(B65="","",IF(AND(F65<>"",COUNTIF($F$12:$F$200,F65)>1),"⚠ FATURA DUPLICADA",IF(AND(E65<>"",F65<>"",COUNTIFS($E$12:$E$200,E65,$F$12:$F$200,F65)>1),"⚠ DUPLICADO","")))
A66: =IF(B66="","",COUNTA($B$12:B66)) | G66: =IF(B66="","","FAT-"&TEXT(COUNTA($B$12:B66),"000")) | L66: =IF(B66="","",IF(AND(F66<>"",COUNTIF($F$12:$F$200,F66)>1),"⚠ FATURA DUPLICADA",IF(AND(E66<>"",F66<>"",COUNTIFS($E$12:$E$200,E66,$F$12:$F$200,F66)>1),"⚠ DUPLICADO","")))
A67: =IF(B67="","",COUNTA($B$12:B67)) | G67: =IF(B67="","","FAT-"&TEXT(COUNTA($B$12:B67),"000")) | L67: =IF(B67="","",IF(AND(F67<>"",COUNTIF($F$12:$F$200,F67)>1),"⚠ FATURA DUPLICADA",IF(AND(E67<>"",F67<>"",COUNTIFS($E$12:$E$200,E67,$F$12:$F$200,F67)>1),"⚠ DUPLICADO","")))
A68: =IF(B68="","",COUNTA($B$12:B68)) | G68: =IF(B68="","","FAT-"&TEXT(COUNTA($B$12:B68),"000")) | L68: =IF(B68="","",IF(AND(F68<>"",COUNTIF($F$12:$F$200,F68)>1),"⚠ FATURA DUPLICADA",IF(AND(E68<>"",F68<>"",COUNTIFS($E$12:$E$200,E68,$F$12:$F$200,F68)>1),"⚠ DUPLICADO","")))
A69: =IF(B69="","",COUNTA($B$12:B69)) | G69: =IF(B69="","","FAT-"&TEXT(COUNTA($B$12:B69),"000")) | L69: =IF(B69="","",IF(AND(F69<>"",COUNTIF($F$12:$F$200,F69)>1),"⚠ FATURA DUPLICADA",IF(AND(E69<>"",F69<>"",COUNTIFS($E$12:$E$200,E69,$F$12:$F$200,F69)>1),"⚠ DUPLICADO","")))
A70: =IF(B70="","",COUNTA($B$12:B70)) | G70: =IF(B70="","","FAT-"&TEXT(COUNTA($B$12:B70),"000")) | L70: =IF(B70="","",IF(AND(F70<>"",COUNTIF($F$12:$F$200,F70)>1),"⚠ FATURA DUPLICADA",IF(AND(E70<>"",F70<>"",COUNTIFS($E$12:$E$200,E70,$F$12:$F$200,F70)>1),"⚠ DUPLICADO","")))
A71: =IF(B71="","",COUNTA($B$12:B71)) | G71: =IF(B71="","","FAT-"&TEXT(COUNTA($B$12:B71),"000")) | L71: =IF(B71="","",IF(AND(F71<>"",COUNTIF($F$12:$F$200,F71)>1),"⚠ FATURA DUPLICADA",IF(AND(E71<>"",F71<>"",COUNTIFS($E$12:$E$200,E71,$F$12:$F$200,F71)>1),"⚠ DUPLICADO","")))
A72: =IF(B72="","",COUNTA($B$12:B72)) | G72: =IF(B72="","","FAT-"&TEXT(COUNTA($B$12:B72),"000")) | L72: =IF(B72="","",IF(AND(F72<>"",COUNTIF($F$12:$F$200,F72)>1),"⚠ FATURA DUPLICADA",IF(AND(E72<>"",F72<>"",COUNTIFS($E$12:$E$200,E72,$F$12:$F$200,F72)>1),"⚠ DUPLICADO","")))
A73: =IF(B73="","",COUNTA($B$12:B73)) | G73: =IF(B73="","","FAT-"&TEXT(COUNTA($B$12:B73),"000")) | L73: =IF(B73="","",IF(AND(F73<>"",COUNTIF($F$12:$F$200,F73)>1),"⚠ FATURA DUPLICADA",IF(AND(E73<>"",F73<>"",COUNTIFS($E$12:$E$200,E73,$F$12:$F$200,F73)>1),"⚠ DUPLICADO","")))
A74: =IF(B74="","",COUNTA($B$12:B74)) | G74: =IF(B74="","","FAT-"&TEXT(COUNTA($B$12:B74),"000")) | L74: =IF(B74="","",IF(AND(F74<>"",COUNTIF($F$12:$F$200,F74)>1),"⚠ FATURA DUPLICADA",IF(AND(E74<>"",F74<>"",COUNTIFS($E$12:$E$200,E74,$F$12:$F$200,F74)>1),"⚠ DUPLICADO","")))
A75: =IF(B75="","",COUNTA($B$12:B75)) | G75: =IF(B75="","","FAT-"&TEXT(COUNTA($B$12:B75),"000")) | L75: =IF(B75="","",IF(AND(F75<>"",COUNTIF($F$12:$F$200,F75)>1),"⚠ FATURA DUPLICADA",IF(AND(E75<>"",F75<>"",COUNTIFS($E$12:$E$200,E75,$F$12:$F$200,F75)>1),"⚠ DUPLICADO","")))
... A200: =IF(B200="","",COUNTA($B$12:B200)) | G200: =IF(B200="","","FAT-"&TEXT(COUNTA($B$12:B200),"000")) | L200: =IF(B200="","",IF(AND(F200<>"",COUNTIF($F$12:$F$200,F200)>1),"⚠ FATURA DUPLICADA",IF(AND(E200<>"",F200<>"",COUNTIFS($E$12:$E$200,E200,$F$12:$F$200,F200)>1),"⚠ DUPLICADO","")))

Sheet Arquivos Digitais
A1: GESTÃO DE ARQUIVOS DIGITAIS – DOCUMENTOS DE ARRANQUE / EMPRÉSTIMOS
A2: École Consulaire du Congo (Brazzaville) de Luanda • Ligado aos Nº Internos (FAT-xxx) da planilha Lançamentos
A3: Convenção de nome de ficheiro: FAT-XXX_Categoria_Fornecedor_AAAA-MM-DD.pdf | Amarelo = preencher | Verde = ligado / calculado
A5: RESUMO DO ARQUIVO DIGITAL
A6: Total documentos registados | B6: =COUNTA(A12:A100) -> 54
A7: Com ficheiro digital (Sim) | B7: =COUNTIF(G12:G100,"Sim") -> 1
A8: Sem ficheiro digital (Não / pendente) | B8: =COUNTIF(G12:G100,"Não")+COUNTIF(G12:G100,"Pendente") -> 51
A9: Local principal do arquivo | B9: Google Drive / Pasta partilhada da escola
A10: Instruções: 1) Preencha o Nº Interno (ex: FAT-001) — os dados da despesa/entrada são puxados automaticamente. 2) Indique se existe ficheiro digital, o nome do ficheiro e o link/caminho. 3) Use a convenção de nome para organizar as pastas no Drive/PC.
A11: Nº Interno | B11: Data Doc. | C11: Categoria | D11: Descrição | E11: Fornecedor | F11: Nº Fatura Forn. | G11: Ficheiro Digital? | H11: Nome do Ficheiro | I11: Tipo Ficheiro | J11: Link / Caminho | K11: Data Arquivo | L11: Observações
A12: FAT-001 | B12: =IF(A12="","",IFERROR(INDEX(Lançamentos!B:B,MATCH(A12,Lançamentos!G:G,0)),"—")) -> 46187 | C12: =IF(A12="","",IFERROR(INDEX(Lançamentos!C:C,MATCH(A12,Lançamentos!G:G,0)),"—")) -> Empréstimo Sócio | D12: =IF(A12="","",IFERROR(INDEX(Lançamentos!D:D,MATCH(A12,Lançamentos!G:G,0)),"—")) -> Entrada de capital do sócio (total das despesas de arranque) | E12: =IF(A12="","",IFERROR(INDEX(Lançamentos!E:E,MATCH(A12,Lançamentos!G:G,0)),"—")) -> 0 | F12: =IF(A12="","",IFERROR(INDEX(Lançamentos!F:F,MATCH(A12,Lançamentos!G:G,0)),"—")) -> 0 | G12: Sim | H12: =IF(A12="","",A12&"_"&IFERROR(SUBSTITUTE(INDEX(Lançamentos!C:C,MATCH(A12,Lançamentos!G:G,0))," ","-"),"")&"_"&TEXT(IFERROR(INDEX(Lançamentos!B:B,MATCH(A12,Lançamentos!G:G,0)),""),"YYYY-MM-DD")&".pdf") -> FAT-001_Empréstimo-Sócio_2026-06-14.pdf | I12: PDF
A13: FAT-002 | B13: =IF(A13="","",IFERROR(INDEX(Lançamentos!B:B,MATCH(A13,Lançamentos!G:G,0)),"—")) -> 46187 | C13: =IF(A13="","",IFERROR(INDEX(Lançamentos!C:C,MATCH(A13,Lançamentos!G:G,0)),"—")) -> Pintura Exterior | D13: =IF(A13="","",IFERROR(INDEX(Lançamentos!D:D,MATCH(A13,Lançamentos!G:G,0)),"—")) -> Tinta para pintura exterior | E13: =IF(A13="","",IFERROR(INDEX(Lançamentos!E:E,MATCH(A13,Lançamentos!G:G,0)),"—")) -> Achour - Comércio Geral | F13: =IF(A13="","",IFERROR(INDEX(Lançamentos!F:F,MATCH(A13,Lançamentos!G:G,0)),"—")) -> 829 | G13: Pendente | H13: =IF(A13="","",A13&"_"&IFERROR(SUBSTITUTE(INDEX(Lançamentos!C:C,MATCH(A13,Lançamentos!G:G,0))," ","-"),"")&"_"&TEXT(IFERROR(INDEX(Lançamentos!B:B,MATCH(A13,Lançamentos!G:G,0)),""),"YYYY-MM-DD")&".pdf") -> FAT-002_Pintura-Exterior_2026-06-14.pdf
A14: FAT-003 | B14: =IF(A14="","",IFERROR(INDEX(Lançamentos!B:B,MATCH(A14,Lançamentos!G:G,0)),"—")) -> 46198 | C14: =IF(A14="","",IFERROR(INDEX(Lançamentos!C:C,MATCH(A14,Lançamentos!G:G,0)),"—")) -> Internet / Telefone | D14: =IF(A14="","",IFERROR(INDEX(Lançamentos!D:D,MATCH(A14,Lançamentos!G:G,0)),"—")) -> Telemóvel secretaria | E14: =IF(A14="","",IFERROR(INDEX(Lançamentos!E:E,MATCH(A14,Lançamentos!G:G,0)),"—")) -> Mobismart | F14: =IF(A14="","",IFERROR(INDEX(Lançamentos!F:F,MATCH(A14,Lançamentos!G:G,0)),"—")) -> ´202606251721242870014 | G14: Pendente | H14: =IF(A14="","",A14&"_"&IFERROR(SUBSTITUTE(INDEX(Lançamentos!C:C,MATCH(A14,Lançamentos!G:G,0))," ","-"),"")&"_"&TEXT(IFERROR(INDEX(Lançamentos!B:B,MATCH(A14,Lançamentos!G:G,0)),""),"YYYY-MM-DD")&".pdf") -> FAT-003_Internet-/-Telefone_2026-06-25.pdf
A15: FAT-004 | B15: =IF(A15="","",IFERROR(INDEX(Lançamentos!B:B,MATCH(A15,Lançamentos!G:G,0)),"—")) -> 46198 | C15: =IF(A15="","",IFERROR(INDEX(Lançamentos!C:C,MATCH(A15,Lançamentos!G:G,0)),"—")) -> Internet / Telefone | D15: =IF(A15="","",IFERROR(INDEX(Lançamentos!D:D,MATCH(A15,Lançamentos!G:G,0)),"—")) -> Telemóvel direcção pedagógica | E15: =IF(A15="","",IFERROR(INDEX(Lançamentos!E:E,MATCH(A15,Lançamentos!G:G,0)),"—")) -> Mobismart | F15: =IF(A15="","",IFERROR(INDEX(Lançamentos!F:F,MATCH(A15,Lançamentos!G:G,0)),"—")) -> ´202606251717116930013 | G15: Pendente | H15: =IF(A15="","",A15&"_"&IFERROR(SUBSTITUTE(INDEX(Lançamentos!C:C,MATCH(A15,Lançamentos!G:G,0))," ","-"),"")&"_"&TEXT(IFERROR(INDEX(Lançamentos!B:B,MATCH(A15,Lançamentos!G:G,0)),""),"YYYY-MM-DD")&".pdf") -> FAT-004_Internet-/-Telefone_2026-06-25.pdf
A16: FAT-005 | B16: =IF(A16="","",IFERROR(INDEX(Lançamentos!B:B,MATCH(A16,Lançamentos!G:G,0)),"—")) -> 46198 | C16: =IF(A16="","",IFERROR(INDEX(Lançamentos!C:C,MATCH(A16,Lançamentos!G:G,0)),"—")) -> Internet / Telefone | D16: =IF(A16="","",IFERROR(INDEX(Lançamentos!D:D,MATCH(A16,Lançamentos!G:G,0)),"—")) -> Cartão SIM 945402542 | E16: =IF(A16="","",IFERROR(INDEX(Lançamentos!E:E,MATCH(A16,Lançamentos!G:G,0)),"—")) -> Unitel | F16: =IF(A16="","",IFERROR(INDEX(Lançamentos!F:F,MATCH(A16,Lançamentos!G:G,0)),"—")) -> FR4426S42818N/174541 | G16: Pendente | H16: =IF(A16="","",A16&"_"&IFERROR(SUBSTITUTE(INDEX(Lançamentos!C:C,MATCH(A16,Lançamentos!G:G,0))," ","-"),"")&"_"&TEXT(IFERROR(INDEX(Lançamentos!B:B,MATCH(A16,Lançamentos!G:G,0)),""),"YYYY-MM-DD")&".pdf") -> FAT-005_Internet-/-Telefone_2026-06-25.pdf
A17: FAT-006 | B17: =IF(A17="","",IFERROR(INDEX(Lançamentos!B:B,MATCH(A17,Lançamentos!G:G,0)),"—")) -> 46198 | C17: =IF(A17="","",IFERROR(INDEX(Lançamentos!C:C,MATCH(A17,Lançamentos!G:G,0)),"—")) -> Internet / Telefone | D17: =IF(A17="","",IFERROR(INDEX(Lançamentos!D:D,MATCH(A17,Lançamentos!G:G,0)),"—")) -> Cartões SIM (3 números) | E17: =IF(A17="","",IFERROR(INDEX(Lançamentos!E:E,MATCH(A17,Lançamentos!G:G,0)),"—")) -> Unitel | F17: =IF(A17="","",IFERROR(INDEX(Lançamentos!F:F,MATCH(A17,Lançamentos!G:G,0)),"—")) -> FR4426S42818N/174538 | G17: Pendente | H17: =IF(A17="","",A17&"_"&IFERROR(SUBSTITUTE(INDEX(Lançamentos!C:C,MATCH(A17,Lançamentos!G:G,0))," ","-"),"")&"_"&TEXT(IFERROR(INDEX(Lançamentos!B:B,MATCH(A17,Lançamentos!G:G,0)),""),"YYYY-MM-DD")&".pdf") -> FAT-006_Internet-/-Telefone_2026-06-25.pdf
A18: FAT-007 | B18: =IF(A18="","",IFERROR(INDEX(Lançamentos!B:B,MATCH(A18,Lançamentos!G:G,0)),"—")) -> 46198 | C18: =IF(A18="","",IFERROR(INDEX(Lançamentos!C:C,MATCH(A18,Lançamentos!G:G,0)),"—")) -> Material de Escritório | D18: =IF(A18="","",IFERROR(INDEX(Lançamentos!D:D,MATCH(A18,Lançamentos!G:G,0)),"—")) -> Material de escritório | E18: =IF(A18="","",IFERROR(INDEX(Lançamentos!E:E,MATCH(A18,Lançamentos!G:G,0)),"—")) -> KERO | F18: =IF(A18="","",IFERROR(INDEX(Lançamentos!F:F,MATCH(A18,Lançamentos!G:G,0)),"—")) -> FR8326S25915N/6523 | G18: Pendente | H18: =IF(A18="","",A18&"_"&IFERROR(SUBSTITUTE(INDEX(Lançamentos!C:C,MATCH(A18,Lançamentos!G:G,0))," ","-"),"")&"_"&TEXT(IFERROR(INDEX(Lançamentos!B:B,MATCH(A18,Lançamentos!G:G,0)),""),"YYYY-MM-DD")&".pdf") -> FAT-007_Material-de-Escritório_2026-06-25.pdf
A19: FAT-008 | B19: =IF(A19="","",IFERROR(INDEX(Lançamentos!B:B,MATCH(A19,Lançamentos!G:G,0)),"—")) -> 46199 | C19: =IF(A19="","",IFERROR(INDEX(Lançamentos!C:C,MATCH(A19,Lançamentos!G:G,0)),"—")) -> Equipamentos | D19: =IF(A19="","",IFERROR(INDEX(Lançamentos!D:D,MATCH(A19,Lançamentos!G:G,0)),"—")) -> 4 tinteiros HP Officejet Pro 7740 | E19: =IF(A19="","",IFERROR(INDEX(Lançamentos!E:E,MATCH(A19,Lançamentos!G:G,0)),"—")) -> NCR | F19: =IF(A19="","",IFERROR(INDEX(Lançamentos!F:F,MATCH(A19,Lançamentos!G:G,0)),"—")) -> FR4726S809N/35071 | G19: Pendente | H19: =IF(A19="","",A19&"_"&IFERROR(SUBSTITUTE(INDEX(Lançamentos!C:C,MATCH(A19,Lançamentos!G:G,0))," ","-"),"")&"_"&TEXT(IFERROR(INDEX(Lançamentos!B:B,MATCH(A19,Lançamentos!G:G,0)),""),"YYYY-MM-DD")&".pdf") -> FAT-008_Equipamentos_2026-06-26.pdf
A20: FAT-009 | B20: =IF(A20="","",IFERROR(INDEX(Lançamentos!B:B,MATCH(A20,Lançamentos!G:G,0)),"—")) -> 46199 | C20: =IF(A20="","",IFERROR(INDEX(Lançamentos!C:C,MATCH(A20,Lançamentos!G:G,0)),"—")) -> Outras Despesas | D20: =IF(A20="","",IFERROR(INDEX(Lançamentos!D:D,MATCH(A20,Lançamentos!G:G,0)),"—")) -> 2 fechaduras | E20: =IF(A20="","",IFERROR(INDEX(Lançamentos!E:E,MATCH(A20,Lançamentos!G:G,0)),"—")) -> Sahal Trading - Imp. & Exp. | F20: =IF(A20="","",IFERROR(INDEX(Lançamentos!F:F,MATCH(A20,Lançamentos!G:G,0)),"—")) -> RTJ2026/1157 | G20: Pendente | H20: =IF(A20="","",A20&"_"&IFERROR(SUBSTITUTE(INDEX(Lançamentos!C:C,MATCH(A20,Lançamentos!G:G,0))," ","-"),"")&"_"&TEXT(IFERROR(INDEX(Lançamentos!B:B,MATCH(A20,Lançamentos!G:G,0)),""),"YYYY-MM-DD")&".pdf") -> FAT-009_Outras-Despesas_2026-06-26.pdf
A21: FAT-010 | B21: =IF(A21="","",IFERROR(INDEX(Lançamentos!B:B,MATCH(A21,Lançamentos!G:G,0)),"—")) -> 46204 | C21: =IF(A21="","",IFERROR(INDEX(Lançamentos!C:C,MATCH(A21,Lançamentos!G:G,0)),"—")) -> Pintura Exterior | D21: =IF(A21="","",IFERROR(INDEX(Lançamentos!D:D,MATCH(A21,Lançamentos!G:G,0)),"—")) -> Tintas exterior e material construção | E21: =IF(A21="","",IFERROR(INDEX(Lançamentos!E:E,MATCH(A21,Lançamentos!G:G,0)),"—")) -> Comércio Geral - Imp. & Exp. | F21: =IF(A21="","",IFERROR(INDEX(Lançamentos!F:F,MATCH(A21,Lançamentos!G:G,0)),"—")) -> 1083 | G21: Pendente | H21: =IF(A21="","",A21&"_"&IFERROR(SUBSTITUTE(INDEX(Lançamentos!C:C,MATCH(A21,Lançamentos!G:G,0))," ","-"),"")&"_"&TEXT(IFERROR(INDEX(Lançamentos!B:B,MATCH(A21,Lançamentos!G:G,0)),""),"YYYY-MM-DD")&".pdf") -> FAT-010_Pintura-Exterior_2026-07-01.pdf
A22: FAT-011 | B22: =IF(A22="","",IFERROR(INDEX(Lançamentos!B:B,MATCH(A22,Lançamentos!G:G,0)),"—")) -> 46206 | C22: =IF(A22="","",IFERROR(INDEX(Lançamentos!C:C,MATCH(A22,Lançamentos!G:G,0)),"—")) -> Outras Despesas | D22: =IF(A22="","",IFERROR(INDEX(Lançamentos!D:D,MATCH(A22,Lançamentos!G:G,0)),"—")) -> Estuque e lixas | E22: =IF(A22="","",IFERROR(INDEX(Lançamentos!E:E,MATCH(A22,Lançamentos!G:G,0)),"—")) -> M.N.A. SD. RAHMA | F22: =IF(A22="","",IFERROR(INDEX(Lançamentos!F:F,MATCH(A22,Lançamentos!G:G,0)),"—")) -> 0 | G22: Pendente | H22: =IF(A22="","",A22&"_"&IFERROR(SUBSTITUTE(INDEX(Lançamentos!C:C,MATCH(A22,Lançamentos!G:G,0))," ","-"),"")&"_"&TEXT(IFERROR(INDEX(Lançamentos!B:B,MATCH(A22,Lançamentos!G:G,0)),""),"YYYY-MM-DD")&".pdf") -> FAT-011_Outras-Despesas_2026-07-03.pdf
A23: FAT-012 | B23: =IF(A23="","",IFERROR(INDEX(Lançamentos!B:B,MATCH(A23,Lançamentos!G:G,0)),"—")) -> 46211 | C23: =IF(A23="","",IFERROR(INDEX(Lançamentos!C:C,MATCH(A23,Lançamentos!G:G,0)),"—")) -> Pintura Exterior | D23: =IF(A23="","",IFERROR(INDEX(Lançamentos!D:D,MATCH(A23,Lançamentos!G:G,0)),"—")) -> Tintas e material de pintura | E23: =IF(A23="","",IFERROR(INDEX(Lançamentos!E:E,MATCH(A23,Lançamentos!G:G,0)),"—")) -> Achour - Comércio Geral | F23: =IF(A23="","",IFERROR(INDEX(Lançamentos!F:F,MATCH(A23,Lançamentos!G:G,0)),"—")) -> 805 | G23: Pendente | H23: =IF(A23="","",A23&"_"&IFERROR(SUBSTITUTE(INDEX(Lançamentos!C:C,MATCH(A23,Lançamentos!G:G,0))," ","-"),"")&"_"&TEXT(IFERROR(INDEX(Lançamentos!B:B,MATCH(A23,Lançamentos!G:G,0)),""),"YYYY-MM-DD")&".pdf") -> FAT-012_Pintura-Exterior_2026-07-08.pdf
A24: FAT-013 | B24: =IF(A24="","",IFERROR(INDEX(Lançamentos!B:B,MATCH(A24,Lançamentos!G:G,0)),"—")) -> 46211 | C24: =IF(A24="","",IFERROR(INDEX(Lançamentos!C:C,MATCH(A24,Lançamentos!G:G,0)),"—")) -> Publicidade Exterior | D24: =IF(A24="","",IFERROR(INDEX(Lançamentos!D:D,MATCH(A24,Lançamentos!G:G,0)),"—")) -> Impressão lona pesada 300x900 | E24: =IF(A24="","",IFERROR(INDEX(Lançamentos!E:E,MATCH(A24,Lançamentos!G:G,0)),"—")) -> Gráfica TAMACO | F24: =IF(A24="","",IFERROR(INDEX(Lançamentos!F:F,MATCH(A24,Lançamentos!G:G,0)),"—")) -> AFA7F84768594FCA | G24: Pendente | H24: =IF(A24="","",A24&"_"&IFERROR(SUBSTITUTE(INDEX(Lançamentos!C:C,MATCH(A24,Lançamentos!G:G,0))," ","-"),"")&"_"&TEXT(IFERROR(INDEX(Lançamentos!B:B,MATCH(A24,Lançamentos!G:G,0)),""),"YYYY-MM-DD")&".pdf") -> FAT-013_Publicidade-Exterior_2026-07-08.pdf
... A63: FAT-052 | B63: =IF(A63="","",IFERROR(INDEX(Lançamentos!B:B,MATCH(A63,Lançamentos!G:G,0)),"—")) -> 46247 | C63: =IF(A63="","",IFERROR(INDEX(Lançamentos!C:C,MATCH(A63,Lançamentos!G:G,0)),"—")) -> Despesas de Representação | D63: =IF(A63="","",IFERROR(INDEX(Lançamentos!D:D,MATCH(A63,Lançamentos!G:G,0)),"—")) -> Almoço de negócio para o colégio | E63: =IF(A63="","",IFERROR(INDEX(Lançamentos!E:E,MATCH(A63,Lançamentos!G:G,0)),"—")) -> Restaurante Convés | F63: =IF(A63="","",IFERROR(INDEX(Lançamentos!F:F,MATCH(A63,Lançamentos!G:G,0)),"—")) -> FR 22026/28686 | G63: Pendente | H63: =IF(A63="","",A63&"_"&IFERROR(SUBSTITUTE(INDEX(Lançamentos!C:C,MATCH(A63,Lançamentos!G:G,0))," ","-"),"")&"_"&TEXT(IFERROR(INDEX(Lançamentos!B:B,MATCH(A63,Lançamentos!G:G,0)),""),"YYYY-MM-DD")&".pdf") -> FAT-052_Despesas-de-Representação_2026-08-13.pdf
A78: CONVENÇÃO DE NOMES E PASTAS RECOMENDADA
A79: Estrutura de pastas sugerida (Google Drive / PC): /Arquivo Digital Escola/ /2026-2027 Arranque/ /01 Emprestimos e Adiantamentos/ /02 Pintura/ /03 Serralharia/ /04 Mao de Obra/ /05 Publicidade/ /06 Material Escritorio/ /07 Salarios/ /08 Transporte/ /09 Compras Mercado/ /10 Outros/ Nome do ficheiro: FAT-001_Pintura-Exterior_2026-07-05.pdf Assim o Nº Interno (FAT-xxx) fica sempre visível no nome do ficheiro e no registo desta planilha.

Sheet Resumo por Categoria
A1: RESUMO POR CATEGORIA DE DESPESA / ENTRADA
A2: Totais calculados automaticamente a partir da planilha Lançamentos
A4: Categoria | B4: Total Entradas (KZ) | C4: Total Despesas (KZ) | D4: Observação
A5: Empréstimo Sócio | B5: =SUMIFS(Lançamentos!I:I,Lançamentos!C:C,A5,Lançamentos!H:H,"Entrada") -> 4988379.9 | C5: =SUMIFS(Lançamentos!I:I,Lançamentos!C:C,A5,Lançamentos!H:H,"Despesa") -> 0
A6: Adiantamento Sócio | B6: =SUMIFS(Lançamentos!I:I,Lançamentos!C:C,A6,Lançamentos!H:H,"Entrada") -> 0 | C6: =SUMIFS(Lançamentos!I:I,Lançamentos!C:C,A6,Lançamentos!H:H,"Despesa") -> 0
A7: Pintura Exterior | B7: =SUMIFS(Lançamentos!I:I,Lançamentos!C:C,A7,Lançamentos!H:H,"Entrada") -> 0 | C7: =SUMIFS(Lançamentos!I:I,Lançamentos!C:C,A7,Lançamentos!H:H,"Despesa") -> 1093730
A8: Pintura Interior | B8: =SUMIFS(Lançamentos!I:I,Lançamentos!C:C,A8,Lançamentos!H:H,"Entrada") -> 0 | C8: =SUMIFS(Lançamentos!I:I,Lançamentos!C:C,A8,Lançamentos!H:H,"Despesa") -> 0
A9: Serralharia | B9: =SUMIFS(Lançamentos!I:I,Lançamentos!C:C,A9,Lançamentos!H:H,"Entrada") -> 0 | C9: =SUMIFS(Lançamentos!I:I,Lançamentos!C:C,A9,Lançamentos!H:H,"Despesa") -> 1208000
A10: Material Serralharia | B10: =SUMIFS(Lançamentos!I:I,Lançamentos!C:C,A10,Lançamentos!H:H,"Entrada") -> 0 | C10: =SUMIFS(Lançamentos!I:I,Lançamentos!C:C,A10,Lançamentos!H:H,"Despesa") -> 592500
A11: Mão de Obra | B11: =SUMIFS(Lançamentos!I:I,Lançamentos!C:C,A11,Lançamentos!H:H,"Entrada") -> 0 | C11: =SUMIFS(Lançamentos!I:I,Lançamentos!C:C,A11,Lançamentos!H:H,"Despesa") -> 45000
A12: Panfletos / Publicidade | B12: =SUMIFS(Lançamentos!I:I,Lançamentos!C:C,A12,Lançamentos!H:H,"Entrada") -> 0 | C12: =SUMIFS(Lançamentos!I:I,Lançamentos!C:C,A12,Lançamentos!H:H,"Despesa") -> 200000
A13: Publicidade Exterior | B13: =SUMIFS(Lançamentos!I:I,Lançamentos!C:C,A13,Lançamentos!H:H,"Entrada") -> 0 | C13: =SUMIFS(Lançamentos!I:I,Lançamentos!C:C,A13,Lançamentos!H:H,"Despesa") -> 285200
A14: Material de Escritório | B14: =SUMIFS(Lançamentos!I:I,Lançamentos!C:C,A14,Lançamentos!H:H,"Entrada") -> 0 | C14: =SUMIFS(Lançamentos!I:I,Lançamentos!C:C,A14,Lançamentos!H:H,"Despesa") -> 380566
A15: Salários | B15: =SUMIFS(Lançamentos!I:I,Lançamentos!C:C,A15,Lançamentos!H:H,"Entrada") -> 0 | C15: =SUMIFS(Lançamentos!I:I,Lançamentos!C:C,A15,Lançamentos!H:H,"Despesa") -> 90000
A16: Uniformes | B16: =SUMIFS(Lançamentos!I:I,Lançamentos!C:C,A16,Lançamentos!H:H,"Entrada") -> 0 | C16: =SUMIFS(Lançamentos!I:I,Lançamentos!C:C,A16,Lançamentos!H:H,"Despesa") -> 0
... A30: Ação Social / Custo com Pessoal | B30: =SUMIFS(Lançamentos!I:I,Lançamentos!C:C,A30,Lançamentos!H:H,"Entrada") -> 0 | C30: =SUMIFS(Lançamentos!I:I,Lançamentos!C:C,A30,Lançamentos!H:H,"Despesa") -> 0
A31: TOTAL GERAL | B31: =SUM(B5:B30) -> 4988379.9 | C31: =SUM(C5:C30) -> 4988379.9
A33: TOTAL A REEMBOLSAR AO SÓCIO (Entradas) | C33: =B31 -> 4988379.9 | D33: KZ

Sheet Lista de Categorias
A1: LISTA DE CATEGORIAS SUGERIDAS
A3: Categoria | B3: Tipo típico
A4: Empréstimo Sócio | B4: Entrada
A5: Adiantamento Sócio | B5: Entrada
A6: Pintura Exterior | B6: Despesa
A7: Pintura Interior | B7: Despesa
A8: Serralharia | B8: Despesa
A9: Material Serralharia | B9: Despesa
A10: Mão de Obra | B10: Despesa
A11: Panfletos / Publicidade | B11: Despesa
A12: Publicidade Exterior | B12: Despesa
A13: Material de Escritório | B13: Despesa
A14: Salários | B14: Despesa
... A29: Ação Social | B29: Despesa
A30: Despesas Confindencias
A32: Pode acrescentar novas categorias na lista suspensa da planilha Lançamentos se necessário.
