Workbook

Sheet Movimentos
A1: BAI Express – Movimentos do Cartão (Cartão 9)
A2: Conta: 5048 08******617 3 | Débito | Válido até 03/30
A4: SALDO INICIAL | B4: 68112.25 | C4: ← Insira aqui o saldo inicial (valor em Kz)
A6: Data | B6: Descrição (Banco) | C6: Descrição Pessoal (Entrada/Saída) | D6: Entrada (Kz) | E6: Saída (Kz) | F6: Saldo (Kz) | G6: Observações
A7: 24-07-2026 | B7: Juros vencidos | C7: Juros vencidos | E7: 9.45 | F7: =$B$4+IF(D7="",0,D7)-IF(E7="",0,E7) -> 68102.8
A8: 24-07-2026 | B8: Imposto s/Juros | C8: Imposto sobre juros | E8: 0.02 | F8: =F7+IF(D8="",0,D8)-IF(E8="",0,E8) -> 68102.78
A9: 24-07-2026 | B9: Comissao_gest_M | C9: Comissão de gestão mensal | E9: 3200 | F9: =F8+IF(D9="",0,D9)-IF(E9="",0,E9) -> 64902.78
A10: 24-07-2026 | B10: IVA sobre comis | C10: IVA sobre comissão | E10: 448 | F10: =F9+IF(D10="",0,D10)-IF(E10="",0,E10) -> 64454.78
A11: 27-07-2026 | B11: Fecho TPA 00004 | C11: Fecho de terminal de pagamento (TPA) | D11: 564000 | F11: =F10+IF(D11="",0,D11)-IF(E11="",0,E11) -> 628454.78 | G11: Matrícula(s)
A12: 27-07-2026 | B12: Comissao-Fecho | C12: Comissão de fecho TPA | E12: 6429.6 | F12: =F11+IF(D12="",0,D12)-IF(E12="",0,E12) -> 622025.18
A13: 27-07-2026 | B13: Fecho TPA 00004 | C13: Fecho de terminal de pagamento (TPA) | D13: 220000 | F13: =F12+IF(D13="",0,D13)-IF(E13="",0,E13) -> 842025.18 | G13: Matrícula(s)
A14: 27-07-2026 | B14: Comissao-Fecho | C14: Comissão de fecho TPA | E14: 2508 | F14: =F13+IF(D14="",0,D14)-IF(E14="",0,E14) -> 839517.18
A15: 30-07-2026 | B15: Transf. pelo NI | C15: Transferência recebida (NI) | D15: 350000 | F15: =F14+IF(D15="",0,D15)-IF(E15="",0,E15) -> 1189517.2 | G15: Matrícula(s)
A16: 31-07-2026 | B16: Comissao_gest_M | C16: Comissão de gestão mensal | E16: 4500 | F16: =F15+IF(D16="",0,D16)-IF(E16="",0,E16) -> 1185017.2
A17: 31-07-2026 | B17: IVA sobre comis | C17: IVA sobre comissão | E17: 630 | F17: =F16+IF(D17="",0,D17)-IF(E17="",0,E17) -> 1184387.2
A18: 31-07-2026 | B18: Comissao Alug T | C18: Comissão aluguer TPA | E18: 10000 | F18: =F17+IF(D18="",0,D18)-IF(E18="",0,E18) -> 1174387.2
A19: 31-07-2026 | B19: IVA Comissao Al | C19: IVA comissão aluguer | E19: 1400 | F19: =F18+IF(D19="",0,D19)-IF(E19="",0,E19) -> 1172987.2
A20: 31-07-2026 | B20: Imposto de Selo | C20: Imposto de selo | E20: 8.05 | F20: =F19+IF(D20="",0,D20)-IF(E20="",0,E20) -> 1172979.1
A21: 31-07-2026 | B21: Juros devedores | C21: Juros devedores | E21: 207.93 | F21: =F20+IF(D21="",0,D21)-IF(E21="",0,E21) -> 1172771.2
A22: 31-07-2026 | B22: Imposto de Selo | C22: Imposto de selo | E22: 0.21 | F22: =F21+IF(D22="",0,D22)-IF(E22="",0,E22) -> 1172771
A23: 02-08-2026 | B23: Transf. pelo NI | C23: Transferência recebida (NI) | D23: 360000 | F23: =F22+IF(D23="",0,D23)-IF(E23="",0,E23) -> 1532771 | G23: Matrícula(s)
A24: 03-08-2026 | B24: TRF KWiK de MAN | C24: Transferência KWiK recebida | D24: 180000 | F24: =F23+IF(D24="",0,D24)-IF(E24="",0,E24) -> 1712771 | G24: Matrícula(s)
A25: 06-08-2026 | B25: Fecho TPA 00004 | C25: Fecho de terminal de pagamento (TPA) | D25: 150000 | F25: =F24+IF(D25="",0,D25)-IF(E25="",0,E25) -> 1862771 | G25: Matrícula(s)
A26: 06-08-2026 | B26: Comissao-Fecho | C26: Comissão de fecho TPA | E26: 1710 | F26: =F25+IF(D26="",0,D26)-IF(E26="",0,E26) -> 1861061
A27: 06-08-2026 | B27: ATM-MCX504808*2 | C27: Levantamento ATM | E27: 46000 | F27: =F26+IF(D27="",0,D27)-IF(E27="",0,E27) -> 1815061
A28: 06-08-2026 | B28: TPA-MCX504808** | C28: Pagamento com cartão | E28: 100000 | F28: =F27+IF(D28="",0,D28)-IF(E28="",0,E28) -> 1715061 | G28: Gráfica Tamaco - panfletos
A29: 07-08-2026 | B29: ATM-MCX504808*2 | C29: Levantamento ATM | E29: 10000 | F29: =F28+IF(D29="",0,D29)-IF(E29="",0,E29) -> 1705061
A30: 08-08-2026 | B30: ATM-MCX504808*3 | C30: Levantamento p/ pagamento em dinheiro | E30: 20000 | F30: =F29+IF(D30="",0,D30)-IF(E30="",0,E30) -> 1685061
A31: 09-08-2026 | B31: TPA-MCX504808** | C31: Pagamento com cartão | E31: 12251 | F31: =F30+IF(D31="",0,D31)-IF(E31="",0,E31) -> 1672810 | G31: Maxi - Produtos de higiene
A32: 09-08-2026 | B32: TPA-MCX504808** | C32: Pagamento com cartão | E32: 162493.43 | F32: =F31+IF(D32="",0,D32)-IF(E32="",0,E32) -> 1510316.6 | G32: Sistec - Cartuchos Impressora
A33: 09-08-2026 | B33: TPA-MCX504808** | C33: Pagamento com cartão | E33: 18000 | F33: =F32+IF(D33="",0,D33)-IF(E33="",0,E33) -> 1492316.6 | G33: Compra saco de gesso e lixas
A34: 09-08-2026 | B34: ATM-MCX504808*2 | C34: Levantamento ATM | E34: 20000 | F34: =F33+IF(D34="",0,D34)-IF(E34="",0,E34) -> 1472316.6
A35: 11-08-2026 | B35: ATM-MCX504808*3 | C35: Levantamento ATM | E35: 50000 | F35: =F34+IF(D35="",0,D35)-IF(E35="",0,E35) -> 1422316.6
A36: 11-08-2026 | B36: TPA-MCX504808** | C36: Pagamento com cartão | E36: 2250 | F36: =F35+IF(D36="",0,D36)-IF(E36="",0,E36) -> 1420066.6 | G36: Compra Rolos p/ multicaixa
A37: 12-08-2026 | B37: Transf. pelo NI | C37: Transferência recebida (NI) | D37: 150000 | F37: =F36+IF(D37="",0,D37)-IF(E37="",0,E37) -> 1570066.6 | G37: Matrícula(s)
A38: 13-08-2026 | B38: Transf. pelo NI | C38: Transferência recebida (NI) | D38: 2000 | F38: =F37+IF(D38="",0,D38)-IF(E38="",0,E38) -> 1572066.6 | G38: Caderno(s) Escolar(s)
A39: 13-08-2026 | B39: Fecho TPA 00004 | C39: Fecho de terminal de pagamento (TPA) | D39: 610000 | F39: =F38+IF(D39="",0,D39)-IF(E39="",0,E39) -> 2182066.6 | G39: Matrícula(s) + 100mil ATL
A40: 13-08-2026 | B40: Comissao-Fecho | C40: Comissão de fecho TPA | E40: 6954 | F40: =F39+IF(D40="",0,D40)-IF(E40="",0,E40) -> 2175112.6
A41: 13-08-2026 | B41: TPA-MCX504808** | C41: Pagamento com cartão | E41: 21198 | F41: =F40+IF(D41="",0,D41)-IF(E41="",0,E41) -> 2153914.6 | G41: Sonangol Combustível Viatura
A42: 14-08-2026 | B42: TPA-MCX504808** | C42: Pagamento com cartão | E42: 28750 | F42: =F41+IF(D42="",0,D42)-IF(E42="",0,E42) -> 2125164.6 | G42: A reembolsar
A43: 14-08-2026 | B43: TPA-MCX504808** | C43: Pagamento com cartão | E43: 2000 | F43: =F42+IF(D43="",0,D43)-IF(E43="",0,E43) -> 2123164.6 | G43: A reembolsar
A44: 17-08-2026 | B44: Serviço Especial | C44: Pagamento com cartão | E44: 34590 | F44: =F43+IF(D44="",0,D44)-IF(E44="",0,E44) -> 2088574.6 | G44: Pagmto ZAP Fibra - internet
A45: 46251 | B45: ATM-MCX504808**3 | C45: Levantamento ATM | E45: 20000 | F45: =F44+IF(D45="",0,D45)-IF(E45="",0,E45) -> 2068574.6
A46: 46251 | B46: TPA-MCX504808** | C46: Pagamento com cartão | E46: 17500 | F46: =F45+IF(D46="",0,D46)-IF(E46="",0,E46) -> 2051074.6 | G46: FNK - Peixe p/ funcionários
A47: 46251 | B47: ATM-MCX504808*3 | C47: Levantamento ATM | E47: 10000 | F47: =F46+IF(D47="",0,D47)-IF(E47="",0,E47) -> 2041074.6
A48: 46251 | B48: TPA-MCX504808** | C48: Pagamento com cartão | E48: 19040 | F48: =F47+IF(D48="",0,D48)-IF(E48="",0,E48) -> 2022034.6 | G48: Kero - Compra funcionários
A49: 46255 | B49: MB-Transf.p/NI | C49: Transferência efectuada | E49: 80000 | F49: =F48+IF(D49="",0,D49)-IF(E49="",0,E49) -> 1942034.6 | G49: Pagamto Curso Intensivo Inês
A50: 46255 | B50: ATM-MCX504808*3 | C50: Levantamento ATM | E50: 60000 | F50: =F49+IF(D50="",0,D50)-IF(E50="",0,E50) -> 1882034.6 | G50: Fundo maneio Evento 50 anos
A51: 46255 | B51: ATM-MCX504808*4 | C51: Levantamento ATM | E51: 60000 | F51: =F50+IF(D51="",0,D51)-IF(E51="",0,E51) -> 1822034.6 | G51: Fundo maneio Evento 50 anos
A52: 46255 | B52: TPA-MCX504808** | C52: Pagamento com cartão | E52: 52500 | F52: =F51+IF(D52="",0,D52)-IF(E52="",0,E52) -> 1769534.6 | G52: CM S22026/18259
A53: 46255 | B53: TPA-MCX504808** | C53: Pagamento com cartão | E53: 31100 | F53: =F52+IF(D53="",0,D53)-IF(E53="",0,E53) -> 1738434.6 | G53: FRS22026/9376
A54: 46255 | B54: MB-Transf.p/NI | C54: Transferência efectuada | E54: 100000 | F54: =F53+IF(D54="",0,D54)-IF(E54="",0,E54) -> 1638434.6 | G54: Compras Evento 50 anos
A55: 46255 | B55: MB-Transf.p/NI | C55: Transferência efectuada | E55: 20000 | F55: =F54+IF(D55="",0,D55)-IF(E55="",0,E55) -> 1618434.6 | G55: Compras Evento 50 anos
A56: 46255 | B56: MB-Transf.p/NI | C56: Transferência efectuada | E56: 200000 | F56: =F55+IF(D56="",0,D56)-IF(E56="",0,E56) -> 1418434.6 | G56: Compras Evento 50 anos
A57: 46255 | B57: MB-Transf.p/NI | C57: Transferência efectuada | E57: 135000 | F57: =F56+IF(D57="",0,D57)-IF(E57="",0,E57) -> 1283434.6 | G57: Compras Evento 50 anos
A58: 46255 | B58: MB-Transf.p/NI | C58: Transferência efectuada | E58: 59400 | F58: =F57+IF(D58="",0,D58)-IF(E58="",0,E58) -> 1224034.6 | G58: Compras Evento 50 anos
F59: =F58+IF(D59="",0,D59)-IF(E59="",0,E59) -> 1224034.6
F60: =F59+IF(D60="",0,D60)-IF(E60="",0,E60) -> 1224034.6
F61: =F60+IF(D61="",0,D61)-IF(E61="",0,E61) -> 1224034.6
F62: =F61+IF(D62="",0,D62)-IF(E62="",0,E62) -> 1224034.6
F63: =F62+IF(D63="",0,D63)-IF(E63="",0,E63) -> 1224034.6
F64: =F63+IF(D64="",0,D64)-IF(E64="",0,E64) -> 1224034.6
F65: =F64+IF(D65="",0,D65)-IF(E65="",0,E65) -> 1224034.6
F66: =F65+IF(D66="",0,D66)-IF(E66="",0,E66) -> 1224034.6
F67: =F66+IF(D67="",0,D67)-IF(E67="",0,E67) -> 1224034.6
F68: =F67+IF(D68="",0,D68)-IF(E68="",0,E68) -> 1224034.6
F69: =F68+IF(D69="",0,D69)-IF(E69="",0,E69) -> 1224034.6
F70: =F69+IF(D70="",0,D70)-IF(E70="",0,E70) -> 1224034.6
A72: TOTAIS | D72: =SUM(D7:D70) -> 2586000 | E72: =SUM(E7:E70) -> 1430077.7 | F72: =F70 -> 1224034.6
A74: Nota: Células a amarelo são campos de input. Preencha a coluna 'Descrição Pessoal' e 'Observações'. O saldo é calculado automaticamente. Adicione novas linhas nas células amarelas abaixo dos movimentos existentes.

Sheet Arquivo Faturas Cartão
A1: ARQUIVO DE FATURAS – PAGAMENTOS CARTÃO BAI EXPRESS (Cartão 9)
A2: École Consulaire du Congo (Brazzaville) de Luanda
A5: RESUMO
A6: Total documentos | B6: =COUNTA(B12:B50) -> 13 | C6: Total valor (KZ) | D6: =SUM(G12:G50) -> 448072.43
A11: Nº Interno | B11: Linha Mov. | C11: Data | D11: Descrição (Banco) | E11: Descrição / Detalhe | F11: Fornecedor | G11: Valor (KZ) | H11: Nº Fatura Fornecedor | I11: Observações
A12: =IF(B12="","","CX-"&TEXT(COUNTA($B$12:B12),"000")) -> CX-001 | B12: 28 | C12: =IF(B12="","",INDEX(Movimentos!A:A,B12)) -> 06-08-2026 | D12: =IF(B12="","",INDEX(Movimentos!B:B,B12)) -> TPA-MCX504808** | E12: =IF(B12="","",IF(INDEX(Movimentos!G:G,B12)="",INDEX(Movimentos!C:C,B12),INDEX(Movimentos!G:G,B12))) -> Gráfica Tamaco - panfletos | F12: Gráfica TAMACO | G12: =IF(B12="","",INDEX(Movimentos!E:E,B12)) -> 100000 | I12: =IF(B12="","",INDEX(Movimentos!G:G,B12)) -> Gráfica Tamaco - panfletos
A13: =IF(B13="","","CX-"&TEXT(COUNTA($B$12:B13),"000")) -> CX-002 | B13: 31 | C13: =IF(B13="","",INDEX(Movimentos!A:A,B13)) -> 09-08-2026 | D13: =IF(B13="","",INDEX(Movimentos!B:B,B13)) -> TPA-MCX504808** | E13: =IF(B13="","",IF(INDEX(Movimentos!G:G,B13)="",INDEX(Movimentos!C:C,B13),INDEX(Movimentos!G:G,B13))) -> Maxi - Produtos de higiene | F13: Maxi | G13: =IF(B13="","",INDEX(Movimentos!E:E,B13)) -> 12251 | H13: FR2626S2474N/39811 | I13: =IF(B13="","",INDEX(Movimentos!G:G,B13)) -> Maxi - Produtos de higiene
A14: =IF(B14="","","CX-"&TEXT(COUNTA($B$12:B14),"000")) -> CX-003 | B14: 32 | C14: =IF(B14="","",INDEX(Movimentos!A:A,B14)) -> 09-08-2026 | D14: =IF(B14="","",INDEX(Movimentos!B:B,B14)) -> TPA-MCX504808** | E14: =IF(B14="","",IF(INDEX(Movimentos!G:G,B14)="",INDEX(Movimentos!C:C,B14),INDEX(Movimentos!G:G,B14))) -> Sistec - Cartuchos Impressora | F14: Sistec | G14: =IF(B14="","",INDEX(Movimentos!E:E,B14)) -> 162493.43 | H14: FR4726S449N/3811 | I14: =IF(B14="","",INDEX(Movimentos!G:G,B14)) -> Sistec - Cartuchos Impressora
A15: =IF(B15="","","CX-"&TEXT(COUNTA($B$12:B15),"000")) -> CX-004 | B15: 33 | C15: =IF(B15="","",INDEX(Movimentos!A:A,B15)) -> 09-08-2026 | D15: =IF(B15="","",INDEX(Movimentos!B:B,B15)) -> TPA-MCX504808** | E15: =IF(B15="","",IF(INDEX(Movimentos!G:G,B15)="",INDEX(Movimentos!C:C,B15),INDEX(Movimentos!G:G,B15))) -> Compra saco de gesso e lixas | F15: Delicia Quihango | G15: =IF(B15="","",INDEX(Movimentos!E:E,B15)) -> 18000 | H15: 1403 | I15: =IF(B15="","",INDEX(Movimentos!G:G,B15)) -> Compra saco de gesso e lixas
A16: =IF(B16="","","CX-"&TEXT(COUNTA($B$12:B16),"000")) -> CX-005 | B16: 36 | C16: =IF(B16="","",INDEX(Movimentos!A:A,B16)) -> 11-08-2026 | D16: =IF(B16="","",INDEX(Movimentos!B:B,B16)) -> TPA-MCX504808** | E16: =IF(B16="","",IF(INDEX(Movimentos!G:G,B16)="",INDEX(Movimentos!C:C,B16),INDEX(Movimentos!G:G,B16))) -> Compra Rolos p/ multicaixa | F16: Prestige Horeca | G16: =IF(B16="","",INDEX(Movimentos!E:E,B16)) -> 2250 | H16: FR-2M.2026H/1572 | I16: =IF(B16="","",INDEX(Movimentos!G:G,B16)) -> Compra Rolos p/ multicaixa
A17: =IF(B17="","","CX-"&TEXT(COUNTA($B$12:B17),"000")) -> CX-006 | B17: 41 | C17: =IF(B17="","",INDEX(Movimentos!A:A,B17)) -> 13-08-2026 | D17: =IF(B17="","",INDEX(Movimentos!B:B,B17)) -> TPA-MCX504808** | E17: =IF(B17="","",IF(INDEX(Movimentos!G:G,B17)="",INDEX(Movimentos!C:C,B17),INDEX(Movimentos!G:G,B17))) -> Sonangol Combustível Viatura | F17: Sonangol | G17: =IF(B17="","",INDEX(Movimentos!E:E,B17)) -> 21198 | H17: FR0526S50752N/6028 | I17: =IF(B17="","",INDEX(Movimentos!G:G,B17)) -> Sonangol Combustível Viatura
A18: =IF(B18="","","CX-"&TEXT(COUNTA($B$12:B18),"000")) -> CX-007 | B18: 42 | C18: =IF(B18="","",INDEX(Movimentos!A:A,B18)) -> 14-08-2026 | D18: =IF(B18="","",INDEX(Movimentos!B:B,B18)) -> TPA-MCX504808** | E18: =IF(B18="","",IF(INDEX(Movimentos!G:G,B18)="",INDEX(Movimentos!C:C,B18),INDEX(Movimentos!G:G,B18))) -> A reembolsar | G18: =IF(B18="","",INDEX(Movimentos!E:E,B18)) -> 28750 | I18: =IF(B18="","",INDEX(Movimentos!G:G,B18)) -> A reembolsar
A19: =IF(B19="","","CX-"&TEXT(COUNTA($B$12:B19),"000")) -> CX-008 | B19: 43 | C19: =IF(B19="","",INDEX(Movimentos!A:A,B19)) -> 14-08-2026 | D19: =IF(B19="","",INDEX(Movimentos!B:B,B19)) -> TPA-MCX504808** | E19: =IF(B19="","",IF(INDEX(Movimentos!G:G,B19)="",INDEX(Movimentos!C:C,B19),INDEX(Movimentos!G:G,B19))) -> A reembolsar | G19: =IF(B19="","",INDEX(Movimentos!E:E,B19)) -> 2000 | I19: =IF(B19="","",INDEX(Movimentos!G:G,B19)) -> A reembolsar
A20: =IF(B20="","","CX-"&TEXT(COUNTA($B$12:B20),"000")) -> CX-009 | B20: 44 | C20: =IF(B20="","",INDEX(Movimentos!A:A,B20)) -> 17-08-2026 | D20: =IF(B20="","",INDEX(Movimentos!B:B,B20)) -> Serviço Especial | E20: =IF(B20="","",IF(INDEX(Movimentos!G:G,B20)="",INDEX(Movimentos!C:C,B20),INDEX(Movimentos!G:G,B20))) -> Pagmto ZAP Fibra - internet | F20: ZAP Fibra | G20: =IF(B20="","",INDEX(Movimentos!E:E,B20)) -> 34590 | H20: 664 | I20: =IF(B20="","",INDEX(Movimentos!G:G,B20)) -> Pagmto ZAP Fibra - internet
A21: =IF(B21="","","CX-"&TEXT(COUNTA($B$12:B21),"000")) -> CX-010 | B21: 45 | C21: =IF(B21="","",INDEX(Movimentos!A:A,B21)) -> 46251 | D21: =IF(B21="","",INDEX(Movimentos!B:B,B21)) -> ATM-MCX504808**3 | E21: =IF(B21="","",IF(INDEX(Movimentos!G:G,B21)="",INDEX(Movimentos!C:C,B21),INDEX(Movimentos!G:G,B21))) -> Levantamento ATM | G21: =IF(B21="","",INDEX(Movimentos!E:E,B21)) -> 20000 | I21: =IF(B21="","",INDEX(Movimentos!G:G,B21)) -> 0
A22: =IF(B22="","","CX-"&TEXT(COUNTA($B$12:B22),"000")) -> CX-011 | B22: 46 | C22: =IF(B22="","",INDEX(Movimentos!A:A,B22)) -> 46251 | D22: =IF(B22="","",INDEX(Movimentos!B:B,B22)) -> TPA-MCX504808** | E22: =IF(B22="","",IF(INDEX(Movimentos!G:G,B22)="",INDEX(Movimentos!C:C,B22),INDEX(Movimentos!G:G,B22))) -> FNK - Peixe p/ funcionários | G22: =IF(B22="","",INDEX(Movimentos!E:E,B22)) -> 17500 | I22: =IF(B22="","",INDEX(Movimentos!G:G,B22)) -> FNK - Peixe p/ funcionários
A23: =IF(B23="","","CX-"&TEXT(COUNTA($B$12:B23),"000")) -> CX-012 | B23: 47 | C23: =IF(B23="","",INDEX(Movimentos!A:A,B23)) -> 46251 | D23: =IF(B23="","",INDEX(Movimentos!B:B,B23)) -> ATM-MCX504808*3 | E23: =IF(B23="","",IF(INDEX(Movimentos!G:G,B23)="",INDEX(Movimentos!C:C,B23),INDEX(Movimentos!G:G,B23))) -> Levantamento ATM | G23: =IF(B23="","",INDEX(Movimentos!E:E,B23)) -> 10000 | I23: =IF(B23="","",INDEX(Movimentos!G:G,B23)) -> 0
A24: =IF(B24="","","CX-"&TEXT(COUNTA($B$12:B24),"000")) -> CX-013 | B24: 48 | C24: =IF(B24="","",INDEX(Movimentos!A:A,B24)) -> 46251 | D24: =IF(B24="","",INDEX(Movimentos!B:B,B24)) -> TPA-MCX504808** | E24: =IF(B24="","",IF(INDEX(Movimentos!G:G,B24)="",INDEX(Movimentos!C:C,B24),INDEX(Movimentos!G:G,B24))) -> Kero - Compra funcionários | G24: =IF(B24="","",INDEX(Movimentos!E:E,B24)) -> 19040 | I24: =IF(B24="","",INDEX(Movimentos!G:G,B24)) -> Kero - Compra funcionários
A25: =IF(B25="","","CX-"&TEXT(COUNTA($B$12:B25),"000")) | C25: =IF(B25="","",INDEX(Movimentos!A:A,B25)) | D25: =IF(B25="","",INDEX(Movimentos!B:B,B25)) | E25: =IF(B25="","",IF(INDEX(Movimentos!G:G,B25)="",INDEX(Movimentos!C:C,B25),INDEX(Movimentos!G:G,B25))) | G25: =IF(B25="","",INDEX(Movimentos!E:E,B25)) | I25: =IF(B25="","",INDEX(Movimentos!G:G,B25))
A26: =IF(B26="","","CX-"&TEXT(COUNTA($B$12:B26),"000")) | C26: =IF(B26="","",INDEX(Movimentos!A:A,B26)) | D26: =IF(B26="","",INDEX(Movimentos!B:B,B26)) | E26: =IF(B26="","",IF(INDEX(Movimentos!G:G,B26)="",INDEX(Movimentos!C:C,B26),INDEX(Movimentos!G:G,B26))) | G26: =IF(B26="","",INDEX(Movimentos!E:E,B26)) | I26: =IF(B26="","",INDEX(Movimentos!G:G,B26))
A27: =IF(B27="","","CX-"&TEXT(COUNTA($B$12:B27),"000")) | C27: =IF(B27="","",INDEX(Movimentos!A:A,B27)) | D27: =IF(B27="","",INDEX(Movimentos!B:B,B27)) | E27: =IF(B27="","",IF(INDEX(Movimentos!G:G,B27)="",INDEX(Movimentos!C:C,B27),INDEX(Movimentos!G:G,B27))) | G27: =IF(B27="","",INDEX(Movimentos!E:E,B27)) | I27: =IF(B27="","",INDEX(Movimentos!G:G,B27))
A28: =IF(B28="","","CX-"&TEXT(COUNTA($B$12:B28),"000")) | C28: =IF(B28="","",INDEX(Movimentos!A:A,B28)) | D28: =IF(B28="","",INDEX(Movimentos!B:B,B28)) | E28: =IF(B28="","",IF(INDEX(Movimentos!G:G,B28)="",INDEX(Movimentos!C:C,B28),INDEX(Movimentos!G:G,B28))) | G28: =IF(B28="","",INDEX(Movimentos!E:E,B28)) | I28: =IF(B28="","",INDEX(Movimentos!G:G,B28))
A29: =IF(B29="","","CX-"&TEXT(COUNTA($B$12:B29),"000")) | C29: =IF(B29="","",INDEX(Movimentos!A:A,B29)) | D29: =IF(B29="","",INDEX(Movimentos!B:B,B29)) | E29: =IF(B29="","",IF(INDEX(Movimentos!G:G,B29)="",INDEX(Movimentos!C:C,B29),INDEX(Movimentos!G:G,B29))) | G29: =IF(B29="","",INDEX(Movimentos!E:E,B29)) | I29: =IF(B29="","",INDEX(Movimentos!G:G,B29))
A30: =IF(B30="","","CX-"&TEXT(COUNTA($B$12:B30),"000")) | C30: =IF(B30="","",INDEX(Movimentos!A:A,B30)) | D30: =IF(B30="","",INDEX(Movimentos!B:B,B30)) | E30: =IF(B30="","",IF(INDEX(Movimentos!G:G,B30)="",INDEX(Movimentos!C:C,B30),INDEX(Movimentos!G:G,B30))) | G30: =IF(B30="","",INDEX(Movimentos!E:E,B30)) | I30: =IF(B30="","",INDEX(Movimentos!G:G,B30))
A31: =IF(B31="","","CX-"&TEXT(COUNTA($B$12:B31),"000")) | C31: =IF(B31="","",INDEX(Movimentos!A:A,B31)) | D31: =IF(B31="","",INDEX(Movimentos!B:B,B31)) | E31: =IF(B31="","",IF(INDEX(Movimentos!G:G,B31)="",INDEX(Movimentos!C:C,B31),INDEX(Movimentos!G:G,B31))) | G31: =IF(B31="","",INDEX(Movimentos!E:E,B31)) | I31: =IF(B31="","",INDEX(Movimentos!G:G,B31))
A32: =IF(B32="","","CX-"&TEXT(COUNTA($B$12:B32),"000")) | C32: =IF(B32="","",INDEX(Movimentos!A:A,B32)) | D32: =IF(B32="","",INDEX(Movimentos!B:B,B32)) | E32: =IF(B32="","",IF(INDEX(Movimentos!G:G,B32)="",INDEX(Movimentos!C:C,B32),INDEX(Movimentos!G:G,B32))) | G32: =IF(B32="","",INDEX(Movimentos!E:E,B32)) | I32: =IF(B32="","",INDEX(Movimentos!G:G,B32))
A33: =IF(B33="","","CX-"&TEXT(COUNTA($B$12:B33),"000")) | C33: =IF(B33="","",INDEX(Movimentos!A:A,B33)) | D33: =IF(B33="","",INDEX(Movimentos!B:B,B33)) | E33: =IF(B33="","",IF(INDEX(Movimentos!G:G,B33)="",INDEX(Movimentos!C:C,B33),INDEX(Movimentos!G:G,B33))) | G33: =IF(B33="","",INDEX(Movimentos!E:E,B33)) | I33: =IF(B33="","",INDEX(Movimentos!G:G,B33))
A34: =IF(B34="","","CX-"&TEXT(COUNTA($B$12:B34),"000")) | C34: =IF(B34="","",INDEX(Movimentos!A:A,B34)) | D34: =IF(B34="","",INDEX(Movimentos!B:B,B34)) | E34: =IF(B34="","",IF(INDEX(Movimentos!G:G,B34)="",INDEX(Movimentos!C:C,B34),INDEX(Movimentos!G:G,B34))) | G34: =IF(B34="","",INDEX(Movimentos!E:E,B34)) | I34: =IF(B34="","",INDEX(Movimentos!G:G,B34))
A35: =IF(B35="","","CX-"&TEXT(COUNTA($B$12:B35),"000")) | C35: =IF(B35="","",INDEX(Movimentos!A:A,B35)) | D35: =IF(B35="","",INDEX(Movimentos!B:B,B35)) | E35: =IF(B35="","",IF(INDEX(Movimentos!G:G,B35)="",INDEX(Movimentos!C:C,B35),INDEX(Movimentos!G:G,B35))) | G35: =IF(B35="","",INDEX(Movimentos!E:E,B35)) | I35: =IF(B35="","",INDEX(Movimentos!G:G,B35))
A38: INSTRUÇÕES
A39: 1) Na coluna "Linha Mov." indique o número da linha da planilha Movimentos onde está o pagamento TPA/cartão (ex: 28, 31, 32…). 2) Data, Descrição Banco, Detalhe, Valor e Observações são preenchidos automaticamente a partir de Movimentos. 3) Preencha manualmente (amarelo): Fornecedor e Nº Fatura Fornecedor. 4) O Nº Interno (CX-001, CX-002…) gera-se automaticamente — escreva-o na fatura física. 5) Para um novo pagamento: adicione-o primeiro em Movimentos; depois indique o nº da linha aqui. 6) Apenas pagamentos TPA/cartão (não ATM, comissões nem transferências recebidas).

Sheet Fundo de Maneio
A1: FUNDO DE MANEIO – ESCOLA
A2: Cada levantamento ATM cria um bloco. Os pagamentos em dinheiro são descontados desse valor.
A4: LEVANTAMENTOS (ATM)
A5: Data | B5: Valor Levantado (Kz) | C5: Saldo Anterior (Kz) | D5: Já Gasto (Kz) | E5: Saldo Restante (Kz) | F5: Estado
A6: 06-08-2026 | B6: 46000 | C6: 0 | D6: =SUM(C18:C25) -> 46000 | E6: =B6+C6-D6 -> 0 | F6: =IF(E6<=0,"ESGOTADO",IF(D6=0,"Disponível","Em uso")) -> ESGOTADO
A7: 07-08-2026 | B7: 10000 | C7: =MAX(0,E6) -> 0 | D7: =SUM(C29:C36) -> 10000 | E7: =B7+C7-D7 -> 0 | F7: =IF(E7<=0,"ESGOTADO",IF(D7=0,"Disponível","Em uso")) -> ESGOTADO
A8: 08-08-2026 | B8: 20000 | C8: =MAX(0,E7) -> 0 | D8: =SUM(C40:C47) -> 18000 | E8: =B8+C8-D8 -> 2000 | F8: =IF(E8<=0,"ESGOTADO",IF(D8=0,"Disponível","Em uso")) -> Em uso
A9: 09-08-2026 | B9: 20000 | C9: =MAX(0,E8) -> 2000 | D9: =SUM(C51:C58) -> 22000 | E9: =B9+C9-D9 -> 0 | F9: =IF(E9<=0,"ESGOTADO",IF(D9=0,"Disponível","Em uso")) -> ESGOTADO
A10: 11-08-2026 | B10: 50000 | C10: =MAX(0,E9) -> 0 | D10: =SUM(C62:C69) -> 8000 | E10: =B10+C10-D10 -> 42000 | F10: =IF(E10<=0,"ESGOTADO",IF(D10=0,"Disponível","Em uso")) -> Em uso
A11: 17-08-2026 | B11: 20000 | C11: =MAX(0,E10) -> 42000 | D11: =SUM(C73:C80) -> 20000 | E11: =B11+C11-D11 -> 42000 | F11: =IF(E11<=0,"ESGOTADO",IF(D11=0,"Disponível","Em uso")) -> Em uso
A12: 17-08-2026 | B12: 10000 | C12: =MAX(0,E11) -> 42000 | D12: =SUM(C84:C91) -> 28800 | E12: =B12+C12-D12 -> 23200 | F12: =IF(E12<=0,"ESGOTADO",IF(D12=0,"Disponível","Em uso")) -> Em uso
A13: TOTAL | B13: =SUM(B6:B12) -> 176000 | D13: =SUM(D6:D12) -> 152800 | E13: =E12 -> 23200
A15: PAGAMENTOS EM DINHEIRO (descontados de cada levantamento)
A16: Data | B16: Descrição do pagamento | C16: Valor (Kz) | D16: Saldo restante do levantamento | E16: Quem recebeu | F16: Observações
A17: ▶ Levantamento 06-08-2026 — 46 000 Kz
A18: 46240 | B18: Pagamento mão-de-obra pintor | C18: 44000 | D18: =B6-IF(C18="",0,C18) -> 2000 | E18: Pedro
A19: 46240 | B19: Pagamento transporte pintor | C19: 2000 | D19: =D18-IF(C19="",0,C19) -> 0 | E19: Pedro
D20: =D19-IF(C20="",0,C20) -> 0
D21: =D20-IF(C21="",0,C21) -> 0
D22: =D21-IF(C22="",0,C22) -> 0
D23: =D22-IF(C23="",0,C23) -> 0
D24: =D23-IF(C24="",0,C24) -> 0
D25: =D24-IF(C25="",0,C25) -> 0
A26: Total gasto neste levantamento | C26: =SUM(C18:C25) -> 46000
A28: ="▶ Levantamento 07-08-2026 — "&TEXT(B7,"#,##0")&" Kz + ant. "&TEXT(C7,"#,##0")&" = "&TEXT(B7+C7,"#,##0")&" disponíveis" -> ▶ Levantamento 07-08-2026 — 10000,0 Kz + ant. ,0 = 10000,0 disponíveis
A29: 46241 | B29: Transporte funcionário | C29: 2000 | D29: =B7+C7-IF(C29="",0,C29) -> 8000
A30: 46241 | B30: Transporte funcionário | C30: 2000 | D30: =D29-IF(C30="",0,C30) -> 6000
A31: 46241 | B31: Transporte funcionário | C31: 2000 | D31: =D30-IF(C31="",0,C31) -> 4000
A32: 46241 | B32: Transporte funcionário | C32: 4000 | D32: =D31-IF(C32="",0,C32) -> 0
D33: =D32-IF(C33="",0,C33) -> 0
D34: =D33-IF(C34="",0,C34) -> 0
D35: =D34-IF(C35="",0,C35) -> 0
D36: =D35-IF(C36="",0,C36) -> 0
A37: Total gasto neste levantamento | C37: =SUM(C29:C36) -> 10000
A39: ="▶ Levantamento 08-08-2026 — "&TEXT(B8,"#,##0")&" Kz + ant. "&TEXT(C8,"#,##0")&" = "&TEXT(B8+C8,"#,##0")&" disponíveis" -> ▶ Levantamento 08-08-2026 — 20000,0 Kz + ant. ,0 = 20000,0 disponíveis
A40: 46242 | B40: Compra Braçadeiras e fio de para esteiras | C40: 10000 | D40: =B8+C8-IF(C40="",0,C40) -> 10000 | E40: Paulino Nfinda
A41: 46242 | B41: Transporte p/ entrega de panfletos GAMEK | C41: 1000 | D41: =D40-IF(C41="",0,C41) -> 9000 | E41: Francisco Kativa
A42: 46242 | B42: Compra Saco Cimento Cola e transporte | C42: 4000 | D42: =D41-IF(C42="",0,C42) -> 5000 | E42: Pedro
A43: 46242 | B43: Transporte p/ serralheiro | C43: 3000 | D43: =D42-IF(C43="",0,C43) -> 2000 | E43: Paulino Nfinda
D44: =D43-IF(C44="",0,C44) -> 2000
D45: =D44-IF(C45="",0,C45) -> 2000
D46: =D45-IF(C46="",0,C46) -> 2000
D47: =D46-IF(C47="",0,C47) -> 2000
A48: Total gasto neste levantamento | C48: =SUM(C40:C47) -> 18000
A50: ="▶ Levantamento 09-08-2026 — "&TEXT(B9,"#,##0")&" Kz + ant. "&TEXT(C9,"#,##0")&" = "&TEXT(B9+C9,"#,##0")&" disponíveis" -> ▶ Levantamento 09-08-2026 — 20000,0 Kz + ant. 2000,0 = 22000,0 disponíveis
A51: 46243 | B51: Transporte funcionário p/ compra do gesso e etc | C51: 2400 | D51: =B9+C9-IF(C51="",0,C51) -> 19600 | E51: Pedro
C52: 19600 | D52: =D51-IF(C52="",0,C52) -> 0
D53: =D52-IF(C53="",0,C53) -> 0
D54: =D53-IF(C54="",0,C54) -> 0
D55: =D54-IF(C55="",0,C55) -> 0
D56: =D55-IF(C56="",0,C56) -> 0
D57: =D56-IF(C57="",0,C57) -> 0
D58: =D57-IF(C58="",0,C58) -> 0
A59: Total gasto neste levantamento | C59: =SUM(C51:C58) -> 22000
A61: ="▶ Levantamento 11-08-2026 — "&TEXT(B10,"#,##0")&" Kz + ant. "&TEXT(C10,"#,##0")&" = "&TEXT(B10+C10,"#,##0")&" disponíveis" -> ▶ Levantamento 11-08-2026 — 50000,0 Kz + ant. ,0 = 50000,0 disponíveis
A62: 46245 | B62: Transporte p/ deslocação técnico do gerador | C62: 2000 | D62: =B10+C10-IF(C62="",0,C62) -> 48000 | E62: Flávio
A63: 46245 | B63: Adiantamento p/ pintor | C63: 6000 | D63: =D62-IF(C63="",0,C63) -> 42000 | E63: Pedro
D64: =D63-IF(C64="",0,C64) -> 42000
D65: =D64-IF(C65="",0,C65) -> 42000
D66: =D65-IF(C66="",0,C66) -> 42000
D67: =D66-IF(C67="",0,C67) -> 42000
D68: =D67-IF(C68="",0,C68) -> 42000
D69: =D68-IF(C69="",0,C69) -> 42000
A70: Total gasto neste levantamento | C70: =SUM(C62:C69) -> 8000
A72: ="▶ Levantamento 17-08-2026 — "&TEXT(B11,"#,##0")&" Kz + ant. "&TEXT(C11,"#,##0")&" = "&TEXT(B11+C11,"#,##0")&" disponíveis" -> ▶ Levantamento 17-08-2026 — 20000,0 Kz + ant. 42000,0 = 62000,0 disponíveis
A73: 46251 | B73: Fatura 142 - CASA COMERCIAL | C73: 18000 | D73: =B11+C11-IF(C73="",0,C73) -> 44000 | E73: Pedro | F73: Fatura 142
A74: 46251 | B74: Botija de gás | C74: 2000 | D74: =D73-IF(C74="",0,C74) -> 42000 | E74: Francisco Kativa
D75: =D74-IF(C75="",0,C75) -> 42000
D76: =D75-IF(C76="",0,C76) -> 42000
D77: =D76-IF(C77="",0,C77) -> 42000
D78: =D77-IF(C78="",0,C78) -> 42000
D79: =D78-IF(C79="",0,C79) -> 42000
D80: =D79-IF(C80="",0,C80) -> 42000
A81: Total gasto neste levantamento | C81: =SUM(C73:C80) -> 20000
A83: ="▶ Levantamento 17-08-2026 — "&TEXT(B12,"#,##0")&" Kz + ant. "&TEXT(C12,"#,##0")&" = "&TEXT(B12+C12,"#,##0")&" disponíveis" -> ▶ Levantamento 17-08-2026 — 10000,0 Kz + ant. 42000,0 = 52000,0 disponíveis
A84: 46251 | B84: Compra de Saco Arroz | C84: 8750 | D84: =B12+C12-IF(C84="",0,C84) -> 43250 | E84: Francisco Kativa | F84: FR2026/21650
A85: 46251 | B85: Transporte p/ funcionário compras | C85: 1250 | D85: =D84-IF(C85="",0,C85) -> 42000 | E85: Francisco Kativa
A86: 46251 | B86: Compra pão e Sheltox p/ seguranças | C86: 7000 | D86: =D85-IF(C86="",0,C86) -> 35000 | E86: Alberto Capolo
A87: 46251 | B87: Adiantamento p/ pintor | C87: 6000 | D87: =D86-IF(C87="",0,C87) -> 29000 | E87: Pedro
A88: 46254 | B88: Compra 2 pincéis pintura | C88: 1800 | D88: =D87-IF(C88="",0,C88) -> 27200 | E88: Pedro
A89: 46254 | B89: Adiantamento p/ pintor (táxi) | C89: 2000 | D89: =D88-IF(C89="",0,C89) -> 25200 | E89: Pedro
A90: 46255 | B90: Compra esfregona p/ limpeza recinto escolar | C90: 2000 | D90: =D89-IF(C90="",0,C90) -> 23200 | E90: Francisco Kativa
D91: =D90-IF(C91="",0,C91) -> 23200
A95: Total gasto neste levantamento | C95: =SUM(C84:C91) -> 28800
A97: ▶ Levantamento __-__-____ — (preencher data/valor no resumo e ligar D95 a Bxx+Cxx)
D98: =0-IF(C98="",0,C98) -> 0
D99: =D98-IF(C99="",0,C99) -> 0
D100: =D99-IF(C100="",0,C100) -> 0
D101: =D100-IF(C101="",0,C101) -> 0
D102: =D101-IF(C102="",0,C102) -> 0
D103: =D102-IF(C103="",0,C103) -> 0
D104: =D103-IF(C104="",0,C104) -> 0
D105: =D104-IF(C105="",0,C105) -> 0
A106: Total gasto neste levantamento | C106: =SUM(C98:C105) -> 0
A108: ▶ Levantamento __-__-____ — (preencher data/valor no resumo e ligar D106 a Bxx+Cxx)
D109: =0-IF(C109="",0,C109) -> 0
D110: =D109-IF(C110="",0,C110) -> 0
D111: =D110-IF(C111="",0,C111) -> 0
D112: =D111-IF(C112="",0,C112) -> 0
D113: =D112-IF(C113="",0,C113) -> 0
...

Sheet Resumo Mensal
A1: Resumo por Mês – Cartão BAI Express
A3: Mês | B3: Total Entradas (Kz) | C3: Total Saídas (Kz) | D3: Saldo do Mês (Kz) | E3: Nº Movimentos
A4: Julho 2026 | B4: =SUMIF(Movimentos!A7:A70,"*-07-2026",Movimentos!D7:D70) -> 1134000 | C4: =SUMIF(Movimentos!A7:A70,"*-07-2026",Movimentos!E7:E70) -> 29341.26 | D4: =B4-C4 -> 1104658.7 | E4: =COUNTIF(Movimentos!A7:A70,"*-07-2026") -> 16
A5: Agosto 2026 | B5: =SUMIF(Movimentos!A7:A70,"*-08-2026",Movimentos!D7:D70) -> 1452000 | C5: =SUMIF(Movimentos!A7:A70,"*-08-2026",Movimentos!E7:E70) -> 536196.43 | D5: =B5-C5 -> 915803.57 | E5: =COUNTIF(Movimentos!A7:A70,"*-08-2026") -> 22
A6: Setembro 2026
A7: Outubro 2026
A8: Novembro 2026
A9: Dezembro 2026
A10: Janeiro 2027
A11: Fevereiro 2027
A12: Março 2027
A13: Abril 2027
A14: Maio 2027
A15: Junho 2027
A17: Instruções:
A18: 1. Na folha 'Movimentos' preencha o Saldo Inicial (célula B4) com o valor real no início do período. 2. Preencha a coluna 'Descrição Pessoal' para detalhar a origem/destino do dinheiro. 3. Para adicionar novos movimentos, use as linhas amarelas vazias (coloque a data no formato DD-MM-AAAA). 4. O saldo atualiza automaticamente. A folha 'Resumo Mensal' calcula totais por mês. 5. Para meses futuros, pode continuar a adicionar linhas na folha Movimentos; o resumo pode ser atualizado manualmente.

Sheet Instruções
A1: Como usar esta planilha
A3: 1. Saldo Inicial
A4: Na folha Movimentos, célula B4 (amarela), introduza o saldo que a conta tinha antes da primeira transação listada (24-07-2026).
A5: 2. Descrição Pessoal
A6: Na coluna C, escreva uma descrição clara da entrada ou saída (ex: 'Pagamento a fornecedor X', 'Levantamento para caixa', 'Recebimento de cliente Y').
A7: 3. Novos movimentos
A8: Use as linhas amarelas abaixo dos movimentos já preenchidos. Preencha Data, Descrição Banco, Descrição Pessoal, Entrada ou Saída. O Saldo calcula-se sozinho.
A9: 4. Formato da Data
A10: Use sempre DD-MM-AAAA (ex: 15-08-2026) para que os filtros e resumos funcionem corretamente.
A11: 5. Entradas vs Saídas
A12: Coloque valores positivos apenas na coluna Entrada (créditos) ou Saída (débitos). Não coloque o sinal negativo.
A13: 6. Resumo Mensal
... A21: Existe uma nova folha "Fundo de Maneio" onde os levantamentos ATM destinados ao fundo de maneio da Escola são registados como entradas. Use as linhas amarelas dessa folha para registar todas as saídas (gastos) do dinheiro do fundo. O saldo do fundo calcula-se automaticamente.
