Workbook

Sheet Dashboard
B2: DASHBOARD FINANCEIRO ESCOLAR | École Consulaire du Congo - Luanda | 2026/2027
B3: Valores atualizados automaticamente a partir do Controlo de Propinas, Mensalidades, Fluxo de Caixa e DRE
B5: TOTAL INSCRICOES (c/ desc.) | D5: =SUMIF('Controlo de Propinas'!J6:J256,">0") -> 170000 | G5: RESULTADO LIQUIDO (DRE) | K5: ='Controlo de Propinas'!N295 -> 3258000
B6: ='Controlo de Propinas'!N295 -> 3258000 | D6: =SUMIF('Controlo de Propinas'!J6:J105,">0")+SUMIF('Controlo de Propinas'!J110:J124,">0")+SUMIF('Controlo de Propinas'!J129:J187,">0")+SUMIF('Controlo de Propinas'!J192:J206,">0")+SUMIF('Controlo de Propinas'!J210:J248,">0")+SUMIF('Controlo de Propinas'!J253:J292,">0") -> 170000 | G6: =DRE!B25 -> -1730379.9 | K6: ='Controlo de Propinas'!N295 -> 3258000
B9: ALUNOS INSCRITOS | D9: SALDO DE CAIXA | G9: DESCONTOS CONCEDIDOS | K9: TAXA COBRANCA SET/26
B10: =COUNTA('Controlo de Propinas'!B6:B105)+COUNTA('Controlo de Propinas'!B110:B124)+COUNTA('Controlo de Propinas'!B129:B187)+COUNTA('Controlo de Propinas'!B192:B206)+COUNTA('Controlo de Propinas'!B210:B248)+COUNTA('Controlo de Propinas'!B253:B292) -> 17 | D10: ='Fluxo de Caixa'!H6 -> 3058000 | G10: ='Controlo de Propinas'!L295-'Controlo de Propinas'!N295 -> 36000 | K10: =IF(COUNTA(Mensalidades!A6:A12)=0,0,COUNTIF(Mensalidades!E6:E12,">0")/7) -> 0
B12: RECEITAS POR GRUPO (Inscricoes c/ desconto)
B13: Grupo | C13: Alunos | D13: Valor Bruto | E13: Valor c/ Desc.
B14: Maternelle | C14: =COUNTA('Controlo de Propinas'!B6:B105) -> 9 | D14: ='Controlo de Propinas'!L106 -> 1730000 | E14: ='Controlo de Propinas'!N106 -> 1712000
B15: CM1 | C15: =COUNTA('Controlo de Propinas'!B110:B124) -> 1 | D15: ='Controlo de Propinas'!L125 -> 180000 | E15: ='Controlo de Propinas'!N125 -> 180000
B16: CM2 | C16: =COUNTA('Controlo de Propinas'!B129:B187) -> 4 | D16: ='Controlo de Propinas'!L188 -> 834000 | E16: ='Controlo de Propinas'!N188 -> 834000
B17: 6eme | C17: =COUNTA('Controlo de Propinas'!B192:B206) -> 1 | D17: ='Controlo de Propinas'!L207 -> 180000 | E17: ='Controlo de Propinas'!N207 -> 180000
B18: 4eme | C18: =COUNTA('Controlo de Propinas'!B210:B248) -> 1 | D18: ='Controlo de Propinas'!L249 -> 180000 | E18: ='Controlo de Propinas'!N249 -> 162000
B19: TOTAL | C19: =C14+C15+C16+C17+C18 -> 16 | D19: ='Controlo de Propinas'!L295 -> 3294000 | E19: ='Controlo de Propinas'!N295 -> 3258000
B21: DRE RESUMIDO
B22: Proveitos de Inscricoes | C22: =DRE!B4 -> 3088000
B23: Proveitos de Propinas | C23: =DRE!B5 -> 170000
B24: Outros Proveitos | C24: =DRE!B6+DRE!B7 -> 0
B25: TOTAL PROVEITOS | C25: =DRE!B8 -> 3258000
B26: TOTAL CUSTOS | C26: =DRE!B23 -> 4988379.9
B27: RESULTADO LIQUIDO
B29: FLUXO DE CAIXA (resumo mensal)
B30: Mes | C30: Inscricoes | D30: Propinas | E30: Saldo Acum.
B31: Jul/26 | C31: ='Fluxo de Caixa'!B4 -> 1168000 | D31: ='Fluxo de Caixa'!C4 -> 170000 | E31: ='Fluxo de Caixa'!H4 -> 2826379.9
B32: Ago/26 | C32: ='Fluxo de Caixa'!B5 -> 1720000 | D32: ='Fluxo de Caixa'!C5 -> 0 | E32: ='Fluxo de Caixa'!H5 -> 3058000
B33: Set/26 | C33: ='Fluxo de Caixa'!B6 -> 0 | D33: ='Fluxo de Caixa'!C6 -> 0 | E33: ='Fluxo de Caixa'!H6 -> 3058000
B34: Out/26 | C34: ='Fluxo de Caixa'!B7 -> 0 | D34: ='Fluxo de Caixa'!C7 -> 0 | E34: ='Fluxo de Caixa'!H7 -> 3058000
B35: Nov/26 | C35: ='Fluxo de Caixa'!B8 -> 0 | D35: ='Fluxo de Caixa'!C8 -> 0 | E35: ='Fluxo de Caixa'!H8 -> 3058000
B36: Dez/26
B38: STATUS MENSALIDADES (Setembro)
B39: Alunos com pagamento em Set/26 | C39: =COUNTIF(Mensalidades!E6:E80,">0")+COUNTIF(Mensalidades!E85:E159,">0")+COUNTIF(Mensalidades!E164:E238,">0")+COUNTIF(Mensalidades!E243:E317,">0") -> 0
B40: Alunos pendentes (Setembro) | C40: =COUNTIFS(Mensalidades!B6:B80,"<>",Mensalidades!E6:E80,0)+COUNTIFS(Mensalidades!B85:B159,"<>",Mensalidades!E85:E159,0)+COUNTIFS(Mensalidades!B164:B238,"<>",Mensalidades!E164:E238,0)+COUNTIFS(Mensalidades!B243:B317,"<>",Mensalidades!E243:E317,0) -> 212
B41: Valor recebido em Setembro
B43: DESCONTOS POR PARENTESCO
B44: Familias com 2 irmaos (10%) | C44: 3 | D44: Sebastiao da Silva | Calei da Costa | Bernardo Clementino
B45: Filhos unicos (0%) | C45: 4 | D45: Gael, Wendy, Pedro, Kaila
B46: Total descontos concedidos (KZ)
B48: NOTA: Todos os valores sao calculados automaticamente. Atualize Controlo de Propinas ou Mensalidades para refletir alteracoes no Dashboard.
B49: Ecole Consulaire du Congo (Brazzaville) de Luanda • Escola consular – Isenta de impostos • Dashboard financeiro

Sheet Plano de Contas
A1: PLANO GERAL DE CONTABILIDADE (PGC)
A2: CÓDIGO | B2: DESCRIÇÃO
A3: 11 | B3: Imobilizações Corpóreas
A4: 31 | B4: Clientes (Alunos)
A5: 36 | B5: Pessoal
A6: 41 | B6: Bancos
A7: 61 | B7: Compras / Manuais Escolares
A8: 62 | B8: Despesas com Atividades Extracurriculares
A9: 71 | B9: Custo Pessoal
A10: 81 | B10: Proveitos de propinas
A11: 82 | B11: Proveitos Atividades Extra
A12: 83 | B12: Outros Proveitos

Sheet Controlo de Propinas
A1: CONTROLO DE INSCRIÇÕES / MATRÍCULAS – 2026/2027
A2: Amarelo = preencher | Verde = calculado | Desconto: 2 irmãos 10% • 3=15% • 4+=20% | A4 landscape
A4: ▶ MATERNELLE
A5: ID | B5: Nome Aluno | C5: Turma | D5: Inscrição | E5: Manuais | F5: Uniforme | G5: Seguro | H5: Ativ. Extras | I5: Curso Intensivo | J5: 1ª Mensal. | K5: Data Pag. | L5: Valor Bruto | M5: Desc. % | N5: Valor c/ Desc. | O5: Observações
A6: P1-01 | B6: Hazail Epandi Calei da Costa | C6: Maternelle | D6: 150000 | G6: 30000 | K6: 46229 | L6: =IF(B6="","",SUM(D6:J6)) -> 180000 | M6: 0.1 | N6: =IF(B6="","",L6*(1-IF(M6="",0,M6))) -> 162000
A7: P1-02 | B7: Erick Libânio Sebastião da Silva | C7: Maternelle P1 | D7: 150000 | G7: 30000 | K7: 46235 | L7: =IF(B7="","",SUM(D7:J7)) -> 180000 | M7: 0 | N7: =IF(B7="","",L7*(1-IF(M7="",0,M7))) -> 180000
A8: P2-03 | B8: Eloa Marina Sebastião da Silva | C8: Maternelle P2 | D8: 150000 | G8: 30000 | K8: 46235 | L8: =IF(B8="","",SUM(D8:J8)) -> 180000 | M8: 0 | N8: =IF(B8="","",L8*(1-IF(M8="",0,M8))) -> 180000
A9: P2-04 | B9: Ivander Trindade Bernardo Clementino | C9: Maternelle P2 | D9: 150000 | G9: 30000 | K9: 46240 | L9: =IF(B9="","",SUM(D9:J9)) -> 180000 | M9: 0 | N9: =IF(B9="","",L9*(1-IF(M9="",0,M9))) -> 180000
A10: P3-05 | B10: Gael Hanji Ventura Quimbundo | C10: Maternelle P3 | D10: 150000 | G10: 30000 | K10: 46237 | L10: =IF(B10="","",SUM(D10:J10)) -> 180000 | M10: 0 | N10: =IF(B10="","",L10*(1-IF(M10="",0,M10))) -> 180000
A11: P3-06 | B11: Ivanna Chayane Bernardo Clementino | C11: Maternelle P3 | D11: 150000 | G11: 30000 | K11: 46240 | L11: =IF(B11="","",SUM(D11:J11)) -> 180000 | M11: 0 | N11: =IF(B11="","",L11*(1-IF(M11="",0,M11))) -> 180000
A12: P3-07 | B12: Wendy Aryanne Chimuco Sabino | C12: Maternelle P3 | D12: 150000 | G12: 30000 | J12: 170000 | K12: 46232 | L12: =IF(B12="","",SUM(D12:J12)) -> 350000 | M12: 0 | N12: =IF(B12="","",L12*(1-IF(M12="",0,M12))) -> 350000
A13: P1-08 | B13: Kesane Aimé Teixeira Correia de Azevedo | C13: Maternelle P1 | D13: 150000 | G13: 0 | K13: 46255 | L13: =IF(B13="","",SUM(D13:J13)) -> 150000 | M13: 0 | N13: =IF(B13="","",L13*(1-IF(M13="",0,M13))) -> 150000
A14: P3-09 | B14: Kuami Hazael Francisco Venâncio | C14: Maternelle P3 | D14: 150000 | G14: 0 | K14: 46245 | L14: =IF(B14="","",SUM(D14:J14)) -> 150000 | M14: 0 | N14: =IF(B14="","",L14*(1-IF(M14="",0,M14))) -> 150000
L15: =IF(B15="","",SUM(D15:J15)) | N15: =IF(B15="","",L15*(1-IF(M15="",0,M15)))
L16: =IF(B16="","",SUM(D16:J16)) | N16: =IF(B16="","",L16*(1-IF(M16="",0,M16)))
L17: =IF(B17="","",SUM(D17:J17)) | N17: =IF(B17="","",L17*(1-IF(M17="",0,M17)))
L18: =IF(B18="","",SUM(D18:J18)) | N18: =IF(B18="","",L18*(1-IF(M18="",0,M18)))
L19: =IF(B19="","",SUM(D19:J19)) | N19: =IF(B19="","",L19*(1-IF(M19="",0,M19)))
L20: =IF(B20="","",SUM(D20:J20)) | N20: =IF(B20="","",L20*(1-IF(M20="",0,M20)))
L21: =IF(B21="","",SUM(D21:J21)) | N21: =IF(B21="","",L21*(1-IF(M21="",0,M21)))
L22: =IF(B22="","",SUM(D22:J22)) | N22: =IF(B22="","",L22*(1-IF(M22="",0,M22)))
L23: =IF(B23="","",SUM(D23:J23)) | N23: =IF(B23="","",L23*(1-IF(M23="",0,M23)))
L24: =IF(B24="","",SUM(D24:J24)) | N24: =IF(B24="","",L24*(1-IF(M24="",0,M24)))
L25: =IF(B25="","",SUM(D25:J25)) | N25: =IF(B25="","",L25*(1-IF(M25="",0,M25)))
L26: =IF(B26="","",SUM(D26:J26)) | N26: =IF(B26="","",L26*(1-IF(M26="",0,M26)))
... L105: =IF(B105="","",SUM(D105:J105)) | N105: =IF(B105="","",L105*(1-IF(M105="",0,M105)))
A106: Subtotal | B106: =COUNTIF(B6:B105,"?*")&" alunos" -> 9 alunos | L106: =SUM(L6:L105) -> 1730000 | N106: =SUM(N6:N105) -> 1712000
A108: ▶ CM1
A109: ID | B109: Nome Aluno | C109: Turma | D109: Inscrição | E109: Manuais | F109: Uniforme | G109: Seguro | H109: Ativ. Extras | I109: Curso Intensivo | J109: 1ª Mensal. | K109: Data Pag. | L109: Valor Bruto | M109: Desc. % | N109: Valor c/ Desc. | O109: Observações
A110: CM1-01 | B110: Crisber Uluwami António Cristovão De Sousa | C110: CM1 | D110: 150000 | G110: 30000 | K110: 46252 | L110: =IF(B110="","",SUM(D110:J110)) -> 180000 | N110: =IF(B110="","",L110*(1-IF(M110="",0,M110))) -> 180000
A111: CM1-02 | C111: CM1 | L111: =IF(B111="","",SUM(D111:J111)) | N111: =IF(B111="","",L111*(1-IF(M111="",0,M111)))
C112: CM1 | L112: =IF(B112="","",SUM(D112:J112)) | N112: =IF(B112="","",L112*(1-IF(M112="",0,M112)))
C113: CM1 | L113: =IF(B113="","",SUM(D113:J113)) | N113: =IF(B113="","",L113*(1-IF(M113="",0,M113)))
C114: CM1 | L114: =IF(B114="","",SUM(D114:J114)) | N114: =IF(B114="","",L114*(1-IF(M114="",0,M114)))
C115: CM1 | L115: =IF(B115="","",SUM(D115:J115)) | N115: =IF(B115="","",L115*(1-IF(M115="",0,M115)))
C116: CM1 | L116: =IF(B116="","",SUM(D116:J116)) | N116: =IF(B116="","",L116*(1-IF(M116="",0,M116)))
C117: CM1 | L117: =IF(B117="","",SUM(D117:J117)) | N117: =IF(B117="","",L117*(1-IF(M117="",0,M117)))
C118: CM1 | L118: =IF(B118="","",SUM(D118:J118)) | N118: =IF(B118="","",L118*(1-IF(M118="",0,M118)))
C119: CM1 | L119: =IF(B119="","",SUM(D119:J119)) | N119: =IF(B119="","",L119*(1-IF(M119="",0,M119)))
C120: CM1 | L120: =IF(B120="","",SUM(D120:J120)) | N120: =IF(B120="","",L120*(1-IF(M120="",0,M120)))
C121: CM1 | L121: =IF(B121="","",SUM(D121:J121)) | N121: =IF(B121="","",L121*(1-IF(M121="",0,M121)))
C122: CM1 | L122: =IF(B122="","",SUM(D122:J122)) | N122: =IF(B122="","",L122*(1-IF(M122="",0,M122)))
C123: CM1 | L123: =IF(B123="","",SUM(D123:J123)) | N123: =IF(B123="","",L123*(1-IF(M123="",0,M123)))
C124: CM1 | L124: =IF(B124="","",SUM(D124:J124)) | N124: =IF(B124="","",L124*(1-IF(M124="",0,M124)))
A125: Subtotal | B125: =COUNTIF(B110:B124,"?*")&" alunos" -> 1 alunos | L125: =SUM(L110:L124) -> 180000 | N125: =SUM(N110:N124) -> 180000
A127: ▶ CM2
A128: ID | B128: Nome Aluno | C128: Turma | D128: Inscrição | E128: Manuais | F128: Uniforme | G128: Seguro | H128: Ativ. Extras | I128: Curso Intensivo | J128: 1ª Mensal. | K128: Data Pag. | L128: Valor Bruto | M128: Desc. % | N128: Valor c/ Desc. | O128: Observações
A129: CM2-01 | B129: Kaila Abigail Katata da Silva | C129: CM2 | D129: 150000 | E129: 40000 | G129: 30000 | I129: 40000 | K129: 46230 | L129: =IF(B129="","",SUM(D129:J129)) -> 260000 | M129: 0 | N129: =IF(B129="","",L129*(1-IF(M129="",0,M129))) -> 260000
A130: CM2-02 | B130: Pedro Henriques Simão dos Santos | C130: CM2 | D130: 150000 | E130: 54000 | G130: 30000 | K130: 46229 | L130: =IF(B130="","",SUM(D130:J130)) -> 234000 | M130: 0 | N130: =IF(B130="","",L130*(1-IF(M130="",0,M130))) -> 234000
A131: CM2-03 | B131: Keane António Teixeira Correia de Azevedo | C131: CM2 | D131: 150000 | G131: 0 | I131: 40000 | K131: 46239 | L131: =IF(B131="","",SUM(D131:J131)) -> 190000 | M131: 0 | N131: =IF(B131="","",L131*(1-IF(M131="",0,M131))) -> 190000
A132: CM2-04 | B132: Márcio Uzziel Francisco Venâncio | C132: CM2 | D132: 150000 | G132: 0 | K132: 46245 | L132: =IF(B132="","",SUM(D132:J132)) -> 150000 | M132: 0 | N132: =IF(B132="","",L132*(1-IF(M132="",0,M132))) -> 150000
C133: CM2 | L133: =IF(B133="","",SUM(D133:J133)) | N133: =IF(B133="","",L133*(1-IF(M133="",0,M133)))
C134: CM2 | L134: =IF(B134="","",SUM(D134:J134)) | N134: =IF(B134="","",L134*(1-IF(M134="",0,M134)))
C135: CM2 | L135: =IF(B135="","",SUM(D135:J135)) | N135: =IF(B135="","",L135*(1-IF(M135="",0,M135)))
C136: CM2 | L136: =IF(B136="","",SUM(D136:J136)) | N136: =IF(B136="","",L136*(1-IF(M136="",0,M136)))
C137: CM2 | L137: =IF(B137="","",SUM(D137:J137)) | N137: =IF(B137="","",L137*(1-IF(M137="",0,M137)))
C138: CM2 | L138: =IF(B138="","",SUM(D138:J138)) | N138: =IF(B138="","",L138*(1-IF(M138="",0,M138)))
C139: CM2 | L139: =IF(B139="","",SUM(D139:J139)) | N139: =IF(B139="","",L139*(1-IF(M139="",0,M139)))
C140: CM2 | L140: =IF(B140="","",SUM(D140:J140)) | N140: =IF(B140="","",L140*(1-IF(M140="",0,M140)))
C141: CM2 | L141: =IF(B141="","",SUM(D141:J141)) | N141: =IF(B141="","",L141*(1-IF(M141="",0,M141)))
C142: CM2 | L142: =IF(B142="","",SUM(D142:J142)) | N142: =IF(B142="","",L142*(1-IF(M142="",0,M142)))
C143: CM2 | L143: =IF(B143="","",SUM(D143:J143)) | N143: =IF(B143="","",L143*(1-IF(M143="",0,M143)))
C144: CM2 | L144: =IF(B144="","",SUM(D144:J144)) | N144: =IF(B144="","",L144*(1-IF(M144="",0,M144)))
... C187: CM2 | L187: =IF(B187="","",SUM(D187:J187)) | N187: =IF(B187="","",L187*(1-IF(M187="",0,M187)))
A188: Subtotal | B188: =COUNTIF(B129:B187,"?*")&" alunos" -> 4 alunos | L188: =SUM(L129:L187) -> 834000 | N188: =SUM(N129:N187) -> 834000
A190: ▶ 6EME (Sixième)
A191: ID | B191: Nome Aluno | C191: Turma | D191: Inscrição | E191: Manuais | F191: Uniforme | G191: Seguro | H191: Ativ. Extras | I191: Curso Intensivo | J191: 1ª Mensal. | K191: Data Pag. | L191: Valor Bruto | M191: Desc. % | N191: Valor c/ Desc. | O191: Observações
A192: 6E-01 | B192: Imayami Suriel António Cristovão De Sousa | C192: 6eme | D192: 150000 | G192: 30000 | L192: =IF(B192="","",SUM(D192:J192)) -> 180000 | N192: =IF(B192="","",L192*(1-IF(M192="",0,M192))) -> 180000
C193: 6eme | L193: =IF(B193="","",SUM(D193:J193)) | N193: =IF(B193="","",L193*(1-IF(M193="",0,M193)))
C194: 6eme | L194: =IF(B194="","",SUM(D194:J194)) | N194: =IF(B194="","",L194*(1-IF(M194="",0,M194)))
C195: 6eme | L195: =IF(B195="","",SUM(D195:J195)) | N195: =IF(B195="","",L195*(1-IF(M195="",0,M195)))
C196: 6eme | L196: =IF(B196="","",SUM(D196:J196)) | N196: =IF(B196="","",L196*(1-IF(M196="",0,M196)))
C197: 6eme | L197: =IF(B197="","",SUM(D197:J197)) | N197: =IF(B197="","",L197*(1-IF(M197="",0,M197)))
C198: 6eme | L198: =IF(B198="","",SUM(D198:J198)) | N198: =IF(B198="","",L198*(1-IF(M198="",0,M198)))
C199: 6eme | L199: =IF(B199="","",SUM(D199:J199)) | N199: =IF(B199="","",L199*(1-IF(M199="",0,M199)))
C200: 6eme | L200: =IF(B200="","",SUM(D200:J200)) | N200: =IF(B200="","",L200*(1-IF(M200="",0,M200)))
C201: 6eme | L201: =IF(B201="","",SUM(D201:J201)) | N201: =IF(B201="","",L201*(1-IF(M201="",0,M201)))
C202: 6eme | L202: =IF(B202="","",SUM(D202:J202)) | N202: =IF(B202="","",L202*(1-IF(M202="",0,M202)))
C203: 6eme | L203: =IF(B203="","",SUM(D203:J203)) | N203: =IF(B203="","",L203*(1-IF(M203="",0,M203)))
C204: 6eme | L204: =IF(B204="","",SUM(D204:J204)) | N204: =IF(B204="","",L204*(1-IF(M204="",0,M204)))
... C206: 6eme | L206: =IF(B206="","",SUM(D206:J206)) | N206: =IF(B206="","",L206*(1-IF(M206="",0,M206)))
A207: Subtotal | B207: =COUNTIF(B192:B206,"?*")&" alunos" -> 1 alunos | L207: =SUM(L192:L206) -> 180000 | N207: =SUM(N192:N206) -> 180000
A208: ▶ 4EME
A209: ID | B209: Nome Aluno | C209: Turma | D209: Inscrição | E209: Manuais | F209: Uniforme | G209: Seguro | H209: Ativ. Extras | I209: Curso Intensivo | J209: 1ª Mensal. | K209: Data Pag. | L209: Valor Bruto | M209: Desc. % | N209: Valor c/ Desc. | O209: Observações
A210: 4E-01 | B210: Nathaniel Dialude Calei da Costa | C210: 4eme | D210: 150000 | G210: 30000 | K210: 46229 | L210: =IF(B210="","",SUM(D210:J210)) -> 180000 | M210: 0.1 | N210: =IF(B210="","",L210*(1-IF(M210="",0,M210))) -> 162000
C211: 4eme | L211: =IF(B211="","",SUM(D211:J211)) | N211: =IF(B211="","",L211*(1-IF(M211="",0,M211)))
C212: 4eme | L212: =IF(B212="","",SUM(D212:J212)) | N212: =IF(B212="","",L212*(1-IF(M212="",0,M212)))
C213: 4eme | L213: =IF(B213="","",SUM(D213:J213)) | N213: =IF(B213="","",L213*(1-IF(M213="",0,M213)))
C214: 4eme | L214: =IF(B214="","",SUM(D214:J214)) | N214: =IF(B214="","",L214*(1-IF(M214="",0,M214)))
C215: 4eme | L215: =IF(B215="","",SUM(D215:J215)) | N215: =IF(B215="","",L215*(1-IF(M215="",0,M215)))
C216: 4eme | L216: =IF(B216="","",SUM(D216:J216)) | N216: =IF(B216="","",L216*(1-IF(M216="",0,M216)))
C217: 4eme | L217: =IF(B217="","",SUM(D217:J217)) | N217: =IF(B217="","",L217*(1-IF(M217="",0,M217)))
C218: 4eme | L218: =IF(B218="","",SUM(D218:J218)) | N218: =IF(B218="","",L218*(1-IF(M218="",0,M218)))
C219: 4eme | L219: =IF(B219="","",SUM(D219:J219)) | N219: =IF(B219="","",L219*(1-IF(M219="",0,M219)))
C220: 4eme | L220: =IF(B220="","",SUM(D220:J220)) | N220: =IF(B220="","",L220*(1-IF(M220="",0,M220)))
C221: 4eme | L221: =IF(B221="","",SUM(D221:J221)) | N221: =IF(B221="","",L221*(1-IF(M221="",0,M221)))
C222: 4eme | L222: =IF(B222="","",SUM(D222:J222)) | N222: =IF(B222="","",L222*(1-IF(M222="",0,M222)))
... C248: 4eme | L248: =IF(B248="","",SUM(D248:J248)) | N248: =IF(B248="","",L248*(1-IF(M248="",0,M248)))
A249: Subtotal | B249: =COUNTIF(B210:B248,"?*")&" alunos" -> 1 alunos | L249: =SUM(L210:L248) -> 180000 | N249: =SUM(N210:N248) -> 162000
A251: ▶ OUTROS
...

Sheet Mensalidades
A1: CONTROLO DE MENSALIDADES – 2026/2027
A2: Ligado ao Controlo de Propinas | Amarelo = pago no mês | Verde = calculado | Status: Pendente / Parcial / Pago | A4 landscape
A4: ▶ MATERNELLE (até 75 alunos)
A5: ID | B5: Nome Aluno | C5: Turma | D5: Propina | E5: Set | F5: Out | G5: Nov | H5: Dez | I5: Jan | J5: Fev | K5: Mar | L5: Abr | M5: Mai | N5: Jun | O5: Total | P5: Status | Q5: Obs.
A6: =IF('Controlo de Propinas'!A6="","",'Controlo de Propinas'!A6) -> P1-01 | B6: =IF('Controlo de Propinas'!B6="","",'Controlo de Propinas'!B6) -> Hazail Epandi Calei da Costa | C6: =IF('Controlo de Propinas'!C6="","",'Controlo de Propinas'!C6) -> Maternelle | D6: =IF(C6="","",IF(OR(C6="Maternelle",C6="Maternelle P1",C6="Maternelle P2",C6="Maternelle P3"),170000,IF(C6="CM2",250000,IF(C6="4eme",260000,170000)))) -> 170000 | E6: 0 | F6: 0 | G6: 0 | H6: 0 | I6: 0 | J6: 0 | K6: 0 | L6: 0 | M6: 0 | N6: 0 | O6: =IF(B6="","",SUM(E6:N6)) -> 0 | P6: =IF(B6="","",IF(O6=0,"Pendente",IF(O6<D6,"Parcial","Pago"))) -> Pendente
A7: =IF('Controlo de Propinas'!A7="","",'Controlo de Propinas'!A7) -> P1-02 | B7: =IF('Controlo de Propinas'!B7="","",'Controlo de Propinas'!B7) -> Erick Libânio Sebastião da Silva | C7: =IF('Controlo de Propinas'!C7="","",'Controlo de Propinas'!C7) -> Maternelle P1 | D7: =IF(C7="","",IF(OR(C7="Maternelle",C7="Maternelle P1",C7="Maternelle P2",C7="Maternelle P3"),170000,IF(C7="CM2",250000,IF(C7="4eme",260000,170000)))) -> 170000 | E7: 0 | F7: 0 | G7: 0 | H7: 0 | I7: 0 | J7: 0 | K7: 0 | L7: 0 | M7: 0 | N7: 0 | O7: =IF(B7="","",SUM(E7:N7)) -> 0 | P7: =IF(B7="","",IF(O7=0,"Pendente",IF(O7<D7,"Parcial","Pago"))) -> Pendente
A8: =IF('Controlo de Propinas'!A8="","",'Controlo de Propinas'!A8) -> P2-03 | B8: =IF('Controlo de Propinas'!B8="","",'Controlo de Propinas'!B8) -> Eloa Marina Sebastião da Silva | C8: =IF('Controlo de Propinas'!C8="","",'Controlo de Propinas'!C8) -> Maternelle P2 | D8: =IF(C8="","",IF(OR(C8="Maternelle",C8="Maternelle P1",C8="Maternelle P2",C8="Maternelle P3"),170000,IF(C8="CM2",250000,IF(C8="4eme",260000,170000)))) -> 170000 | E8: 0 | F8: 0 | G8: 0 | H8: 0 | I8: 0 | J8: 0 | K8: 0 | L8: 0 | M8: 0 | N8: 0 | O8: =IF(B8="","",SUM(E8:N8)) -> 0 | P8: =IF(B8="","",IF(O8=0,"Pendente",IF(O8<D8,"Parcial","Pago"))) -> Pendente
A9: =IF('Controlo de Propinas'!A9="","",'Controlo de Propinas'!A9) -> P2-04 | B9: =IF('Controlo de Propinas'!B9="","",'Controlo de Propinas'!B9) -> Ivander Trindade Bernardo Clementino | C9: =IF('Controlo de Propinas'!C9="","",'Controlo de Propinas'!C9) -> Maternelle P2 | D9: =IF(C9="","",IF(OR(C9="Maternelle",C9="Maternelle P1",C9="Maternelle P2",C9="Maternelle P3"),170000,IF(C9="CM2",250000,IF(C9="4eme",260000,170000)))) -> 170000 | E9: 0 | F9: 0 | G9: 0 | H9: 0 | I9: 0 | J9: 0 | K9: 0 | L9: 0 | M9: 0 | N9: 0 | O9: =IF(B9="","",SUM(E9:N9)) -> 0 | P9: =IF(B9="","",IF(O9=0,"Pendente",IF(O9<D9,"Parcial","Pago"))) -> Pendente
A10: =IF('Controlo de Propinas'!A10="","",'Controlo de Propinas'!A10) -> P3-05 | B10: =IF('Controlo de Propinas'!B10="","",'Controlo de Propinas'!B10) -> Gael Hanji Ventura Quimbundo | C10: =IF('Controlo de Propinas'!C10="","",'Controlo de Propinas'!C10) -> Maternelle P3 | D10: =IF(C10="","",IF(OR(C10="Maternelle",C10="Maternelle P1",C10="Maternelle P2",C10="Maternelle P3"),170000,IF(C10="CM2",250000,IF(C10="4eme",260000,170000)))) -> 170000 | E10: 0 | F10: 0 | G10: 0 | H10: 0 | I10: 0 | J10: 0 | K10: 0 | L10: 0 | M10: 0 | N10: 0 | O10: =IF(B10="","",SUM(E10:N10)) -> 0 | P10: =IF(B10="","",IF(O10=0,"Pendente",IF(O10<D10,"Parcial","Pago"))) -> Pendente
A11: =IF('Controlo de Propinas'!A11="","",'Controlo de Propinas'!A11) -> P3-06 | B11: =IF('Controlo de Propinas'!B11="","",'Controlo de Propinas'!B11) -> Ivanna Chayane Bernardo Clementino | C11: =IF('Controlo de Propinas'!C11="","",'Controlo de Propinas'!C11) -> Maternelle P3 | D11: =IF(C11="","",IF(OR(C11="Maternelle",C11="Maternelle P1",C11="Maternelle P2",C11="Maternelle P3"),170000,IF(C11="CM2",250000,IF(C11="4eme",260000,170000)))) -> 170000 | E11: 0 | F11: 0 | G11: 0 | H11: 0 | I11: 0 | J11: 0 | K11: 0 | L11: 0 | M11: 0 | N11: 0 | O11: =IF(B11="","",SUM(E11:N11)) -> 0 | P11: =IF(B11="","",IF(O11=0,"Pendente",IF(O11<D11,"Parcial","Pago"))) -> Pendente
A12: =IF('Controlo de Propinas'!A12="","",'Controlo de Propinas'!A12) -> P3-07 | B12: =IF('Controlo de Propinas'!B12="","",'Controlo de Propinas'!B12) -> Wendy Aryanne Chimuco Sabino | C12: =IF('Controlo de Propinas'!C12="","",'Controlo de Propinas'!C12) -> Maternelle P3 | D12: =IF(C12="","",IF(OR(C12="Maternelle",C12="Maternelle P1",C12="Maternelle P2",C12="Maternelle P3"),170000,IF(C12="CM2",250000,IF(C12="4eme",260000,170000)))) -> 170000 | E12: 0 | F12: 0 | G12: 0 | H12: 0 | I12: 0 | J12: 0 | K12: 0 | L12: 0 | M12: 0 | N12: 0 | O12: =IF(B12="","",SUM(E12:N12)) -> 0 | P12: =IF(B12="","",IF(O12=0,"Pendente",IF(O12<D12,"Parcial","Pago"))) -> Pendente
A13: =IF('Controlo de Propinas'!A13="","",'Controlo de Propinas'!A13) -> P1-08 | B13: =IF('Controlo de Propinas'!B13="","",'Controlo de Propinas'!B13) -> Kesane Aimé Teixeira Correia de Azevedo | C13: =IF('Controlo de Propinas'!C13="","",'Controlo de Propinas'!C13) -> Maternelle P1 | D13: =IF(C13="","",IF(OR(C13="Maternelle",C13="Maternelle P1",C13="Maternelle P2",C13="Maternelle P3"),170000,IF(C13="CM2",250000,IF(C13="4eme",260000,170000)))) -> 170000 | E13: 0 | F13: 0 | G13: 0 | H13: 0 | I13: 0 | J13: 0 | K13: 0 | L13: 0 | M13: 0 | N13: 0 | O13: =IF(B13="","",SUM(E13:N13)) -> 0 | P13: =IF(B13="","",IF(O13=0,"Pendente",IF(O13<D13,"Parcial","Pago"))) -> Pendente
A14: =IF('Controlo de Propinas'!A14="","",'Controlo de Propinas'!A14) -> P3-09 | B14: =IF('Controlo de Propinas'!B14="","",'Controlo de Propinas'!B14) -> Kuami Hazael Francisco Venâncio | C14: =IF('Controlo de Propinas'!C14="","",'Controlo de Propinas'!C14) -> Maternelle P3 | D14: =IF(C14="","",IF(OR(C14="Maternelle",C14="Maternelle P1",C14="Maternelle P2",C14="Maternelle P3"),170000,IF(C14="CM2",250000,IF(C14="4eme",260000,170000)))) -> 170000 | E14: 0 | F14: 0 | G14: 0 | H14: 0 | I14: 0 | J14: 0 | K14: 0 | L14: 0 | M14: 0 | N14: 0 | O14: =IF(B14="","",SUM(E14:N14)) -> 0 | P14: =IF(B14="","",IF(O14=0,"Pendente",IF(O14<D14,"Parcial","Pago"))) -> Pendente
A15: =IF('Controlo de Propinas'!A15="","",'Controlo de Propinas'!A15) | B15: =IF('Controlo de Propinas'!B15="","",'Controlo de Propinas'!B15) | C15: =IF('Controlo de Propinas'!C15="","",'Controlo de Propinas'!C15) | D15: =IF(C15="","",IF(OR(C15="Maternelle",C15="Maternelle P1",C15="Maternelle P2",C15="Maternelle P3"),170000,IF(C15="CM2",250000,IF(C15="4eme",260000,170000)))) | E15: 0 | F15: 0 | G15: 0 | H15: 0 | I15: 0 | J15: 0 | K15: 0 | L15: 0 | M15: 0 | N15: 0 | O15: =IF(B15="","",SUM(E15:N15)) | P15: =IF(B15="","",IF(O15=0,"Pendente",IF(O15<D15,"Parcial","Pago")))
A16: =IF('Controlo de Propinas'!A16="","",'Controlo de Propinas'!A16) | B16: =IF('Controlo de Propinas'!B16="","",'Controlo de Propinas'!B16) | C16: =IF('Controlo de Propinas'!C16="","",'Controlo de Propinas'!C16) | D16: =IF(C16="","",IF(OR(C16="Maternelle",C16="Maternelle P1",C16="Maternelle P2",C16="Maternelle P3"),170000,IF(C16="CM2",250000,IF(C16="4eme",260000,170000)))) | E16: 0 | F16: 0 | G16: 0 | H16: 0 | I16: 0 | J16: 0 | K16: 0 | L16: 0 | M16: 0 | N16: 0 | O16: =IF(B16="","",SUM(E16:N16)) | P16: =IF(B16="","",IF(O16=0,"Pendente",IF(O16<D16,"Parcial","Pago")))
A17: =IF('Controlo de Propinas'!A17="","",'Controlo de Propinas'!A17) | B17: =IF('Controlo de Propinas'!B17="","",'Controlo de Propinas'!B17) | C17: =IF('Controlo de Propinas'!C17="","",'Controlo de Propinas'!C17) | D17: =IF(C17="","",IF(OR(C17="Maternelle",C17="Maternelle P1",C17="Maternelle P2",C17="Maternelle P3"),170000,IF(C17="CM2",250000,IF(C17="4eme",260000,170000)))) | E17: 0 | F17: 0 | G17: 0 | H17: 0 | I17: 0 | J17: 0 | K17: 0 | L17: 0 | M17: 0 | N17: 0 | O17: =IF(B17="","",SUM(E17:N17)) | P17: =IF(B17="","",IF(O17=0,"Pendente",IF(O17<D17,"Parcial","Pago")))
... A80: =IF('Controlo de Propinas'!A80="","",'Controlo de Propinas'!A80) | B80: =IF('Controlo de Propinas'!B80="","",'Controlo de Propinas'!B80) | C80: =IF('Controlo de Propinas'!C80="","",'Controlo de Propinas'!C80) | D80: =IF(C80="","",IF(OR(C80="Maternelle",C80="Maternelle P1",C80="Maternelle P2",C80="Maternelle P3"),170000,IF(C80="CM2",250000,IF(C80="4eme",260000,170000)))) | E80: 0 | F80: 0 | G80: 0 | H80: 0 | I80: 0 | J80: 0 | K80: 0 | L80: 0 | M80: 0 | N80: 0 | O80: =IF(B80="","",SUM(E80:N80)) | P80: =IF(B80="","",IF(O80=0,"Pendente",IF(O80<D80,"Parcial","Pago")))
A81: Subtotal | B81: =COUNTIF(B6:B80,"?*")&" alunos" -> 9 alunos | E81: =SUM(E6:E80) -> 0 | F81: =SUM(F6:F80) -> 0 | G81: =SUM(G6:G80) -> 0 | H81: =SUM(H6:H80) -> 0 | I81: =SUM(I6:I80) -> 0 | J81: =SUM(J6:J80) -> 0 | K81: =SUM(K6:K80) -> 0 | L81: =SUM(L6:L80) -> 0 | ... O81: =SUM(O6:O80) -> 0
A83: ▶ CM1 (até 75 alunos)
A84: ID | B84: Nome Aluno | C84: Turma | D84: Propina | E84: Set | F84: Out | G84: Nov | H84: Dez | I84: Jan | J84: Fev | K84: Mar | L84: Abr | M84: Mai | N84: Jun | O84: Total | P84: Status | Q84: Obs.
A85: =IF('Controlo de Propinas'!A110="","",'Controlo de Propinas'!A110) -> CM1-01 | B85: =IF('Controlo de Propinas'!B110="","",'Controlo de Propinas'!B110) -> Crisber Uluwami António Cristovão De Sousa | C85: =IF('Controlo de Propinas'!C110="","",'Controlo de Propinas'!C110) -> CM1 | D85: =IF(C85="","",IF(OR(C85="Maternelle",C85="Maternelle P1",C85="Maternelle P2",C85="Maternelle P3"),170000,IF(C85="CM2",250000,IF(C85="4eme",260000,170000)))) -> 170000 | O85: =IF(B85="","",SUM(E85:N85)) -> 0 | P85: =IF(B85="","",IF(O85=0,"Pendente",IF(COUNTIF(E85:N85,">0")>=10,"Pago","Parcial"))) -> Pendente
A86: =IF('Controlo de Propinas'!A111="","",'Controlo de Propinas'!A111) -> CM1-02 | B86: =IF('Controlo de Propinas'!B111="","",'Controlo de Propinas'!B111) | C86: =IF('Controlo de Propinas'!C111="","",'Controlo de Propinas'!C111) -> CM1 | D86: =IF(C86="","",IF(OR(C86="Maternelle",C86="Maternelle P1",C86="Maternelle P2",C86="Maternelle P3"),170000,IF(C86="CM2",250000,IF(C86="4eme",260000,170000)))) -> 170000 | O86: =IF(B86="","",SUM(E86:N86)) | P86: =IF(B86="","",IF(O86=0,"Pendente",IF(COUNTIF(E86:N86,">0")>=10,"Pago","Parcial")))
A87: =IF('Controlo de Propinas'!A112="","",'Controlo de Propinas'!A112) | B87: =IF('Controlo de Propinas'!B112="","",'Controlo de Propinas'!B112) | C87: =IF('Controlo de Propinas'!C112="","",'Controlo de Propinas'!C112) -> CM1 | D87: =IF(C87="","",IF(OR(C87="Maternelle",C87="Maternelle P1",C87="Maternelle P2",C87="Maternelle P3"),170000,IF(C87="CM2",250000,IF(C87="4eme",260000,170000)))) -> 170000 | O87: =IF(B87="","",SUM(E87:N87)) | P87: =IF(B87="","",IF(O87=0,"Pendente",IF(COUNTIF(E87:N87,">0")>=10,"Pago","Parcial")))
A88: =IF('Controlo de Propinas'!A113="","",'Controlo de Propinas'!A113) | B88: =IF('Controlo de Propinas'!B113="","",'Controlo de Propinas'!B113) | C88: =IF('Controlo de Propinas'!C113="","",'Controlo de Propinas'!C113) -> CM1 | D88: =IF(C88="","",IF(OR(C88="Maternelle",C88="Maternelle P1",C88="Maternelle P2",C88="Maternelle P3"),170000,IF(C88="CM2",250000,IF(C88="4eme",260000,170000)))) -> 170000 | O88: =IF(B88="","",SUM(E88:N88)) | P88: =IF(B88="","",IF(O88=0,"Pendente",IF(COUNTIF(E88:N88,">0")>=10,"Pago","Parcial")))
A89: =IF('Controlo de Propinas'!A114="","",'Controlo de Propinas'!A114) | B89: =IF('Controlo de Propinas'!B114="","",'Controlo de Propinas'!B114) | C89: =IF('Controlo de Propinas'!C114="","",'Controlo de Propinas'!C114) -> CM1 | D89: =IF(C89="","",IF(OR(C89="Maternelle",C89="Maternelle P1",C89="Maternelle P2",C89="Maternelle P3"),170000,IF(C89="CM2",250000,IF(C89="4eme",260000,170000)))) -> 170000 | O89: =IF(B89="","",SUM(E89:N89)) | P89: =IF(B89="","",IF(O89=0,"Pendente",IF(COUNTIF(E89:N89,">0")>=10,"Pago","Parcial")))
A90: =IF('Controlo de Propinas'!A115="","",'Controlo de Propinas'!A115) | B90: =IF('Controlo de Propinas'!B115="","",'Controlo de Propinas'!B115) | C90: =IF('Controlo de Propinas'!C115="","",'Controlo de Propinas'!C115) -> CM1 | D90: =IF(C90="","",IF(OR(C90="Maternelle",C90="Maternelle P1",C90="Maternelle P2",C90="Maternelle P3"),170000,IF(C90="CM2",250000,IF(C90="4eme",260000,170000)))) -> 170000 | O90: =IF(B90="","",SUM(E90:N90)) | P90: =IF(B90="","",IF(O90=0,"Pendente",IF(COUNTIF(E90:N90,">0")>=10,"Pago","Parcial")))
A91: =IF('Controlo de Propinas'!A116="","",'Controlo de Propinas'!A116) | B91: =IF('Controlo de Propinas'!B116="","",'Controlo de Propinas'!B116) | C91: =IF('Controlo de Propinas'!C116="","",'Controlo de Propinas'!C116) -> CM1 | D91: =IF(C91="","",IF(OR(C91="Maternelle",C91="Maternelle P1",C91="Maternelle P2",C91="Maternelle P3"),170000,IF(C91="CM2",250000,IF(C91="4eme",260000,170000)))) -> 170000 | O91: =IF(B91="","",SUM(E91:N91)) | P91: =IF(B91="","",IF(O91=0,"Pendente",IF(COUNTIF(E91:N91,">0")>=10,"Pago","Parcial")))
A92: =IF('Controlo de Propinas'!A117="","",'Controlo de Propinas'!A117) | B92: =IF('Controlo de Propinas'!B117="","",'Controlo de Propinas'!B117) | C92: =IF('Controlo de Propinas'!C117="","",'Controlo de Propinas'!C117) -> CM1 | D92: =IF(C92="","",IF(OR(C92="Maternelle",C92="Maternelle P1",C92="Maternelle P2",C92="Maternelle P3"),170000,IF(C92="CM2",250000,IF(C92="4eme",260000,170000)))) -> 170000 | O92: =IF(B92="","",SUM(E92:N92)) | P92: =IF(B92="","",IF(O92=0,"Pendente",IF(COUNTIF(E92:N92,">0")>=10,"Pago","Parcial")))
A93: =IF('Controlo de Propinas'!A118="","",'Controlo de Propinas'!A118) | B93: =IF('Controlo de Propinas'!B118="","",'Controlo de Propinas'!B118) | C93: =IF('Controlo de Propinas'!C118="","",'Controlo de Propinas'!C118) -> CM1 | D93: =IF(C93="","",IF(OR(C93="Maternelle",C93="Maternelle P1",C93="Maternelle P2",C93="Maternelle P3"),170000,IF(C93="CM2",250000,IF(C93="4eme",260000,170000)))) -> 170000 | O93: =IF(B93="","",SUM(E93:N93)) | P93: =IF(B93="","",IF(O93=0,"Pendente",IF(COUNTIF(E93:N93,">0")>=10,"Pago","Parcial")))
A94: =IF('Controlo de Propinas'!A119="","",'Controlo de Propinas'!A119) | B94: =IF('Controlo de Propinas'!B119="","",'Controlo de Propinas'!B119) | C94: =IF('Controlo de Propinas'!C119="","",'Controlo de Propinas'!C119) -> CM1 | D94: =IF(C94="","",IF(OR(C94="Maternelle",C94="Maternelle P1",C94="Maternelle P2",C94="Maternelle P3"),170000,IF(C94="CM2",250000,IF(C94="4eme",260000,170000)))) -> 170000 | O94: =IF(B94="","",SUM(E94:N94)) | P94: =IF(B94="","",IF(O94=0,"Pendente",IF(COUNTIF(E94:N94,">0")>=10,"Pago","Parcial")))
A95: =IF('Controlo de Propinas'!A120="","",'Controlo de Propinas'!A120) | B95: =IF('Controlo de Propinas'!B120="","",'Controlo de Propinas'!B120) | C95: =IF('Controlo de Propinas'!C120="","",'Controlo de Propinas'!C120) -> CM1 | D95: =IF(C95="","",IF(OR(C95="Maternelle",C95="Maternelle P1",C95="Maternelle P2",C95="Maternelle P3"),170000,IF(C95="CM2",250000,IF(C95="4eme",260000,170000)))) -> 170000 | O95: =IF(B95="","",SUM(E95:N95)) | P95: =IF(B95="","",IF(O95=0,"Pendente",IF(COUNTIF(E95:N95,">0")>=10,"Pago","Parcial")))
A96: =IF('Controlo de Propinas'!A121="","",'Controlo de Propinas'!A121) | B96: =IF('Controlo de Propinas'!B121="","",'Controlo de Propinas'!B121) | C96: =IF('Controlo de Propinas'!C121="","",'Controlo de Propinas'!C121) -> CM1 | D96: =IF(C96="","",IF(OR(C96="Maternelle",C96="Maternelle P1",C96="Maternelle P2",C96="Maternelle P3"),170000,IF(C96="CM2",250000,IF(C96="4eme",260000,170000)))) -> 170000 | O96: =IF(B96="","",SUM(E96:N96)) | P96: =IF(B96="","",IF(O96=0,"Pendente",IF(COUNTIF(E96:N96,">0")>=10,"Pago","Parcial")))
... A98: =IF('Controlo de Propinas'!A123="","",'Controlo de Propinas'!A123) | B98: =IF('Controlo de Propinas'!B123="","",'Controlo de Propinas'!B123) | C98: =IF('Controlo de Propinas'!C123="","",'Controlo de Propinas'!C123) -> CM1 | D98: =IF(C98="","",IF(OR(C98="Maternelle",C98="Maternelle P1",C98="Maternelle P2",C98="Maternelle P3"),170000,IF(C98="CM2",250000,IF(C98="4eme",260000,170000)))) -> 170000 | O98: =IF(B98="","",SUM(E98:N98)) | P98: =IF(B98="","",IF(O98=0,"Pendente",IF(COUNTIF(E98:N98,">0")>=10,"Pago","Parcial")))
A99: Subtotal | B99: =COUNTIF(B85:B98,"?*")&" alunos" -> 1 alunos | O99: =SUM(O85:O98) -> 0
A101: ▶ CM2 (até 75 alunos)
A102: ID | B102: Nome Aluno | C102: Turma | D102: Propina | E102: Set | F102: Out | G102: Nov | H102: Dez | I102: Jan | J102: Fev | K102: Mar | L102: Abr | M102: Mai | N102: Jun | O102: Total | P102: Status | Q102: Obs.
A103: =IF('Controlo de Propinas'!A129="","",'Controlo de Propinas'!A129) -> CM2-01 | B103: =IF('Controlo de Propinas'!B129="","",'Controlo de Propinas'!B129) -> Kaila Abigail Katata da Silva | C103: =IF('Controlo de Propinas'!C129="","",'Controlo de Propinas'!C129) -> CM2 | D103: =IF(C85="","",IF(OR(C85="Maternelle",C85="Maternelle P1",C85="Maternelle P2",C85="Maternelle P3"),170000,IF(C85="CM2",250000,IF(C85="4eme",260000,170000)))) -> 170000 | E103: 0 | F103: 0 | G103: 0 | H103: 0 | I103: 0 | J103: 0 | K103: 0 | L103: 0 | M103: 0 | N103: 0 | O103: =IF(B85="","",SUM(E85:N85)) -> 0 | P103: =IF(B85="","",IF(O85=0,"Pendente",IF(O85<D85,"Parcial","Pago"))) -> Pendente
A104: =IF('Controlo de Propinas'!A130="","",'Controlo de Propinas'!A130) -> CM2-02 | B104: =IF('Controlo de Propinas'!B130="","",'Controlo de Propinas'!B130) -> Pedro Henriques Simão dos Santos | C104: =IF('Controlo de Propinas'!C130="","",'Controlo de Propinas'!C130) -> CM2 | D104: =IF(C86="","",IF(OR(C86="Maternelle",C86="Maternelle P1",C86="Maternelle P2",C86="Maternelle P3"),170000,IF(C86="CM2",250000,IF(C86="4eme",260000,170000)))) -> 170000 | E104: 0 | F104: 0 | G104: 0 | H104: 0 | I104: 0 | J104: 0 | K104: 0 | L104: 0 | M104: 0 | N104: 0 | O104: =IF(B86="","",SUM(E86:N86)) | P104: =IF(B86="","",IF(O86=0,"Pendente",IF(O86<D86,"Parcial","Pago")))
A105: =IF('Controlo de Propinas'!A131="","",'Controlo de Propinas'!A131) -> CM2-03 | B105: =IF('Controlo de Propinas'!B131="","",'Controlo de Propinas'!B131) -> Keane António Teixeira Correia de Azevedo | C105: =IF('Controlo de Propinas'!C131="","",'Controlo de Propinas'!C131) -> CM2 | D105: =IF(C87="","",IF(OR(C87="Maternelle",C87="Maternelle P1",C87="Maternelle P2",C87="Maternelle P3"),170000,IF(C87="CM2",250000,IF(C87="4eme",260000,170000)))) -> 170000 | E105: 0 | F105: 0 | G105: 0 | H105: 0 | I105: 0 | J105: 0 | K105: 0 | L105: 0 | M105: 0 | N105: 0 | O105: =IF(B87="","",SUM(E87:N87)) | P105: =IF(B87="","",IF(O87=0,"Pendente",IF(O87<D87,"Parcial","Pago")))
A106: =IF('Controlo de Propinas'!A132="","",'Controlo de Propinas'!A132) -> CM2-04 | B106: =IF('Controlo de Propinas'!B132="","",'Controlo de Propinas'!B132) -> Márcio Uzziel Francisco Venâncio | C106: =IF('Controlo de Propinas'!C132="","",'Controlo de Propinas'!C132) -> CM2 | D106: =IF(C88="","",IF(OR(C88="Maternelle",C88="Maternelle P1",C88="Maternelle P2",C88="Maternelle P3"),170000,IF(C88="CM2",250000,IF(C88="4eme",260000,170000)))) -> 170000 | E106: 0 | F106: 0 | G106: 0 | H106: 0 | I106: 0 | J106: 0 | K106: 0 | L106: 0 | M106: 0 | N106: 0 | O106: =IF(B88="","",SUM(E88:N88)) | P106: =IF(B88="","",IF(O88=0,"Pendente",IF(O88<D88,"Parcial","Pago")))
A107: =IF('Controlo de Propinas'!A133="","",'Controlo de Propinas'!A133) | B107: =IF('Controlo de Propinas'!B133="","",'Controlo de Propinas'!B133) | C107: =IF('Controlo de Propinas'!C133="","",'Controlo de Propinas'!C133) -> CM2 | D107: =IF(C89="","",IF(OR(C89="Maternelle",C89="Maternelle P1",C89="Maternelle P2",C89="Maternelle P3"),170000,IF(C89="CM2",250000,IF(C89="4eme",260000,170000)))) -> 170000 | E107: 0 | F107: 0 | G107: 0 | H107: 0 | I107: 0 | J107: 0 | K107: 0 | L107: 0 | M107: 0 | N107: 0 | O107: =IF(B89="","",SUM(E89:N89)) | P107: =IF(B89="","",IF(O89=0,"Pendente",IF(O89<D89,"Parcial","Pago")))
A108: =IF('Controlo de Propinas'!A134="","",'Controlo de Propinas'!A134) | B108: =IF('Controlo de Propinas'!B134="","",'Controlo de Propinas'!B134) | C108: =IF('Controlo de Propinas'!C134="","",'Controlo de Propinas'!C134) -> CM2 | D108: =IF(C90="","",IF(OR(C90="Maternelle",C90="Maternelle P1",C90="Maternelle P2",C90="Maternelle P3"),170000,IF(C90="CM2",250000,IF(C90="4eme",260000,170000)))) -> 170000 | E108: 0 | F108: 0 | G108: 0 | H108: 0 | I108: 0 | J108: 0 | K108: 0 | L108: 0 | M108: 0 | N108: 0 | O108: =IF(B90="","",SUM(E90:N90)) | P108: =IF(B90="","",IF(O90=0,"Pendente",IF(O90<D90,"Parcial","Pago")))
A109: =IF('Controlo de Propinas'!A135="","",'Controlo de Propinas'!A135) | B109: =IF('Controlo de Propinas'!B135="","",'Controlo de Propinas'!B135) | C109: =IF('Controlo de Propinas'!C135="","",'Controlo de Propinas'!C135) -> CM2 | D109: =IF(C91="","",IF(OR(C91="Maternelle",C91="Maternelle P1",C91="Maternelle P2",C91="Maternelle P3"),170000,IF(C91="CM2",250000,IF(C91="4eme",260000,170000)))) -> 170000 | E109: 0 | F109: 0 | G109: 0 | H109: 0 | I109: 0 | J109: 0 | K109: 0 | L109: 0 | M109: 0 | N109: 0 | O109: =IF(B91="","",SUM(E91:N91)) | P109: =IF(B91="","",IF(O91=0,"Pendente",IF(O91<D91,"Parcial","Pago")))
A110: =IF('Controlo de Propinas'!A136="","",'Controlo de Propinas'!A136) | B110: =IF('Controlo de Propinas'!B136="","",'Controlo de Propinas'!B136) | C110: =IF('Controlo de Propinas'!C136="","",'Controlo de Propinas'!C136) -> CM2 | D110: =IF(C92="","",IF(OR(C92="Maternelle",C92="Maternelle P1",C92="Maternelle P2",C92="Maternelle P3"),170000,IF(C92="CM2",250000,IF(C92="4eme",260000,170000)))) -> 170000 | E110: 0 | F110: 0 | G110: 0 | H110: 0 | I110: 0 | J110: 0 | K110: 0 | L110: 0 | M110: 0 | N110: 0 | O110: =IF(B92="","",SUM(E92:N92)) | P110: =IF(B92="","",IF(O92=0,"Pendente",IF(O92<D92,"Parcial","Pago")))
A111: =IF('Controlo de Propinas'!A137="","",'Controlo de Propinas'!A137) | B111: =IF('Controlo de Propinas'!B137="","",'Controlo de Propinas'!B137) | C111: =IF('Controlo de Propinas'!C137="","",'Controlo de Propinas'!C137) -> CM2 | D111: =IF(C93="","",IF(OR(C93="Maternelle",C93="Maternelle P1",C93="Maternelle P2",C93="Maternelle P3"),170000,IF(C93="CM2",250000,IF(C93="4eme",260000,170000)))) -> 170000 | E111: 0 | F111: 0 | G111: 0 | H111: 0 | I111: 0 | J111: 0 | K111: 0 | L111: 0 | M111: 0 | N111: 0 | O111: =IF(B93="","",SUM(E93:N93)) | P111: =IF(B93="","",IF(O93=0,"Pendente",IF(O93<D93,"Parcial","Pago")))
A112: =IF('Controlo de Propinas'!A138="","",'Controlo de Propinas'!A138) | B112: =IF('Controlo de Propinas'!B138="","",'Controlo de Propinas'!B138) | C112: =IF('Controlo de Propinas'!C138="","",'Controlo de Propinas'!C138) -> CM2 | D112: =IF(C94="","",IF(OR(C94="Maternelle",C94="Maternelle P1",C94="Maternelle P2",C94="Maternelle P3"),170000,IF(C94="CM2",250000,IF(C94="4eme",260000,170000)))) -> 170000 | E112: 0 | F112: 0 | G112: 0 | H112: 0 | I112: 0 | J112: 0 | K112: 0 | L112: 0 | M112: 0 | N112: 0 | O112: =IF(B94="","",SUM(E94:N94)) | P112: =IF(B94="","",IF(O94=0,"Pendente",IF(O94<D94,"Parcial","Pago")))
A113: =IF('Controlo de Propinas'!A139="","",'Controlo de Propinas'!A139) | B113: =IF('Controlo de Propinas'!B139="","",'Controlo de Propinas'!B139) | C113: =IF('Controlo de Propinas'!C139="","",'Controlo de Propinas'!C139) -> CM2 | D113: =IF(C95="","",IF(OR(C95="Maternelle",C95="Maternelle P1",C95="Maternelle P2",C95="Maternelle P3"),170000,IF(C95="CM2",250000,IF(C95="4eme",260000,170000)))) -> 170000 | E113: 0 | F113: 0 | G113: 0 | H113: 0 | I113: 0 | J113: 0 | K113: 0 | L113: 0 | M113: 0 | N113: 0 | O113: =IF(B95="","",SUM(E95:N95)) | P113: =IF(B95="","",IF(O95=0,"Pendente",IF(O95<D95,"Parcial","Pago")))
A114: =IF('Controlo de Propinas'!A140="","",'Controlo de Propinas'!A140) | B114: =IF('Controlo de Propinas'!B140="","",'Controlo de Propinas'!B140) | C114: =IF('Controlo de Propinas'!C140="","",'Controlo de Propinas'!C140) -> CM2 | D114: =IF(C96="","",IF(OR(C96="Maternelle",C96="Maternelle P1",C96="Maternelle P2",C96="Maternelle P3"),170000,IF(C96="CM2",250000,IF(C96="4eme",260000,170000)))) -> 170000 | E114: 0 | F114: 0 | G114: 0 | H114: 0 | I114: 0 | J114: 0 | K114: 0 | L114: 0 | M114: 0 | N114: 0 | O114: =IF(B96="","",SUM(E96:N96)) | P114: =IF(B96="","",IF(O96=0,"Pendente",IF(O96<D96,"Parcial","Pago")))
... A146: =IF('Controlo de Propinas'!A172="","",'Controlo de Propinas'!A172) | B146: =IF('Controlo de Propinas'!B172="","",'Controlo de Propinas'!B172) | C146: =IF('Controlo de Propinas'!C172="","",'Controlo de Propinas'!C172) -> CM2 | D146: =IF(C128="","",IF(OR(C128="Maternelle",C128="Maternelle P1",C128="Maternelle P2",C128="Maternelle P3"),170000,IF(C128="CM2",250000,IF(C128="4eme",260000,170000)))) -> 250000 | E146: 0 | F146: 0 | G146: 0 | H146: 0 | I146: 0 | J146: 0 | K146: 0 | L146: 0 | M146: 0 | N146: 0 | O146: =IF(B128="","",SUM(E128:N128)) | P146: =IF(B128="","",IF(O128=0,"Pendente",IF(O128<D128,"Parcial","Pago")))
A147: =IF('Controlo de Propinas'!#REF!="","",'Controlo de Propinas'!#REF!) -> #REF! | B147: =IF('Controlo de Propinas'!#REF!="","",'Controlo de Propinas'!#REF!) -> #REF! | C147: =IF('Controlo de Propinas'!#REF!="","",'Controlo de Propinas'!#REF!) -> #REF! | D147: =IF(C129="","",IF(OR(C129="Maternelle",C129="Maternelle P1",C129="Maternelle P2",C129="Maternelle P3"),170000,IF(C129="CM2",250000,IF(C129="4eme",260000,170000)))) -> 250000 | E147: 0 | F147: 0 | G147: 0 | H147: 0 | I147: 0 | J147: 0 | K147: 0 | L147: 0 | M147: 0 | N147: 0 | O147: =IF(B129="","",SUM(E129:N129)) | P147: =IF(B129="","",IF(O129=0,"Pendente",IF(O129<D129,"Parcial","Pago")))
A148: =IF('Controlo de Propinas'!A173="","",'Controlo de Propinas'!A173) | B148: =IF('Controlo de Propinas'!B173="","",'Controlo de Propinas'!B173) | C148: =IF('Controlo de Propinas'!C173="","",'Controlo de Propinas'!C173) -> CM2 | D148: =IF(C130="","",IF(OR(C130="Maternelle",C130="Maternelle P1",C130="Maternelle P2",C130="Maternelle P3"),170000,IF(C130="CM2",250000,IF(C130="4eme",260000,170000)))) -> 250000 | E148: 0 | F148: 0 | G148: 0 | H148: 0 | I148: 0 | J148: 0 | K148: 0 | L148: 0 | M148: 0 | N148: 0 | O148: =IF(B130="","",SUM(E130:N130)) | P148: =IF(B130="","",IF(O130=0,"Pendente",IF(O130<D130,"Parcial","Pago")))
A149: =IF('Controlo de Propinas'!A174="","",'Controlo de Propinas'!A174) | B149: =IF('Controlo de Propinas'!B174="","",'Controlo de Propinas'!B174) | C149: =IF('Controlo de Propinas'!C174="","",'Controlo de Propinas'!C174) -> CM2 | D149: =IF(C131="","",IF(OR(C131="Maternelle",C131="Maternelle P1",C131="Maternelle P2",C131="Maternelle P3"),170000,IF(C131="CM2",250000,IF(C131="4eme",260000,170000)))) -> 250000 | E149: 0 | F149: 0 | G149: 0 | H149: 0 | I149: 0 | J149: 0 | K149: 0 | L149: 0 | M149: 0 | N149: 0 | O149: =IF(B131="","",SUM(E131:N131)) | P149: =IF(B131="","",IF(O131=0,"Pendente",IF(O131<D131,"Parcial","Pago")))
A150: =IF('Controlo de Propinas'!A175="","",'Controlo de Propinas'!A175) | B150: =IF('Controlo de Propinas'!B175="","",'Controlo de Propinas'!B175) | C150: =IF('Controlo de Propinas'!C175="","",'Controlo de Propinas'!C175) -> CM2 | D150: =IF(C132="","",IF(OR(C132="Maternelle",C132="Maternelle P1",C132="Maternelle P2",C132="Maternelle P3"),170000,IF(C132="CM2",250000,IF(C132="4eme",260000,170000)))) -> 250000 | E150: 0 | F150: 0 | G150: 0 | H150: 0 | I150: 0 | J150: 0 | K150: 0 | L150: 0 | M150: 0 | N150: 0 | O150: =IF(B132="","",SUM(E132:N132)) | P150: =IF(B132="","",IF(O132=0,"Pendente",IF(O132<D132,"Parcial","Pago")))
A151: =IF('Controlo de Propinas'!A176="","",'Controlo de Propinas'!A176) | B151: =IF('Controlo de Propinas'!B176="","",'Controlo de Propinas'!B176) | C151: =IF('Controlo de Propinas'!C176="","",'Controlo de Propinas'!C176) -> CM2 | D151: =IF(C133="","",IF(OR(C133="Maternelle",C133="Maternelle P1",C133="Maternelle P2",C133="Maternelle P3"),170000,IF(C133="CM2",250000,IF(C133="4eme",260000,170000)))) -> 250000 | E151: 0 | F151: 0 | G151: 0 | H151: 0 | I151: 0 | J151: 0 | K151: 0 | L151: 0 | M151: 0 | N151: 0 | O151: =IF(B133="","",SUM(E133:N133)) | P151: =IF(B133="","",IF(O133=0,"Pendente",IF(O133<D133,"Parcial","Pago")))
A152: =IF('Controlo de Propinas'!A177="","",'Controlo de Propinas'!A177) | B152: =IF('Controlo de Propinas'!B177="","",'Controlo de Propinas'!B177) | C152: =IF('Controlo de Propinas'!C177="","",'Controlo de Propinas'!C177) -> CM2 | D152: =IF(C134="","",IF(OR(C134="Maternelle",C134="Maternelle P1",C134="Maternelle P2",C134="Maternelle P3"),170000,IF(C134="CM2",250000,IF(C134="4eme",260000,170000)))) -> 250000 | E152: 0 | F152: 0 | G152: 0 | H152: 0 | I152: 0 | J152: 0 | K152: 0 | L152: 0 | M152: 0 | N152: 0 | O152: =IF(B134="","",SUM(E134:N134)) | P152: =IF(B134="","",IF(O134=0,"Pendente",IF(O134<D134,"Parcial","Pago")))
A153: =IF('Controlo de Propinas'!A178="","",'Controlo de Propinas'!A178) | B153: =IF('Controlo de Propinas'!B178="","",'Controlo de Propinas'!B178) | C153: =IF('Controlo de Propinas'!C178="","",'Controlo de Propinas'!C178) -> CM2 | D153: =IF(C135="","",IF(OR(C135="Maternelle",C135="Maternelle P1",C135="Maternelle P2",C135="Maternelle P3"),170000,IF(C135="CM2",250000,IF(C135="4eme",260000,170000)))) -> 250000 | E153: 0 | F153: 0 | G153: 0 | H153: 0 | I153: 0 | J153: 0 | K153: 0 | L153: 0 | M153: 0 | N153: 0 | O153: =IF(B135="","",SUM(E135:N135)) | P153: =IF(B135="","",IF(O135=0,"Pendente",IF(O135<D135,"Parcial","Pago")))
A154: =IF('Controlo de Propinas'!A179="","",'Controlo de Propinas'!A179) | B154: =IF('Controlo de Propinas'!B179="","",'Controlo de Propinas'!B179) | C154: =IF('Controlo de Propinas'!C179="","",'Controlo de Propinas'!C179) -> CM2 | D154: =IF(C136="","",IF(OR(C136="Maternelle",C136="Maternelle P1",C136="Maternelle P2",C136="Maternelle P3"),170000,IF(C136="CM2",250000,IF(C136="4eme",260000,170000)))) -> 250000 | E154: 0 | F154: 0 | G154: 0 | H154: 0 | I154: 0 | J154: 0 | K154: 0 | L154: 0 | M154: 0 | N154: 0 | O154: =IF(B136="","",SUM(E136:N136)) | P154: =IF(B136="","",IF(O136=0,"Pendente",IF(O136<D136,"Parcial","Pago")))
A155: =IF('Controlo de Propinas'!A180="","",'Controlo de Propinas'!A180) | B155: =IF('Controlo de Propinas'!B180="","",'Controlo de Propinas'!B180) | C155: =IF('Controlo de Propinas'!C180="","",'Controlo de Propinas'!C180) -> CM2 | D155: =IF(C137="","",IF(OR(C137="Maternelle",C137="Maternelle P1",C137="Maternelle P2",C137="Maternelle P3"),170000,IF(C137="CM2",250000,IF(C137="4eme",260000,170000)))) -> 250000 | E155: 0 | F155: 0 | G155: 0 | H155: 0 | I155: 0 | J155: 0 | K155: 0 | L155: 0 | M155: 0 | N155: 0 | O155: =IF(B137="","",SUM(E137:N137)) | P155: =IF(B137="","",IF(O137=0,"Pendente",IF(O137<D137,"Parcial","Pago")))
A156: =IF('Controlo de Propinas'!A181="","",'Controlo de Propinas'!A181) | B156: =IF('Controlo de Propinas'!B181="","",'Controlo de Propinas'!B181) | C156: =IF('Controlo de Propinas'!C181="","",'Controlo de Propinas'!C181) -> CM2 | D156: =IF(C138="","",IF(OR(C138="Maternelle",C138="Maternelle P1",C138="Maternelle P2",C138="Maternelle P3"),170000,IF(C138="CM2",250000,IF(C138="4eme",260000,170000)))) -> 250000 | E156: 0 | F156: 0 | G156: 0 | H156: 0 | I156: 0 | J156: 0 | K156: 0 | L156: 0 | M156: 0 | N156: 0 | O156: =IF(B138="","",SUM(E138:N138)) | P156: =IF(B138="","",IF(O138=0,"Pendente",IF(O138<D138,"Parcial","Pago")))
A157: =IF('Controlo de Propinas'!A182="","",'Controlo de Propinas'!A182) | B157: =IF('Controlo de Propinas'!B182="","",'Controlo de Propinas'!B182) | C157: =IF('Controlo de Propinas'!C182="","",'Controlo de Propinas'!C182) -> CM2 | D157: =IF(C139="","",IF(OR(C139="Maternelle",C139="Maternelle P1",C139="Maternelle P2",C139="Maternelle P3"),170000,IF(C139="CM2",250000,IF(C139="4eme",260000,170000)))) -> 250000 | E157: 0 | F157: 0 | G157: 0 | H157: 0 | I157: 0 | J157: 0 | K157: 0 | L157: 0 | M157: 0 | N157: 0 | O157: =IF(B139="","",SUM(E139:N139)) | P157: =IF(B139="","",IF(O139=0,"Pendente",IF(O139<D139,"Parcial","Pago")))
A158: =IF('Controlo de Propinas'!A183="","",'Controlo de Propinas'!A183) | B158: =IF('Controlo de Propinas'!B183="","",'Controlo de Propinas'!B183) | C158: =IF('Controlo de Propinas'!C183="","",'Controlo de Propinas'!C183) -> CM2 | D158: =IF(C140="","",IF(OR(C140="Maternelle",C140="Maternelle P1",C140="Maternelle P2",C140="Maternelle P3"),170000,IF(C140="CM2",250000,IF(C140="4eme",260000,170000)))) -> 250000 | E158: 0 | F158: 0 | G158: 0 | H158: 0 | I158: 0 | J158: 0 | K158: 0 | L158: 0 | M158: 0 | N158: 0 | O158: =IF(B140="","",SUM(E140:N140)) | P158: =IF(B140="","",IF(O140=0,"Pendente",IF(O140<D140,"Parcial","Pago")))
A159: =IF('Controlo de Propinas'!A184="","",'Controlo de Propinas'!A184) | B159: =IF('Controlo de Propinas'!B184="","",'Controlo de Propinas'!B184) | C159: =IF('Controlo de Propinas'!C184="","",'Controlo de Propinas'!C184) -> CM2 | D159: =IF(C141="","",IF(OR(C141="Maternelle",C141="Maternelle P1",C141="Maternelle P2",C141="Maternelle P3"),170000,IF(C141="CM2",250000,IF(C141="4eme",260000,170000)))) -> 250000 | E159: 0 | F159: 0 | G159: 0 | H159: 0 | I159: 0 | J159: 0 | K159: 0 | L159: 0 | M159: 0 | N159: 0 | O159: =IF(B141="","",SUM(E141:N141)) | P159: =IF(B141="","",IF(O141=0,"Pendente",IF(O141<D141,"Parcial","Pago")))
... A161: =IF('Controlo de Propinas'!A186="","",'Controlo de Propinas'!A186) | B161: =IF('Controlo de Propinas'!B186="","",'Controlo de Propinas'!B186) | C161: =IF('Controlo de Propinas'!C186="","",'Controlo de Propinas'!C186) -> CM2 | D161: =IF(C143="","",IF(OR(C143="Maternelle",C143="Maternelle P1",C143="Maternelle P2",C143="Maternelle P3"),170000,IF(C143="CM2",250000,IF(C143="4eme",260000,170000)))) -> 250000 | E161: 0 | F161: 0 | G161: 0 | H161: 0 | I161: 0 | J161: 0 | K161: 0 | L161: 0 | M161: 0 | N161: 0 | O161: =IF(B143="","",SUM(E143:N143)) | P161: =IF(B143="","",IF(O143=0,"Pendente",IF(O143<D143,"Parcial","Pago")))
A162: =IF('Controlo de Propinas'!A187="","",'Controlo de Propinas'!A187)
E163: 0 | F163: 0 | G163: 0 | H163: 0 | I163: 0 | J163: 0 | K163: 0 | L163: 0 | M163: 0 | N163: 0 | O163: =IF(B145="","",SUM(E145:N145)) | P163: =IF(B145="","",IF(O145=0,"Pendente",IF(O145<D145,"Parcial","Pago")))
E164: 0 | F164: 0 | G164: 0 | H164: 0 | I164: 0 | J164: 0 | K164: 0 | L164: 0 | M164: 0 | N164: 0 | O164: =IF(B146="","",SUM(E146:N146)) | P164: =IF(B146="","",IF(O146=0,"Pendente",IF(O146<D146,"Parcial","Pago")))
E165: 0 | F165: 0 | G165: 0 | H165: 0 | I165: 0 | J165: 0 | K165: 0 | L165: 0 | M165: 0 | N165: 0 | O165: =IF(B147="","",SUM(E147:N147)) -> #REF! | P165: =IF(B147="","",IF(O147=0,"Pendente",IF(O147<D147,"Parcial","Pago"))) -> #REF!
E166: 0 | F166: 0 | G166: 0 | H166: 0 | I166: 0 | J166: 0 | K166: 0 | L166: 0 | M166: 0 | N166: 0 | O166: =IF(B148="","",SUM(E148:N148)) | P166: =IF(B148="","",IF(O148=0,"Pendente",IF(O148<D148,"Parcial","Pago")))
E167: 0 | F167: 0 | G167: 0 | H167: 0 | I167: 0 | J167: 0 | K167: 0 | L167: 0 | M167: 0 | N167: 0 | O167: =IF(B149="","",SUM(E149:N149)) | P167: =IF(B149="","",IF(O149=0,"Pendente",IF(O149<D149,"Parcial","Pago")))
E168: 0 | F168: 0 | G168: 0 | H168: 0 | I168: 0 | J168: 0 | K168: 0 | L168: 0 | M168: 0 | N168: 0 | O168: =IF(B150="","",SUM(E150:N150)) | P168: =IF(B150="","",IF(O150=0,"Pendente",IF(O150<D150,"Parcial","Pago")))
E169: 0 | F169: 0 | G169: 0 | H169: 0 | I169: 0 | J169: 0 | K169: 0 | L169: 0 | M169: 0 | N169: 0 | O169: =IF(B151="","",SUM(E151:N151)) | P169: =IF(B151="","",IF(O151=0,"Pendente",IF(O151<D151,"Parcial","Pago")))
E170: 0 | F170: 0 | G170: 0 | H170: 0 | I170: 0 | J170: 0 | K170: 0 | L170: 0 | M170: 0 | N170: 0 | O170: =IF(B152="","",SUM(E152:N152)) | P170: =IF(B152="","",IF(O152=0,"Pendente",IF(O152<D152,"Parcial","Pago")))
E171: 0 | F171: 0 | G171: 0 | H171: 0 | I171: 0 | J171: 0 | K171: 0 | L171: 0 | M171: 0 | N171: 0 | O171: =IF(B153="","",SUM(E153:N153)) | P171: =IF(B153="","",IF(O153=0,"Pendente",IF(O153<D153,"Parcial","Pago")))
E172: 0 | F172: 0 | G172: 0 | H172: 0 | I172: 0 | J172: 0 | K172: 0 | L172: 0 | M172: 0 | N172: 0 | O172: =IF(B154="","",SUM(E154:N154)) | P172: =IF(B154="","",IF(O154=0,"Pendente",IF(O154<D154,"Parcial","Pago")))
E173: 0 | F173: 0 | G173: 0 | H173: 0 | I173: 0 | J173: 0 | K173: 0 | L173: 0 | M173: 0 | N173: 0 | O173: =IF(B155="","",SUM(E155:N155)) | P173: =IF(B155="","",IF(O155=0,"Pendente",IF(O155<D155,"Parcial","Pago")))
E174: 0 | F174: 0 | G174: 0 | H174: 0 | I174: 0 | J174: 0 | K174: 0 | L174: 0 | M174: 0 | N174: 0 | O174: =IF(B156="","",SUM(E156:N156)) | P174: =IF(B156="","",IF(O156=0,"Pendente",IF(O156<D156,"Parcial","Pago")))
... E177: 0 | F177: 0 | G177: 0 | H177: 0 | I177: 0 | J177: 0 | K177: 0 | L177: 0 | M177: 0 | N177: 0 | O177: =IF(B159="","",SUM(E159:N159)) | P177: =IF(B159="","",IF(O159=0,"Pendente",IF(O159<D159,"Parcial","Pago")))
A178: Subtotal | B178: =COUNTIF(B85:B159,"?*")&" alunos" -> 7 alunos | E178: =SUM(E85:E159) -> 0 | F178: =SUM(F85:F159) -> 0 | G178: =SUM(G85:G159) -> 0 | H178: =SUM(H85:H159) -> 0 | I178: =SUM(I85:I159) -> 0 | J178: =SUM(J85:J159) -> 0 | K178: =SUM(K85:K159) -> 0 | L178: =SUM(L85:L159) -> 0 | ... O178: =SUM(O85:O159) -> 0
A180: ▶ 6EME (Sixième) (até 75 alunos)
A181: ID | B181: Nome Aluno | C181: Turma | D181: Propina | E181: Set | F181: Out | G181: Nov | H181: Dez | I181: Jan | J181: Fev | K181: Mar | L181: Abr | M181: Mai | N181: Jun | O181: Total | P181: Status | Q181: Obs.
A182: =IF('Controlo de Propinas'!A192="","",'Controlo de Propinas'!A192) -> 6E-01 | B182: =IF('Controlo de Propinas'!B192="","",'Controlo de Propinas'!B192) -> Imayami Suriel António Cristovão De Sousa | C182: =IF('Controlo de Propinas'!C192="","",'Controlo de Propinas'!C192) -> 6eme | D182: =IF(C182="","",IF(OR(C182="Maternelle",C182="Maternelle P1",C182="Maternelle P2",C182="Maternelle P3"),170000,IF(C182="CM2",250000,IF(C182="4eme",260000,170000)))) -> 170000 | O182: =IF(B182="","",SUM(E182:N182)) -> 0 | P182: =IF(B182="","",IF(O182=0,"Pendente",IF(COUNTIF(E182:N182,">0")>=10,"Pago","Parcial"))) -> Pendente
A183: =IF('Controlo de Propinas'!A193="","",'Controlo de Propinas'!A193) | B183: =IF('Controlo de Propinas'!B193="","",'Controlo de Propinas'!B193) | C183: =IF('Controlo de Propinas'!C193="","",'Controlo de Propinas'!C193) -> 6eme | D183: =IF(C183="","",IF(OR(C183="Maternelle",C183="Maternelle P1",C183="Maternelle P2",C183="Maternelle P3"),170000,IF(C183="CM2",250000,IF(C183="4eme",260000,170000)))) -> 170000 | O183: =IF(B183="","",SUM(E183:N183)) | P183: =IF(B183="","",IF(O183=0,"Pendente",IF(COUNTIF(E183:N183,">0")>=10,"Pago","Parcial")))
A184: =IF('Controlo de Propinas'!A194="","",'Controlo de Propinas'!A194) | B184: =IF('Controlo de Propinas'!B194="","",'Controlo de Propinas'!B194) | C184: =IF('Controlo de Propinas'!C194="","",'Controlo de Propinas'!C194) -> 6eme | D184: =IF(C184="","",IF(OR(C184="Maternelle",C184="Maternelle P1",C184="Maternelle P2",C184="Maternelle P3"),170000,IF(C184="CM2",250000,IF(C184="4eme",260000,170000)))) -> 170000 | O184: =IF(B184="","",SUM(E184:N184)) | P184: =IF(B184="","",IF(O184=0,"Pendente",IF(COUNTIF(E184:N184,">0")>=10,"Pago","Parcial")))
A185: =IF('Controlo de Propinas'!A195="","",'Controlo de Propinas'!A195) | B185: =IF('Controlo de Propinas'!B195="","",'Controlo de Propinas'!B195) | C185: =IF('Controlo de Propinas'!C195="","",'Controlo de Propinas'!C195) -> 6eme | D185: =IF(C185="","",IF(OR(C185="Maternelle",C185="Maternelle P1",C185="Maternelle P2",C185="Maternelle P3"),170000,IF(C185="CM2",250000,IF(C185="4eme",260000,170000)))) -> 170000 | O185: =IF(B185="","",SUM(E185:N185)) | P185: =IF(B185="","",IF(O185=0,"Pendente",IF(COUNTIF(E185:N185,">0")>=10,"Pago","Parcial")))
A186: =IF('Controlo de Propinas'!A196="","",'Controlo de Propinas'!A196) | B186: =IF('Controlo de Propinas'!B196="","",'Controlo de Propinas'!B196) | C186: =IF('Controlo de Propinas'!C196="","",'Controlo de Propinas'!C196) -> 6eme | D186: =IF(C186="","",IF(OR(C186="Maternelle",C186="Maternelle P1",C186="Maternelle P2",C186="Maternelle P3"),170000,IF(C186="CM2",250000,IF(C186="4eme",260000,170000)))) -> 170000 | O186: =IF(B186="","",SUM(E186:N186)) | P186: =IF(B186="","",IF(O186=0,"Pendente",IF(COUNTIF(E186:N186,">0")>=10,"Pago","Parcial")))
A187: =IF('Controlo de Propinas'!A197="","",'Controlo de Propinas'!A197) | B187: =IF('Controlo de Propinas'!B197="","",'Controlo de Propinas'!B197) | C187: =IF('Controlo de Propinas'!C197="","",'Controlo de Propinas'!C197) -> 6eme | D187: =IF(C187="","",IF(OR(C187="Maternelle",C187="Maternelle P1",C187="Maternelle P2",C187="Maternelle P3"),170000,IF(C187="CM2",250000,IF(C187="4eme",260000,170000)))) -> 170000 | O187: =IF(B187="","",SUM(E187:N187)) | P187: =IF(B187="","",IF(O187=0,"Pendente",IF(COUNTIF(E187:N187,">0")>=10,"Pago","Parcial")))
A188: =IF('Controlo de Propinas'!A198="","",'Controlo de Propinas'!A198) | B188: =IF('Controlo de Propinas'!B198="","",'Controlo de Propinas'!B198) | C188: =IF('Controlo de Propinas'!C198="","",'Controlo de Propinas'!C198) -> 6eme | D188: =IF(C188="","",IF(OR(C188="Maternelle",C188="Maternelle P1",C188="Maternelle P2",C188="Maternelle P3"),170000,IF(C188="CM2",250000,IF(C188="4eme",260000,170000)))) -> 170000 | O188: =IF(B188="","",SUM(E188:N188)) | P188: =IF(B188="","",IF(O188=0,"Pendente",IF(COUNTIF(E188:N188,">0")>=10,"Pago","Parcial")))
A189: =IF('Controlo de Propinas'!A199="","",'Controlo de Propinas'!A199) | B189: =IF('Controlo de Propinas'!B199="","",'Controlo de Propinas'!B199) | C189: =IF('Controlo de Propinas'!C199="","",'Controlo de Propinas'!C199) -> 6eme | D189: =IF(C189="","",IF(OR(C189="Maternelle",C189="Maternelle P1",C189="Maternelle P2",C189="Maternelle P3"),170000,IF(C189="CM2",250000,IF(C189="4eme",260000,170000)))) -> 170000 | O189: =IF(B189="","",SUM(E189:N189)) | P189: =IF(B189="","",IF(O189=0,"Pendente",IF(COUNTIF(E189:N189,">0")>=10,"Pago","Parcial")))
A190: =IF('Controlo de Propinas'!A200="","",'Controlo de Propinas'!A200) | B190: =IF('Controlo de Propinas'!B200="","",'Controlo de Propinas'!B200) | C190: =IF('Controlo de Propinas'!C200="","",'Controlo de Propinas'!C200) -> 6eme | D190: =IF(C190="","",IF(OR(C190="Maternelle",C190="Maternelle P1",C190="Maternelle P2",C190="Maternelle P3"),170000,IF(C190="CM2",250000,IF(C190="4eme",260000,170000)))) -> 170000 | O190: =IF(B190="","",SUM(E190:N190)) | P190: =IF(B190="","",IF(O190=0,"Pendente",IF(COUNTIF(E190:N190,">0")>=10,"Pago","Parcial")))
A191: =IF('Controlo de Propinas'!A201="","",'Controlo de Propinas'!A201) | B191: =IF('Controlo de Propinas'!B201="","",'Controlo de Propinas'!B201) | C191: =IF('Controlo de Propinas'!C201="","",'Controlo de Propinas'!C201) -> 6eme | D191: =IF(C191="","",IF(OR(C191="Maternelle",C191="Maternelle P1",C191="Maternelle P2",C191="Maternelle P3"),170000,IF(C191="CM2",250000,IF(C191="4eme",260000,170000)))) -> 170000 | O191: =IF(B191="","",SUM(E191:N191)) | P191: =IF(B191="","",IF(O191=0,"Pendente",IF(COUNTIF(E191:N191,">0")>=10,"Pago","Parcial")))
A192: =IF('Controlo de Propinas'!A202="","",'Controlo de Propinas'!A202) | B192: =IF('Controlo de Propinas'!B202="","",'Controlo de Propinas'!B202) | C192: =IF('Controlo de Propinas'!C202="","",'Controlo de Propinas'!C202) -> 6eme | D192: =IF(C192="","",IF(OR(C192="Maternelle",C192="Maternelle P1",C192="Maternelle P2",C192="Maternelle P3"),170000,IF(C192="CM2",250000,IF(C192="4eme",260000,170000)))) -> 170000 | O192: =IF(B192="","",SUM(E192:N192)) | P192: =IF(B192="","",IF(O192=0,"Pendente",IF(COUNTIF(E192:N192,">0")>=10,"Pago","Parcial")))
A193: =IF('Controlo de Propinas'!A203="","",'Controlo de Propinas'!A203) | B193: =IF('Controlo de Propinas'!B203="","",'Controlo de Propinas'!B203) | C193: =IF('Controlo de Propinas'!C203="","",'Controlo de Propinas'!C203) -> 6eme | D193: =IF(C193="","",IF(OR(C193="Maternelle",C193="Maternelle P1",C193="Maternelle P2",C193="Maternelle P3"),170000,IF(C193="CM2",250000,IF(C193="4eme",260000,170000)))) -> 170000 | O193: =IF(B193="","",SUM(E193:N193)) | P193: =IF(B193="","",IF(O193=0,"Pendente",IF(COUNTIF(E193:N193,">0")>=10,"Pago","Parcial")))
... A195: =IF('Controlo de Propinas'!A205="","",'Controlo de Propinas'!A205) | B195: =IF('Controlo de Propinas'!B205="","",'Controlo de Propinas'!B205) | C195: =IF('Controlo de Propinas'!C205="","",'Controlo de Propinas'!C205) -> 6eme | D195: =IF(C195="","",IF(OR(C195="Maternelle",C195="Maternelle P1",C195="Maternelle P2",C195="Maternelle P3"),170000,IF(C195="CM2",250000,IF(C195="4eme",260000,170000)))) -> 170000 | O195: =IF(B195="","",SUM(E195:N195)) | P195: =IF(B195="","",IF(O195=0,"Pendente",IF(COUNTIF(E195:N195,">0")>=10,"Pago","Parcial")))
A196: Subtotal | B196: =COUNTIF(B182:B195,"?*")&" alunos" -> 1 alunos | O196: =SUM(O182:O195) -> 0
A198: ▶ 4EME (até 75 alunos)
A199: ID | B199: Nome Aluno | C199: Turma | D199: Propina | E199: Set | F199: Out | G199: Nov | H199: Dez | I199: Jan | J199: Fev | K199: Mar | L199: Abr | M199: Mai | N199: Jun | O199: Total | P199: Status | Q199: Obs.
A200: =IF('Controlo de Propinas'!A210="","",'Controlo de Propinas'!A210) -> 4E-01 | B200: =IF('Controlo de Propinas'!B210="","",'Controlo de Propinas'!B210) -> Nathaniel Dialude Calei da Costa | C200: =IF('Controlo de Propinas'!C210="","",'Controlo de Propinas'!C210) -> 4eme | D200: =IF(C164="","",IF(OR(C164="Maternelle",C164="Maternelle P1",C164="Maternelle P2",C164="Maternelle P3"),170000,IF(C164="CM2",250000,IF(C164="4eme",260000,170000)))) | E200: 0 | F200: 0 | G200: 0 | H200: 0 | I200: 0 | J200: 0 | K200: 0 | L200: 0 | M200: 0 | N200: 0 | O200: =IF(B164="","",SUM(E164:N164)) | P200: =IF(B164="","",IF(O164=0,"Pendente",IF(O164<D164,"Parcial","Pago")))
A201: =IF('Controlo de Propinas'!A211="","",'Controlo de Propinas'!A211) | B201: =IF('Controlo de Propinas'!B211="","",'Controlo de Propinas'!B211) | C201: =IF('Controlo de Propinas'!C211="","",'Controlo de Propinas'!C211) -> 4eme | D201: =IF(C165="","",IF(OR(C165="Maternelle",C165="Maternelle P1",C165="Maternelle P2",C165="Maternelle P3"),170000,IF(C165="CM2",250000,IF(C165="4eme",260000,170000)))) | E201: 0 | F201: 0 | G201: 0 | H201: 0 | I201: 0 | J201: 0 | K201: 0 | L201: 0 | M201: 0 | N201: 0 | O201: =IF(B165="","",SUM(E165:N165)) | P201: =IF(B165="","",IF(O165=0,"Pendente",IF(O165<D165,"Parcial","Pago")))
A202: =IF('Controlo de Propinas'!A212="","",'Controlo de Propinas'!A212) | B202: =IF('Controlo de Propinas'!B212="","",'Controlo de Propinas'!B212) | C202: =IF('Controlo de Propinas'!C212="","",'Controlo de Propinas'!C212) -> 4eme | D202: =IF(C166="","",IF(OR(C166="Maternelle",C166="Maternelle P1",C166="Maternelle P2",C166="Maternelle P3"),170000,IF(C166="CM2",250000,IF(C166="4eme",260000,170000)))) | E202: 0 | F202: 0 | G202: 0 | H202: 0 | I202: 0 | J202: 0 | K202: 0 | L202: 0 | M202: 0 | N202: 0 | O202: =IF(B166="","",SUM(E166:N166)) | P202: =IF(B166="","",IF(O166=0,"Pendente",IF(O166<D166,"Parcial","Pago")))
A203: =IF('Controlo de Propinas'!A213="","",'Controlo de Propinas'!A213) | B203: =IF('Controlo de Propinas'!B213="","",'Controlo de Propinas'!B213) | C203: =IF('Controlo de Propinas'!C213="","",'Controlo de Propinas'!C213) -> 4eme | D203: =IF(C167="","",IF(OR(C167="Maternelle",C167="Maternelle P1",C167="Maternelle P2",C167="Maternelle P3"),170000,IF(C167="CM2",250000,IF(C167="4eme",260000,170000)))) | E203: 0 | F203: 0 | G203: 0 | H203: 0 | I203: 0 | J203: 0 | K203: 0 | L203: 0 | M203: 0 | N203: 0 | O203: =IF(B167="","",SUM(E167:N167)) | P203: =IF(B167="","",IF(O167=0,"Pendente",IF(O167<D167,"Parcial","Pago")))
...

Sheet Cadastro de Alunos
A1: CADASTRO DE ALUNOS – 2026/2027
A2: Verde = puxado do Controlo de Propinas | Amarelo = preencher (Responsável, Contacto, Endereço, Alergias, Medicação)
A4: ▶ MATERNELLE
A5: ID | B5: Nome Aluno | C5: Turma | D5: Responsável | E5: Contacto | F5: Data Matrícula | G5: Propina Mensal | H5: Atividades | I5: Endereço | J5: Tem Alergias? | K5: Quais Alergias? | L5: Toma Medicação?
A6: =IF('Controlo de Propinas'!A6="","",'Controlo de Propinas'!A6) -> P1-01 | B6: =IF('Controlo de Propinas'!B6="","",'Controlo de Propinas'!B6) -> Hazail Epandi Calei da Costa | C6: =IF('Controlo de Propinas'!C6="","",'Controlo de Propinas'!C6) -> Maternelle | F6: =IF('Controlo de Propinas'!K6="","",'Controlo de Propinas'!K6) -> 46229 | G6: =IF(C6="","",IF(OR(C6="Maternelle",C6="Maternelle P1",C6="Maternelle P2",C6="Maternelle P3"),170000,IF(C6="CM2",250000,IF(C6="4eme",260000,170000)))) -> 170000
A7: =IF('Controlo de Propinas'!A7="","",'Controlo de Propinas'!A7) -> P1-02 | B7: =IF('Controlo de Propinas'!B7="","",'Controlo de Propinas'!B7) -> Erick Libânio Sebastião da Silva | C7: =IF('Controlo de Propinas'!C7="","",'Controlo de Propinas'!C7) -> Maternelle P1 | F7: =IF('Controlo de Propinas'!K7="","",'Controlo de Propinas'!K7) -> 46235 | G7: =IF(C7="","",IF(OR(C7="Maternelle",C7="Maternelle P1",C7="Maternelle P2",C7="Maternelle P3"),170000,IF(C7="CM2",250000,IF(C7="4eme",260000,170000)))) -> 170000
A8: =IF('Controlo de Propinas'!A8="","",'Controlo de Propinas'!A8) -> P2-03 | B8: =IF('Controlo de Propinas'!B8="","",'Controlo de Propinas'!B8) -> Eloa Marina Sebastião da Silva | C8: =IF('Controlo de Propinas'!C8="","",'Controlo de Propinas'!C8) -> Maternelle P2 | F8: =IF('Controlo de Propinas'!K8="","",'Controlo de Propinas'!K8) -> 46235 | G8: =IF(C8="","",IF(OR(C8="Maternelle",C8="Maternelle P1",C8="Maternelle P2",C8="Maternelle P3"),170000,IF(C8="CM2",250000,IF(C8="4eme",260000,170000)))) -> 170000
A9: =IF('Controlo de Propinas'!A9="","",'Controlo de Propinas'!A9) -> P2-04 | B9: =IF('Controlo de Propinas'!B9="","",'Controlo de Propinas'!B9) -> Ivander Trindade Bernardo Clementino | C9: =IF('Controlo de Propinas'!C9="","",'Controlo de Propinas'!C9) -> Maternelle P2 | F9: =IF('Controlo de Propinas'!K9="","",'Controlo de Propinas'!K9) -> 46240 | G9: =IF(C9="","",IF(OR(C9="Maternelle",C9="Maternelle P1",C9="Maternelle P2",C9="Maternelle P3"),170000,IF(C9="CM2",250000,IF(C9="4eme",260000,170000)))) -> 170000
A10: =IF('Controlo de Propinas'!A10="","",'Controlo de Propinas'!A10) -> P3-05 | B10: =IF('Controlo de Propinas'!B10="","",'Controlo de Propinas'!B10) -> Gael Hanji Ventura Quimbundo | C10: =IF('Controlo de Propinas'!C10="","",'Controlo de Propinas'!C10) -> Maternelle P3 | F10: =IF('Controlo de Propinas'!K10="","",'Controlo de Propinas'!K10) -> 46237 | G10: =IF(C10="","",IF(OR(C10="Maternelle",C10="Maternelle P1",C10="Maternelle P2",C10="Maternelle P3"),170000,IF(C10="CM2",250000,IF(C10="4eme",260000,170000)))) -> 170000
A11: =IF('Controlo de Propinas'!A11="","",'Controlo de Propinas'!A11) -> P3-06 | B11: =IF('Controlo de Propinas'!B11="","",'Controlo de Propinas'!B11) -> Ivanna Chayane Bernardo Clementino | C11: =IF('Controlo de Propinas'!C11="","",'Controlo de Propinas'!C11) -> Maternelle P3 | F11: =IF('Controlo de Propinas'!K11="","",'Controlo de Propinas'!K11) -> 46240 | G11: =IF(C11="","",IF(OR(C11="Maternelle",C11="Maternelle P1",C11="Maternelle P2",C11="Maternelle P3"),170000,IF(C11="CM2",250000,IF(C11="4eme",260000,170000)))) -> 170000
A12: =IF('Controlo de Propinas'!A12="","",'Controlo de Propinas'!A12) -> P3-07 | B12: =IF('Controlo de Propinas'!B12="","",'Controlo de Propinas'!B12) -> Wendy Aryanne Chimuco Sabino | C12: =IF('Controlo de Propinas'!C12="","",'Controlo de Propinas'!C12) -> Maternelle P3 | F12: =IF('Controlo de Propinas'!K12="","",'Controlo de Propinas'!K12) -> 46232 | G12: =IF(C12="","",IF(OR(C12="Maternelle",C12="Maternelle P1",C12="Maternelle P2",C12="Maternelle P3"),170000,IF(C12="CM2",250000,IF(C12="4eme",260000,170000)))) -> 170000
A13: =IF('Controlo de Propinas'!A13="","",'Controlo de Propinas'!A13) -> P1-08 | B13: =IF('Controlo de Propinas'!B13="","",'Controlo de Propinas'!B13) -> Kesane Aimé Teixeira Correia de Azevedo | C13: =IF('Controlo de Propinas'!C13="","",'Controlo de Propinas'!C13) -> Maternelle P1 | F13: =IF('Controlo de Propinas'!K13="","",'Controlo de Propinas'!K13) -> 46255 | G13: =IF(C13="","",IF(OR(C13="Maternelle",C13="Maternelle P1",C13="Maternelle P2",C13="Maternelle P3"),170000,IF(C13="CM2",250000,IF(C13="4eme",260000,170000)))) -> 170000
A14: =IF('Controlo de Propinas'!A14="","",'Controlo de Propinas'!A14) -> P3-09 | B14: =IF('Controlo de Propinas'!B14="","",'Controlo de Propinas'!B14) -> Kuami Hazael Francisco Venâncio | C14: =IF('Controlo de Propinas'!C14="","",'Controlo de Propinas'!C14) -> Maternelle P3 | F14: =IF('Controlo de Propinas'!K14="","",'Controlo de Propinas'!K14) -> 46245 | G14: =IF(C14="","",IF(OR(C14="Maternelle",C14="Maternelle P1",C14="Maternelle P2",C14="Maternelle P3"),170000,IF(C14="CM2",250000,IF(C14="4eme",260000,170000)))) -> 170000
A15: =IF('Controlo de Propinas'!A15="","",'Controlo de Propinas'!A15) | B15: =IF('Controlo de Propinas'!B15="","",'Controlo de Propinas'!B15) | C15: =IF('Controlo de Propinas'!C15="","",'Controlo de Propinas'!C15) | F15: =IF('Controlo de Propinas'!K15="","",'Controlo de Propinas'!K15) | G15: =IF(C15="","",IF(OR(C15="Maternelle",C15="Maternelle P1",C15="Maternelle P2",C15="Maternelle P3"),170000,IF(C15="CM2",250000,IF(C15="4eme",260000,170000))))
A16: =IF('Controlo de Propinas'!A16="","",'Controlo de Propinas'!A16) | B16: =IF('Controlo de Propinas'!B16="","",'Controlo de Propinas'!B16) | C16: =IF('Controlo de Propinas'!C16="","",'Controlo de Propinas'!C16) | F16: =IF('Controlo de Propinas'!K16="","",'Controlo de Propinas'!K16) | G16: =IF(C16="","",IF(OR(C16="Maternelle",C16="Maternelle P1",C16="Maternelle P2",C16="Maternelle P3"),170000,IF(C16="CM2",250000,IF(C16="4eme",260000,170000))))
A17: =IF('Controlo de Propinas'!A17="","",'Controlo de Propinas'!A17) | B17: =IF('Controlo de Propinas'!B17="","",'Controlo de Propinas'!B17) | C17: =IF('Controlo de Propinas'!C17="","",'Controlo de Propinas'!C17) | F17: =IF('Controlo de Propinas'!K17="","",'Controlo de Propinas'!K17) | G17: =IF(C17="","",IF(OR(C17="Maternelle",C17="Maternelle P1",C17="Maternelle P2",C17="Maternelle P3"),170000,IF(C17="CM2",250000,IF(C17="4eme",260000,170000))))
... A105: =IF('Controlo de Propinas'!A105="","",'Controlo de Propinas'!A105) | B105: =IF('Controlo de Propinas'!B105="","",'Controlo de Propinas'!B105) | C105: =IF('Controlo de Propinas'!C105="","",'Controlo de Propinas'!C105) | F105: =IF('Controlo de Propinas'!K105="","",'Controlo de Propinas'!K105) | G105: =IF(C105="","",IF(OR(C105="Maternelle",C105="Maternelle P1",C105="Maternelle P2",C105="Maternelle P3"),170000,IF(C105="CM2",250000,IF(C105="4eme",260000,170000))))
A106: Subtotal | B106: =COUNTIF(B6:B105,"?*")&" alunos" -> 9 alunos
A108: ▶ CM1
A109: ID | B109: Nome Aluno | C109: Turma | D109: Responsável | E109: Contacto | F109: Data Matrícula | G109: Propina Mensal | H109: Atividades | I109: Endereço | J109: Tem Alergias? | K109: Quais Alergias? | L109: Toma Medicação?
A110: =IF('Controlo de Propinas'!A110="","",'Controlo de Propinas'!A110) -> CM1-01 | B110: =IF('Controlo de Propinas'!B110="","",'Controlo de Propinas'!B110) -> Crisber Uluwami António Cristovão De Sousa | C110: =IF('Controlo de Propinas'!C110="","",'Controlo de Propinas'!C110) -> CM1
A111: =IF('Controlo de Propinas'!A111="","",'Controlo de Propinas'!A111) -> CM1-02 | B111: =IF('Controlo de Propinas'!B111="","",'Controlo de Propinas'!B111) | C111: =IF('Controlo de Propinas'!C111="","",'Controlo de Propinas'!C111) -> CM1
A112: =IF('Controlo de Propinas'!A112="","",'Controlo de Propinas'!A112) | B112: =IF('Controlo de Propinas'!B112="","",'Controlo de Propinas'!B112) | C112: =IF('Controlo de Propinas'!C112="","",'Controlo de Propinas'!C112) -> CM1
A113: =IF('Controlo de Propinas'!A113="","",'Controlo de Propinas'!A113) | B113: =IF('Controlo de Propinas'!B113="","",'Controlo de Propinas'!B113) | C113: =IF('Controlo de Propinas'!C113="","",'Controlo de Propinas'!C113) -> CM1
A114: =IF('Controlo de Propinas'!A114="","",'Controlo de Propinas'!A114) | B114: =IF('Controlo de Propinas'!B114="","",'Controlo de Propinas'!B114) | C114: =IF('Controlo de Propinas'!C114="","",'Controlo de Propinas'!C114) -> CM1
A115: =IF('Controlo de Propinas'!A115="","",'Controlo de Propinas'!A115) | B115: =IF('Controlo de Propinas'!B115="","",'Controlo de Propinas'!B115) | C115: =IF('Controlo de Propinas'!C115="","",'Controlo de Propinas'!C115) -> CM1
A116: =IF('Controlo de Propinas'!A116="","",'Controlo de Propinas'!A116) | B116: =IF('Controlo de Propinas'!B116="","",'Controlo de Propinas'!B116) | C116: =IF('Controlo de Propinas'!C116="","",'Controlo de Propinas'!C116) -> CM1
A117: =IF('Controlo de Propinas'!A117="","",'Controlo de Propinas'!A117) | B117: =IF('Controlo de Propinas'!B117="","",'Controlo de Propinas'!B117) | C117: =IF('Controlo de Propinas'!C117="","",'Controlo de Propinas'!C117) -> CM1
A118: =IF('Controlo de Propinas'!A118="","",'Controlo de Propinas'!A118) | B118: =IF('Controlo de Propinas'!B118="","",'Controlo de Propinas'!B118) | C118: =IF('Controlo de Propinas'!C118="","",'Controlo de Propinas'!C118) -> CM1
A119: =IF('Controlo de Propinas'!A119="","",'Controlo de Propinas'!A119) | B119: =IF('Controlo de Propinas'!B119="","",'Controlo de Propinas'!B119) | C119: =IF('Controlo de Propinas'!C119="","",'Controlo de Propinas'!C119) -> CM1
A120: =IF('Controlo de Propinas'!A120="","",'Controlo de Propinas'!A120) | B120: =IF('Controlo de Propinas'!B120="","",'Controlo de Propinas'!B120) | C120: =IF('Controlo de Propinas'!C120="","",'Controlo de Propinas'!C120) -> CM1
A121: =IF('Controlo de Propinas'!A121="","",'Controlo de Propinas'!A121) | B121: =IF('Controlo de Propinas'!B121="","",'Controlo de Propinas'!B121) | C121: =IF('Controlo de Propinas'!C121="","",'Controlo de Propinas'!C121) -> CM1
... A123: =IF('Controlo de Propinas'!A123="","",'Controlo de Propinas'!A123) | B123: =IF('Controlo de Propinas'!B123="","",'Controlo de Propinas'!B123) | C123: =IF('Controlo de Propinas'!C123="","",'Controlo de Propinas'!C123) -> CM1
A124: Subtotal | B124: =COUNTIF(B110:B123,"?*")&" alunos" -> 1 alunos
A126: ▶ CM2
A127: ID | B127: Nome Aluno | C127: Turma | D127: Responsável | E127: Contacto | F127: Data Matrícula | G127: Propina Mensal | H127: Atividades | I127: Endereço | J127: Tem Alergias? | K127: Quais Alergias? | L127: Toma Medicação?
A128: =IF('Controlo de Propinas'!A129="","",'Controlo de Propinas'!A129) -> CM2-01 | B128: =IF('Controlo de Propinas'!B129="","",'Controlo de Propinas'!B129) -> Kaila Abigail Katata da Silva | C128: =IF('Controlo de Propinas'!C129="","",'Controlo de Propinas'!C129) -> CM2 | F128: =IF('Controlo de Propinas'!K129="","",'Controlo de Propinas'!K129) -> 46230 | G128: =IF(C110="","",IF(OR(C110="Maternelle",C110="Maternelle P1",C110="Maternelle P2",C110="Maternelle P3"),170000,IF(C110="CM2",250000,IF(C110="4eme",260000,170000)))) -> 170000
A129: =IF('Controlo de Propinas'!A130="","",'Controlo de Propinas'!A130) -> CM2-02 | B129: =IF('Controlo de Propinas'!B130="","",'Controlo de Propinas'!B130) -> Pedro Henriques Simão dos Santos | C129: =IF('Controlo de Propinas'!C130="","",'Controlo de Propinas'!C130) -> CM2 | F129: =IF('Controlo de Propinas'!K130="","",'Controlo de Propinas'!K130) -> 46229 | G129: =IF(C111="","",IF(OR(C111="Maternelle",C111="Maternelle P1",C111="Maternelle P2",C111="Maternelle P3"),170000,IF(C111="CM2",250000,IF(C111="4eme",260000,170000)))) -> 170000
A130: =IF('Controlo de Propinas'!A131="","",'Controlo de Propinas'!A131) -> CM2-03 | B130: =IF('Controlo de Propinas'!B131="","",'Controlo de Propinas'!B131) -> Keane António Teixeira Correia de Azevedo | C130: =IF('Controlo de Propinas'!C131="","",'Controlo de Propinas'!C131) -> CM2 | F130: =IF('Controlo de Propinas'!K131="","",'Controlo de Propinas'!K131) -> 46239 | G130: =IF(C112="","",IF(OR(C112="Maternelle",C112="Maternelle P1",C112="Maternelle P2",C112="Maternelle P3"),170000,IF(C112="CM2",250000,IF(C112="4eme",260000,170000)))) -> 170000
A131: =IF('Controlo de Propinas'!A132="","",'Controlo de Propinas'!A132) -> CM2-04 | B131: =IF('Controlo de Propinas'!B132="","",'Controlo de Propinas'!B132) -> Márcio Uzziel Francisco Venâncio | C131: =IF('Controlo de Propinas'!C132="","",'Controlo de Propinas'!C132) -> CM2 | F131: =IF('Controlo de Propinas'!K132="","",'Controlo de Propinas'!K132) -> 46245 | G131: =IF(C113="","",IF(OR(C113="Maternelle",C113="Maternelle P1",C113="Maternelle P2",C113="Maternelle P3"),170000,IF(C113="CM2",250000,IF(C113="4eme",260000,170000)))) -> 170000
A132: =IF('Controlo de Propinas'!A133="","",'Controlo de Propinas'!A133) | B132: =IF('Controlo de Propinas'!B133="","",'Controlo de Propinas'!B133) | C132: =IF('Controlo de Propinas'!C133="","",'Controlo de Propinas'!C133) -> CM2 | F132: =IF('Controlo de Propinas'!K133="","",'Controlo de Propinas'!K133) | G132: =IF(C114="","",IF(OR(C114="Maternelle",C114="Maternelle P1",C114="Maternelle P2",C114="Maternelle P3"),170000,IF(C114="CM2",250000,IF(C114="4eme",260000,170000)))) -> 170000
A133: =IF('Controlo de Propinas'!A134="","",'Controlo de Propinas'!A134) | B133: =IF('Controlo de Propinas'!B134="","",'Controlo de Propinas'!B134) | C133: =IF('Controlo de Propinas'!C134="","",'Controlo de Propinas'!C134) -> CM2 | F133: =IF('Controlo de Propinas'!K134="","",'Controlo de Propinas'!K134) | G133: =IF(C115="","",IF(OR(C115="Maternelle",C115="Maternelle P1",C115="Maternelle P2",C115="Maternelle P3"),170000,IF(C115="CM2",250000,IF(C115="4eme",260000,170000)))) -> 170000
A134: =IF('Controlo de Propinas'!A135="","",'Controlo de Propinas'!A135) | B134: =IF('Controlo de Propinas'!B135="","",'Controlo de Propinas'!B135) | C134: =IF('Controlo de Propinas'!C135="","",'Controlo de Propinas'!C135) -> CM2 | F134: =IF('Controlo de Propinas'!K135="","",'Controlo de Propinas'!K135) | G134: =IF(C116="","",IF(OR(C116="Maternelle",C116="Maternelle P1",C116="Maternelle P2",C116="Maternelle P3"),170000,IF(C116="CM2",250000,IF(C116="4eme",260000,170000)))) -> 170000
A135: =IF('Controlo de Propinas'!A136="","",'Controlo de Propinas'!A136) | B135: =IF('Controlo de Propinas'!B136="","",'Controlo de Propinas'!B136) | C135: =IF('Controlo de Propinas'!C136="","",'Controlo de Propinas'!C136) -> CM2 | F135: =IF('Controlo de Propinas'!K136="","",'Controlo de Propinas'!K136) | G135: =IF(C117="","",IF(OR(C117="Maternelle",C117="Maternelle P1",C117="Maternelle P2",C117="Maternelle P3"),170000,IF(C117="CM2",250000,IF(C117="4eme",260000,170000)))) -> 170000
A136: =IF('Controlo de Propinas'!A137="","",'Controlo de Propinas'!A137) | B136: =IF('Controlo de Propinas'!B137="","",'Controlo de Propinas'!B137) | C136: =IF('Controlo de Propinas'!C137="","",'Controlo de Propinas'!C137) -> CM2 | F136: =IF('Controlo de Propinas'!K137="","",'Controlo de Propinas'!K137) | G136: =IF(C118="","",IF(OR(C118="Maternelle",C118="Maternelle P1",C118="Maternelle P2",C118="Maternelle P3"),170000,IF(C118="CM2",250000,IF(C118="4eme",260000,170000)))) -> 170000
A137: =IF('Controlo de Propinas'!A138="","",'Controlo de Propinas'!A138) | B137: =IF('Controlo de Propinas'!B138="","",'Controlo de Propinas'!B138) | C137: =IF('Controlo de Propinas'!C138="","",'Controlo de Propinas'!C138) -> CM2 | F137: =IF('Controlo de Propinas'!K138="","",'Controlo de Propinas'!K138) | G137: =IF(C119="","",IF(OR(C119="Maternelle",C119="Maternelle P1",C119="Maternelle P2",C119="Maternelle P3"),170000,IF(C119="CM2",250000,IF(C119="4eme",260000,170000)))) -> 170000
A138: =IF('Controlo de Propinas'!A139="","",'Controlo de Propinas'!A139) | B138: =IF('Controlo de Propinas'!B139="","",'Controlo de Propinas'!B139) | C138: =IF('Controlo de Propinas'!C139="","",'Controlo de Propinas'!C139) -> CM2 | F138: =IF('Controlo de Propinas'!K139="","",'Controlo de Propinas'!K139) | G138: =IF(C120="","",IF(OR(C120="Maternelle",C120="Maternelle P1",C120="Maternelle P2",C120="Maternelle P3"),170000,IF(C120="CM2",250000,IF(C120="4eme",260000,170000)))) -> 170000
A139: =IF('Controlo de Propinas'!A140="","",'Controlo de Propinas'!A140) | B139: =IF('Controlo de Propinas'!B140="","",'Controlo de Propinas'!B140) | C139: =IF('Controlo de Propinas'!C140="","",'Controlo de Propinas'!C140) -> CM2 | F139: =IF('Controlo de Propinas'!K140="","",'Controlo de Propinas'!K140) | G139: =IF(C121="","",IF(OR(C121="Maternelle",C121="Maternelle P1",C121="Maternelle P2",C121="Maternelle P3"),170000,IF(C121="CM2",250000,IF(C121="4eme",260000,170000)))) -> 170000
... A171: =IF('Controlo de Propinas'!A172="","",'Controlo de Propinas'!A172) | B171: =IF('Controlo de Propinas'!B172="","",'Controlo de Propinas'!B172) | C171: =IF('Controlo de Propinas'!C172="","",'Controlo de Propinas'!C172) -> CM2 | F171: =IF('Controlo de Propinas'!K172="","",'Controlo de Propinas'!K172) | G171: =IF(C153="","",IF(OR(C153="Maternelle",C153="Maternelle P1",C153="Maternelle P2",C153="Maternelle P3"),170000,IF(C153="CM2",250000,IF(C153="4eme",260000,170000)))) -> 250000
A172: =IF('Controlo de Propinas'!#REF!="","",'Controlo de Propinas'!#REF!) -> #REF!
A173: =IF('Controlo de Propinas'!A173="","",'Controlo de Propinas'!A173) | B173: =IF('Controlo de Propinas'!B173="","",'Controlo de Propinas'!B173) | C173: =IF('Controlo de Propinas'!C173="","",'Controlo de Propinas'!C173) -> CM2 | F173: =IF('Controlo de Propinas'!K173="","",'Controlo de Propinas'!K173) | G173: =IF(C155="","",IF(OR(C155="Maternelle",C155="Maternelle P1",C155="Maternelle P2",C155="Maternelle P3"),170000,IF(C155="CM2",250000,IF(C155="4eme",260000,170000)))) -> 250000
A174: =IF('Controlo de Propinas'!A174="","",'Controlo de Propinas'!A174) | B174: =IF('Controlo de Propinas'!B174="","",'Controlo de Propinas'!B174) | C174: =IF('Controlo de Propinas'!C174="","",'Controlo de Propinas'!C174) -> CM2 | F174: =IF('Controlo de Propinas'!K174="","",'Controlo de Propinas'!K174) | G174: =IF(C156="","",IF(OR(C156="Maternelle",C156="Maternelle P1",C156="Maternelle P2",C156="Maternelle P3"),170000,IF(C156="CM2",250000,IF(C156="4eme",260000,170000)))) -> 250000
A175: =IF('Controlo de Propinas'!A175="","",'Controlo de Propinas'!A175) | B175: =IF('Controlo de Propinas'!B175="","",'Controlo de Propinas'!B175) | C175: =IF('Controlo de Propinas'!C175="","",'Controlo de Propinas'!C175) -> CM2 | F175: =IF('Controlo de Propinas'!K175="","",'Controlo de Propinas'!K175) | G175: =IF(C157="","",IF(OR(C157="Maternelle",C157="Maternelle P1",C157="Maternelle P2",C157="Maternelle P3"),170000,IF(C157="CM2",250000,IF(C157="4eme",260000,170000)))) -> 250000
A176: =IF('Controlo de Propinas'!A176="","",'Controlo de Propinas'!A176) | B176: =IF('Controlo de Propinas'!B176="","",'Controlo de Propinas'!B176) | C176: =IF('Controlo de Propinas'!C176="","",'Controlo de Propinas'!C176) -> CM2 | F176: =IF('Controlo de Propinas'!K176="","",'Controlo de Propinas'!K176) | G176: =IF(C158="","",IF(OR(C158="Maternelle",C158="Maternelle P1",C158="Maternelle P2",C158="Maternelle P3"),170000,IF(C158="CM2",250000,IF(C158="4eme",260000,170000)))) -> 250000
A177: =IF('Controlo de Propinas'!A177="","",'Controlo de Propinas'!A177) | B177: =IF('Controlo de Propinas'!B177="","",'Controlo de Propinas'!B177) | C177: =IF('Controlo de Propinas'!C177="","",'Controlo de Propinas'!C177) -> CM2 | F177: =IF('Controlo de Propinas'!K177="","",'Controlo de Propinas'!K177) | G177: =IF(C159="","",IF(OR(C159="Maternelle",C159="Maternelle P1",C159="Maternelle P2",C159="Maternelle P3"),170000,IF(C159="CM2",250000,IF(C159="4eme",260000,170000)))) -> 250000
A178: =IF('Controlo de Propinas'!A178="","",'Controlo de Propinas'!A178) | B178: =IF('Controlo de Propinas'!B178="","",'Controlo de Propinas'!B178) | C178: =IF('Controlo de Propinas'!C178="","",'Controlo de Propinas'!C178) -> CM2 | F178: =IF('Controlo de Propinas'!K178="","",'Controlo de Propinas'!K178) | G178: =IF(C160="","",IF(OR(C160="Maternelle",C160="Maternelle P1",C160="Maternelle P2",C160="Maternelle P3"),170000,IF(C160="CM2",250000,IF(C160="4eme",260000,170000)))) -> 250000
A179: =IF('Controlo de Propinas'!A179="","",'Controlo de Propinas'!A179) | B179: =IF('Controlo de Propinas'!B179="","",'Controlo de Propinas'!B179) | C179: =IF('Controlo de Propinas'!C179="","",'Controlo de Propinas'!C179) -> CM2 | F179: =IF('Controlo de Propinas'!K179="","",'Controlo de Propinas'!K179) | G179: =IF(C161="","",IF(OR(C161="Maternelle",C161="Maternelle P1",C161="Maternelle P2",C161="Maternelle P3"),170000,IF(C161="CM2",250000,IF(C161="4eme",260000,170000)))) -> 250000
A180: =IF('Controlo de Propinas'!A180="","",'Controlo de Propinas'!A180) | B180: =IF('Controlo de Propinas'!B180="","",'Controlo de Propinas'!B180) | C180: =IF('Controlo de Propinas'!C180="","",'Controlo de Propinas'!C180) -> CM2 | F180: =IF('Controlo de Propinas'!K180="","",'Controlo de Propinas'!K180) | G180: =IF(C162="","",IF(OR(C162="Maternelle",C162="Maternelle P1",C162="Maternelle P2",C162="Maternelle P3"),170000,IF(C162="CM2",250000,IF(C162="4eme",260000,170000)))) -> 250000
A181: =IF('Controlo de Propinas'!A181="","",'Controlo de Propinas'!A181) | B181: =IF('Controlo de Propinas'!B181="","",'Controlo de Propinas'!B181) | C181: =IF('Controlo de Propinas'!C181="","",'Controlo de Propinas'!C181) -> CM2 | F181: =IF('Controlo de Propinas'!K181="","",'Controlo de Propinas'!K181) | G181: =IF(C163="","",IF(OR(C163="Maternelle",C163="Maternelle P1",C163="Maternelle P2",C163="Maternelle P3"),170000,IF(C163="CM2",250000,IF(C163="4eme",260000,170000)))) -> 250000
A182: =IF('Controlo de Propinas'!A182="","",'Controlo de Propinas'!A182) | B182: =IF('Controlo de Propinas'!B182="","",'Controlo de Propinas'!B182) | C182: =IF('Controlo de Propinas'!C182="","",'Controlo de Propinas'!C182) -> CM2 | F182: =IF('Controlo de Propinas'!K182="","",'Controlo de Propinas'!K182) | G182: =IF(C164="","",IF(OR(C164="Maternelle",C164="Maternelle P1",C164="Maternelle P2",C164="Maternelle P3"),170000,IF(C164="CM2",250000,IF(C164="4eme",260000,170000)))) -> 250000
A183: =IF('Controlo de Propinas'!A183="","",'Controlo de Propinas'!A183) | B183: =IF('Controlo de Propinas'!B183="","",'Controlo de Propinas'!B183) | C183: =IF('Controlo de Propinas'!C183="","",'Controlo de Propinas'!C183) -> CM2 | F183: =IF('Controlo de Propinas'!K183="","",'Controlo de Propinas'!K183) | G183: =IF(C165="","",IF(OR(C165="Maternelle",C165="Maternelle P1",C165="Maternelle P2",C165="Maternelle P3"),170000,IF(C165="CM2",250000,IF(C165="4eme",260000,170000)))) -> 250000
A184: =IF('Controlo de Propinas'!A184="","",'Controlo de Propinas'!A184) | B184: =IF('Controlo de Propinas'!B184="","",'Controlo de Propinas'!B184) | C184: =IF('Controlo de Propinas'!C184="","",'Controlo de Propinas'!C184) -> CM2 | F184: =IF('Controlo de Propinas'!K184="","",'Controlo de Propinas'!K184) | G184: =IF(C166="","",IF(OR(C166="Maternelle",C166="Maternelle P1",C166="Maternelle P2",C166="Maternelle P3"),170000,IF(C166="CM2",250000,IF(C166="4eme",260000,170000)))) -> 250000
... A187: =IF('Controlo de Propinas'!A187="","",'Controlo de Propinas'!A187) | B187: =IF('Controlo de Propinas'!B187="","",'Controlo de Propinas'!B187) | C187: =IF('Controlo de Propinas'!C187="","",'Controlo de Propinas'!C187) -> CM2 | F187: =IF('Controlo de Propinas'!K187="","",'Controlo de Propinas'!K187) | G187: =IF(C169="","",IF(OR(C169="Maternelle",C169="Maternelle P1",C169="Maternelle P2",C169="Maternelle P3"),170000,IF(C169="CM2",250000,IF(C169="4eme",260000,170000)))) -> 250000
A188: Subtotal | B188: =COUNTIF(B110:B169,"?*")&" alunos" -> 7 alunos
A190: ▶ 6EME (Sixième)
A191: ID | B191: Nome Aluno | C191: Turma | D191: Responsável | E191: Contacto | F191: Data Matrícula | G191: Propina Mensal | H191: Atividades | I191: Endereço | J191: Tem Alergias? | K191: Quais Alergias? | L191: Toma Medicação?
A192: =IF('Controlo de Propinas'!A192="","",'Controlo de Propinas'!A192) -> 6E-01 | B192: =IF('Controlo de Propinas'!B192="","",'Controlo de Propinas'!B192) -> Imayami Suriel António Cristovão De Sousa | C192: =IF('Controlo de Propinas'!C192="","",'Controlo de Propinas'!C192) -> 6eme
A193: =IF('Controlo de Propinas'!A193="","",'Controlo de Propinas'!A193) | B193: =IF('Controlo de Propinas'!B193="","",'Controlo de Propinas'!B193) | C193: =IF('Controlo de Propinas'!C193="","",'Controlo de Propinas'!C193) -> 6eme
A194: =IF('Controlo de Propinas'!A194="","",'Controlo de Propinas'!A194) | B194: =IF('Controlo de Propinas'!B194="","",'Controlo de Propinas'!B194) | C194: =IF('Controlo de Propinas'!C194="","",'Controlo de Propinas'!C194) -> 6eme
A195: =IF('Controlo de Propinas'!A195="","",'Controlo de Propinas'!A195) | B195: =IF('Controlo de Propinas'!B195="","",'Controlo de Propinas'!B195) | C195: =IF('Controlo de Propinas'!C195="","",'Controlo de Propinas'!C195) -> 6eme
A196: =IF('Controlo de Propinas'!A196="","",'Controlo de Propinas'!A196) | B196: =IF('Controlo de Propinas'!B196="","",'Controlo de Propinas'!B196) | C196: =IF('Controlo de Propinas'!C196="","",'Controlo de Propinas'!C196) -> 6eme
A197: =IF('Controlo de Propinas'!A197="","",'Controlo de Propinas'!A197) | B197: =IF('Controlo de Propinas'!B197="","",'Controlo de Propinas'!B197) | C197: =IF('Controlo de Propinas'!C197="","",'Controlo de Propinas'!C197) -> 6eme
A198: =IF('Controlo de Propinas'!A198="","",'Controlo de Propinas'!A198) | B198: =IF('Controlo de Propinas'!B198="","",'Controlo de Propinas'!B198) | C198: =IF('Controlo de Propinas'!C198="","",'Controlo de Propinas'!C198) -> 6eme
A199: =IF('Controlo de Propinas'!A199="","",'Controlo de Propinas'!A199) | B199: =IF('Controlo de Propinas'!B199="","",'Controlo de Propinas'!B199) | C199: =IF('Controlo de Propinas'!C199="","",'Controlo de Propinas'!C199) -> 6eme
A200: =IF('Controlo de Propinas'!A200="","",'Controlo de Propinas'!A200) | B200: =IF('Controlo de Propinas'!B200="","",'Controlo de Propinas'!B200) | C200: =IF('Controlo de Propinas'!C200="","",'Controlo de Propinas'!C200) -> 6eme
A201: =IF('Controlo de Propinas'!A201="","",'Controlo de Propinas'!A201) | B201: =IF('Controlo de Propinas'!B201="","",'Controlo de Propinas'!B201) | C201: =IF('Controlo de Propinas'!C201="","",'Controlo de Propinas'!C201) -> 6eme
A202: =IF('Controlo de Propinas'!A202="","",'Controlo de Propinas'!A202) | B202: =IF('Controlo de Propinas'!B202="","",'Controlo de Propinas'!B202) | C202: =IF('Controlo de Propinas'!C202="","",'Controlo de Propinas'!C202) -> 6eme
A203: =IF('Controlo de Propinas'!A203="","",'Controlo de Propinas'!A203) | B203: =IF('Controlo de Propinas'!B203="","",'Controlo de Propinas'!B203) | C203: =IF('Controlo de Propinas'!C203="","",'Controlo de Propinas'!C203) -> 6eme
... A205: =IF('Controlo de Propinas'!A205="","",'Controlo de Propinas'!A205) | B205: =IF('Controlo de Propinas'!B205="","",'Controlo de Propinas'!B205) | C205: =IF('Controlo de Propinas'!C205="","",'Controlo de Propinas'!C205) -> 6eme
A206: Subtotal | B206: =COUNTIF(B192:B205,"?*")&" alunos" -> 1 alunos
A208: ▶ 4EME
A209: ID | B209: Nome Aluno | C209: Turma | D209: Responsável | E209: Contacto | F209: Data Matrícula | G209: Propina Mensal | H209: Atividades | I209: Endereço | J209: Tem Alergias? | K209: Quais Alergias? | L209: Toma Medicação?
A210: =IF('Controlo de Propinas'!A210="","",'Controlo de Propinas'!A210) -> 4E-01 | B210: =IF('Controlo de Propinas'!B210="","",'Controlo de Propinas'!B210) -> Nathaniel Dialude Calei da Costa | C210: =IF('Controlo de Propinas'!C210="","",'Controlo de Propinas'!C210) -> 4eme | F210: =IF('Controlo de Propinas'!K210="","",'Controlo de Propinas'!K210) -> 46229 | G210: =IF(C174="","",IF(OR(C174="Maternelle",C174="Maternelle P1",C174="Maternelle P2",C174="Maternelle P3"),170000,IF(C174="CM2",250000,IF(C174="4eme",260000,170000)))) -> 250000
A211: =IF('Controlo de Propinas'!A211="","",'Controlo de Propinas'!A211) | B211: =IF('Controlo de Propinas'!B211="","",'Controlo de Propinas'!B211) | C211: =IF('Controlo de Propinas'!C211="","",'Controlo de Propinas'!C211) -> 4eme | F211: =IF('Controlo de Propinas'!K211="","",'Controlo de Propinas'!K211) | G211: =IF(C175="","",IF(OR(C175="Maternelle",C175="Maternelle P1",C175="Maternelle P2",C175="Maternelle P3"),170000,IF(C175="CM2",250000,IF(C175="4eme",260000,170000)))) -> 250000
A212: =IF('Controlo de Propinas'!A212="","",'Controlo de Propinas'!A212) | B212: =IF('Controlo de Propinas'!B212="","",'Controlo de Propinas'!B212) | C212: =IF('Controlo de Propinas'!C212="","",'Controlo de Propinas'!C212) -> 4eme | F212: =IF('Controlo de Propinas'!K212="","",'Controlo de Propinas'!K212) | G212: =IF(C176="","",IF(OR(C176="Maternelle",C176="Maternelle P1",C176="Maternelle P2",C176="Maternelle P3"),170000,IF(C176="CM2",250000,IF(C176="4eme",260000,170000)))) -> 250000
A213: =IF('Controlo de Propinas'!A213="","",'Controlo de Propinas'!A213) | B213: =IF('Controlo de Propinas'!B213="","",'Controlo de Propinas'!B213) | C213: =IF('Controlo de Propinas'!C213="","",'Controlo de Propinas'!C213) -> 4eme | F213: =IF('Controlo de Propinas'!K213="","",'Controlo de Propinas'!K213) | G213: =IF(C177="","",IF(OR(C177="Maternelle",C177="Maternelle P1",C177="Maternelle P2",C177="Maternelle P3"),170000,IF(C177="CM2",250000,IF(C177="4eme",260000,170000)))) -> 250000
A214: =IF('Controlo de Propinas'!A214="","",'Controlo de Propinas'!A214) | B214: =IF('Controlo de Propinas'!B214="","",'Controlo de Propinas'!B214) | C214: =IF('Controlo de Propinas'!C214="","",'Controlo de Propinas'!C214) -> 4eme | F214: =IF('Controlo de Propinas'!K214="","",'Controlo de Propinas'!K214) | G214: =IF(C178="","",IF(OR(C178="Maternelle",C178="Maternelle P1",C178="Maternelle P2",C178="Maternelle P3"),170000,IF(C178="CM2",250000,IF(C178="4eme",260000,170000)))) -> 250000
A215: =IF('Controlo de Propinas'!A215="","",'Controlo de Propinas'!A215) | B215: =IF('Controlo de Propinas'!B215="","",'Controlo de Propinas'!B215) | C215: =IF('Controlo de Propinas'!C215="","",'Controlo de Propinas'!C215) -> 4eme | F215: =IF('Controlo de Propinas'!K215="","",'Controlo de Propinas'!K215) | G215: =IF(C179="","",IF(OR(C179="Maternelle",C179="Maternelle P1",C179="Maternelle P2",C179="Maternelle P3"),170000,IF(C179="CM2",250000,IF(C179="4eme",260000,170000)))) -> 250000
A216: =IF('Controlo de Propinas'!#REF!="","",'Controlo de Propinas'!#REF!) -> #REF!
A217: =IF('Controlo de Propinas'!A216="","",'Controlo de Propinas'!A216) | B217: =IF('Controlo de Propinas'!B216="","",'Controlo de Propinas'!B216) | C217: =IF('Controlo de Propinas'!C216="","",'Controlo de Propinas'!C216) -> 4eme | F217: =IF('Controlo de Propinas'!K216="","",'Controlo de Propinas'!K216) | G217: =IF(C181="","",IF(OR(C181="Maternelle",C181="Maternelle P1",C181="Maternelle P2",C181="Maternelle P3"),170000,IF(C181="CM2",250000,IF(C181="4eme",260000,170000)))) -> 250000
A218: =IF('Controlo de Propinas'!A217="","",'Controlo de Propinas'!A217) | B218: =IF('Controlo de Propinas'!B217="","",'Controlo de Propinas'!B217) | C218: =IF('Controlo de Propinas'!C217="","",'Controlo de Propinas'!C217) -> 4eme | F218: =IF('Controlo de Propinas'!K217="","",'Controlo de Propinas'!K217) | G218: =IF(C182="","",IF(OR(C182="Maternelle",C182="Maternelle P1",C182="Maternelle P2",C182="Maternelle P3"),170000,IF(C182="CM2",250000,IF(C182="4eme",260000,170000)))) -> 250000
A219: =IF('Controlo de Propinas'!A218="","",'Controlo de Propinas'!A218) | B219: =IF('Controlo de Propinas'!B218="","",'Controlo de Propinas'!B218) | C219: =IF('Controlo de Propinas'!C218="","",'Controlo de Propinas'!C218) -> 4eme | F219: =IF('Controlo de Propinas'!K218="","",'Controlo de Propinas'!K218) | G219: =IF(C183="","",IF(OR(C183="Maternelle",C183="Maternelle P1",C183="Maternelle P2",C183="Maternelle P3"),170000,IF(C183="CM2",250000,IF(C183="4eme",260000,170000)))) -> 250000
A220: =IF('Controlo de Propinas'!A219="","",'Controlo de Propinas'!A219) | B220: =IF('Controlo de Propinas'!B219="","",'Controlo de Propinas'!B219) | C220: =IF('Controlo de Propinas'!C219="","",'Controlo de Propinas'!C219) -> 4eme | F220: =IF('Controlo de Propinas'!K219="","",'Controlo de Propinas'!K219) | G220: =IF(C184="","",IF(OR(C184="Maternelle",C184="Maternelle P1",C184="Maternelle P2",C184="Maternelle P3"),170000,IF(C184="CM2",250000,IF(C184="4eme",260000,170000)))) -> 250000
A221: =IF('Controlo de Propinas'!A220="","",'Controlo de Propinas'!A220) | B221: =IF('Controlo de Propinas'!B220="","",'Controlo de Propinas'!B220) | C221: =IF('Controlo de Propinas'!C220="","",'Controlo de Propinas'!C220) -> 4eme | F221: =IF('Controlo de Propinas'!K220="","",'Controlo de Propinas'!K220) | G221: =IF(C185="","",IF(OR(C185="Maternelle",C185="Maternelle P1",C185="Maternelle P2",C185="Maternelle P3"),170000,IF(C185="CM2",250000,IF(C185="4eme",260000,170000)))) -> 250000
A222: =IF('Controlo de Propinas'!A221="","",'Controlo de Propinas'!A221) | B222: =IF('Controlo de Propinas'!B221="","",'Controlo de Propinas'!B221) | C222: =IF('Controlo de Propinas'!C221="","",'Controlo de Propinas'!C221) -> 4eme | F222: =IF('Controlo de Propinas'!K221="","",'Controlo de Propinas'!K221) | G222: =IF(C186="","",IF(OR(C186="Maternelle",C186="Maternelle P1",C186="Maternelle P2",C186="Maternelle P3"),170000,IF(C186="CM2",250000,IF(C186="4eme",260000,170000)))) -> 250000
A223: =IF('Controlo de Propinas'!A222="","",'Controlo de Propinas'!A222) | B223: =IF('Controlo de Propinas'!B222="","",'Controlo de Propinas'!B222) | C223: =IF('Controlo de Propinas'!C222="","",'Controlo de Propinas'!C222) -> 4eme | F223: =IF('Controlo de Propinas'!K222="","",'Controlo de Propinas'!K222) | G223: =IF(C187="","",IF(OR(C187="Maternelle",C187="Maternelle P1",C187="Maternelle P2",C187="Maternelle P3"),170000,IF(C187="CM2",250000,IF(C187="4eme",260000,170000)))) -> 250000
A224: =IF('Controlo de Propinas'!A223="","",'Controlo de Propinas'!A223) | B224: =IF('Controlo de Propinas'!B223="","",'Controlo de Propinas'!B223) | C224: =IF('Controlo de Propinas'!C223="","",'Controlo de Propinas'!C223) -> 4eme | F224: =IF('Controlo de Propinas'!K223="","",'Controlo de Propinas'!K223) | G224: =IF(C188="","",IF(OR(C188="Maternelle",C188="Maternelle P1",C188="Maternelle P2",C188="Maternelle P3"),170000,IF(C188="CM2",250000,IF(C188="4eme",260000,170000))))
A225: =IF('Controlo de Propinas'!A224="","",'Controlo de Propinas'!A224) | B225: =IF('Controlo de Propinas'!B224="","",'Controlo de Propinas'!B224) | C225: =IF('Controlo de Propinas'!C224="","",'Controlo de Propinas'!C224) -> 4eme | F225: =IF('Controlo de Propinas'!K224="","",'Controlo de Propinas'!K224) | G225: =IF(C189="","",IF(OR(C189="Maternelle",C189="Maternelle P1",C189="Maternelle P2",C189="Maternelle P3"),170000,IF(C189="CM2",250000,IF(C189="4eme",260000,170000))))
A226: =IF('Controlo de Propinas'!A225="","",'Controlo de Propinas'!A225) | B226: =IF('Controlo de Propinas'!B225="","",'Controlo de Propinas'!B225) | C226: =IF('Controlo de Propinas'!C225="","",'Controlo de Propinas'!C225) -> 4eme | F226: =IF('Controlo de Propinas'!K225="","",'Controlo de Propinas'!K225) | G226: =IF(C190="","",IF(OR(C190="Maternelle",C190="Maternelle P1",C190="Maternelle P2",C190="Maternelle P3"),170000,IF(C190="CM2",250000,IF(C190="4eme",260000,170000))))
A227: =IF('Controlo de Propinas'!A226="","",'Controlo de Propinas'!A226) | B227: =IF('Controlo de Propinas'!B226="","",'Controlo de Propinas'!B226) | C227: =IF('Controlo de Propinas'!C226="","",'Controlo de Propinas'!C226) -> 4eme | F227: =IF('Controlo de Propinas'!K226="","",'Controlo de Propinas'!K226) | G227: =IF(C191="","",IF(OR(C191="Maternelle",C191="Maternelle P1",C191="Maternelle P2",C191="Maternelle P3"),170000,IF(C191="CM2",250000,IF(C191="4eme",260000,170000)))) -> 170000
...

Sheet Controlo de Manuais
A1: CONTROLO DE MANUAIS ESCOLARES – 2026/2027
A2: Amarelo = input manual. Verde = calculado. Ligado ao Controlo de Propinas (coluna Manuais). Organize por turma.
A4: ID | B4: Nome Aluno | C4: Turma | D4: Valor Manuais (KZ) | E4: Comprou? | F4: Data Compra | G4: Forma Pagamento | H4: Nº Recibo | I4: Observações | J4: Status | K4: Valor Recebido | L4: Pendente
A5: MATERNELLE
A6: MAT-01 | B6: ='Controlo de Propinas'!B6 -> Hazail Epandi Calei da Costa | C6: ='Controlo de Propinas'!C6 -> Maternelle | D6: =IF('Controlo de Propinas'!E6="","",'Controlo de Propinas'!E6) | E6: Não | J6: =IF(E6="Sim","Pago",IF(OR(D6=0,D6=""),"N/A","Pendente")) -> N/A | K6: =IF(E6="Sim",IF(D6="",0,D6),0) -> 0 | L6: =IF(E6="Sim",0,IF(D6="",0,D6)) -> 0
A7: MAT-02 | B7: ='Controlo de Propinas'!B7 -> Erick Libânio Sebastião da Silva | C7: ='Controlo de Propinas'!C7 -> Maternelle P1 | D7: =IF('Controlo de Propinas'!E7="","",'Controlo de Propinas'!E7) | E7: Não | J7: =IF(E7="Sim","Pago",IF(OR(D7=0,D7=""),"N/A","Pendente")) -> N/A | K7: =IF(E7="Sim",IF(D7="",0,D7),0) -> 0 | L7: =IF(E7="Sim",0,IF(D7="",0,D7)) -> 0
A8: MAT-03 | B8: ='Controlo de Propinas'!B8 -> Eloa Marina Sebastião da Silva | C8: ='Controlo de Propinas'!C8 -> Maternelle P2 | D8: =IF('Controlo de Propinas'!E8="","",'Controlo de Propinas'!E8) | E8: Não | J8: =IF(E8="Sim","Pago",IF(OR(D8=0,D8=""),"N/A","Pendente")) -> N/A | K8: =IF(E8="Sim",IF(D8="",0,D8),0) -> 0 | L8: =IF(E8="Sim",0,IF(D8="",0,D8)) -> 0
A9: MAT-04 | B9: ='Controlo de Propinas'!B9 -> Ivander Trindade Bernardo Clementino | C9: ='Controlo de Propinas'!C9 -> Maternelle P2 | D9: =IF('Controlo de Propinas'!E9="","",'Controlo de Propinas'!E9) | E9: Não | J9: =IF(E9="Sim","Pago",IF(OR(D9=0,D9=""),"N/A","Pendente")) -> N/A | K9: =IF(E9="Sim",IF(D9="",0,D9),0) -> 0 | L9: =IF(E9="Sim",0,IF(D9="",0,D9)) -> 0
A10: MAT-05 | B10: ='Controlo de Propinas'!B10 -> Gael Hanji Ventura Quimbundo | C10: ='Controlo de Propinas'!C10 -> Maternelle P3 | D10: =IF('Controlo de Propinas'!E10="","",'Controlo de Propinas'!E10) | E10: Não | J10: =IF(E10="Sim","Pago",IF(OR(D10=0,D10=""),"N/A","Pendente")) -> N/A | K10: =IF(E10="Sim",IF(D10="",0,D10),0) -> 0 | L10: =IF(E10="Sim",0,IF(D10="",0,D10)) -> 0
A11: MAT-06 | B11: ='Controlo de Propinas'!B11 -> Ivanna Chayane Bernardo Clementino | C11: ='Controlo de Propinas'!C11 -> Maternelle P3 | D11: =IF('Controlo de Propinas'!E11="","",'Controlo de Propinas'!E11) | E11: Não | J11: =IF(E11="Sim","Pago",IF(OR(D11=0,D11=""),"N/A","Pendente")) -> N/A | K11: =IF(E11="Sim",IF(D11="",0,D11),0) -> 0 | L11: =IF(E11="Sim",0,IF(D11="",0,D11)) -> 0
A12: MAT-07 | B12: ='Controlo de Propinas'!B12 -> Wendy Aryanne Chimuco Sabino | C12: ='Controlo de Propinas'!C12 -> Maternelle P3 | D12: =IF('Controlo de Propinas'!E12="","",'Controlo de Propinas'!E12) | E12: Não | J12: =IF(E12="Sim","Pago",IF(OR(D12=0,D12=""),"N/A","Pendente")) -> N/A | K12: =IF(E12="Sim",IF(D12="",0,D12),0) -> 0 | L12: =IF(E12="Sim",0,IF(D12="",0,D12)) -> 0
A13: MAT-08 | B13: ='Controlo de Propinas'!B13 -> Kesane Aimé Teixeira Correia de Azevedo | C13: ='Controlo de Propinas'!C13 -> Maternelle P1 | D13: =IF('Controlo de Propinas'!E13="","",'Controlo de Propinas'!E13) | E13: Não | J13: =IF(E13="Sim","Pago",IF(OR(D13=0,D13=""),"N/A","Pendente")) -> N/A | K13: =IF(E13="Sim",IF(D13="",0,D13),0) -> 0 | L13: =IF(E13="Sim",0,IF(D13="",0,D13)) -> 0
A14: MAT-09 | B14: ='Controlo de Propinas'!B14 -> Kuami Hazael Francisco Venâncio | C14: ='Controlo de Propinas'!C14 -> Maternelle P3 | D14: =IF('Controlo de Propinas'!E14="","",'Controlo de Propinas'!E14) | E14: Não | J14: =IF(E14="Sim","Pago",IF(OR(D14=0,D14=""),"N/A","Pendente")) -> N/A | K14: =IF(E14="Sim",IF(D14="",0,D14),0) -> 0 | L14: =IF(E14="Sim",0,IF(D14="",0,D14)) -> 0
J15: =IF(E15="Sim","Pago",IF(D15=0,"N/A","Pendente")) -> N/A
A17: Subtotal | B17: =COUNTA(B6:B14)&" alunos" -> 9 alunos | D17: =SUM(D6:D14) -> 0 | K17: =SUM(K6:K14) -> 0 | L17: =SUM(L6:L14) -> 0
A19: CM2
A20: ID | B20: Nome Aluno | C20: Turma | D20: Valor Manuais (KZ) | E20: Comprou? | F20: Data Compra | G20: Forma Pagamento | H20: Nº Recibo | I20: Observações | J20: Status | K20: Valor Recebido | L20: Pendente
A21: CM2-01 | B21: ='Controlo de Propinas'!B110 -> Crisber Uluwami António Cristovão De Sousa | C21: ='Controlo de Propinas'!C110 -> CM1 | D21: =IF('Controlo de Propinas'!E110="","",'Controlo de Propinas'!E110) | E21: Sim | F21: 46230 | G21: Cartão Multicaixa | J21: =IF(E21="Sim","Pago",IF(OR(D21=0,D21=""),"N/A","Pendente")) -> Pago | K21: =IF(E21="Sim",IF(D21="",0,D21),0) -> 0 | L21: =IF(E21="Sim",0,IF(D21="",0,D21)) -> 0
A22: CM2-02 | B22: ='Controlo de Propinas'!B111 -> 0 | C22: ='Controlo de Propinas'!C111 -> CM1 | D22: =IF('Controlo de Propinas'!E111="","",'Controlo de Propinas'!E111) | E22: Sim | F22: 46167 | G22: Cartão Multicaixa | J22: =IF(E22="Sim","Pago",IF(OR(D22=0,D22=""),"N/A","Pendente")) -> Pago | K22: =IF(E22="Sim",IF(D22="",0,D22),0) -> 0 | L22: =IF(E22="Sim",0,IF(D22="",0,D22)) -> 0
A23: CM2-03 | B23: ='Controlo de Propinas'!B112 -> 0 | C23: ='Controlo de Propinas'!C112 -> CM1 | D23: =IF('Controlo de Propinas'!E112="","",'Controlo de Propinas'!E112) | E23: Não | J23: =IF(E23="Sim","Pago",IF(OR(D23=0,D23=""),"N/A","Pendente")) -> N/A | K23: =IF(E23="Sim",IF(D23="",0,D23),0) -> 0 | L23: =IF(E23="Sim",0,IF(D23="",0,D23)) -> 0
A24: CM2-04 | B24: ='Controlo de Propinas'!B113 -> 0 | C24: ='Controlo de Propinas'!C113 -> CM1 | D24: =IF('Controlo de Propinas'!E113="","",'Controlo de Propinas'!E113) | E24: Não | J24: =IF(E24="Sim","Pago",IF(OR(D24=0,D24=""),"N/A","Pendente")) -> N/A | K24: =IF(E24="Sim",IF(D24="",0,D24),0) -> 0 | L24: =IF(E24="Sim",0,IF(D24="",0,D24)) -> 0
A26: Subtotal | B26: =COUNTA(B21:B24)&" alunos" -> 4 alunos | D26: =SUM(D21:D24) -> 0 | K26: =SUM(K21:K24) -> 0 | L26: =SUM(L21:L24) -> 0
A28: 4EME
A29: ID | B29: Nome Aluno | C29: Turma | D29: Valor Manuais (KZ) | E29: Comprou? | F29: Data Compra | G29: Forma Pagamento | H29: Nº Recibo | I29: Observações | J29: Status | K29: Valor Recebido | L29: Pendente
A30: 4E-01 | B30: ='Controlo de Propinas'!B174 -> 0 | C30: ='Controlo de Propinas'!C174 -> CM2 | D30: =IF('Controlo de Propinas'!E174="","",'Controlo de Propinas'!E174) | E30: Não | J30: =IF(E30="Sim","Pago",IF(OR(D30=0,D30=""),"N/A","Pendente")) -> N/A | K30: =IF(E30="Sim",IF(D30="",0,D30),0) -> 0 | L30: =IF(E30="Sim",0,IF(D30="",0,D30)) -> 0
A33: Subtotal | B33: =COUNTA(B30:B30)&" alunos" -> 1 alunos | D33: =SUM(D30:D30) -> 0 | K33: =SUM(K30:K30) -> 0 | L33: =SUM(L30:L30) -> 0
A35: TOTAL GERAL | B35: =COUNTA(B6:B14)+COUNTA(B21:B24)+COUNTA(B30:B30)&" alunos" -> 14 alunos | D35: =D17+D26+D33 -> 0 | K35: =K17+K26+K33 -> 0 | L35: =L17+L26+L33 -> 0
A37: NOTA: Preencha "Comprou?" com Sim/Não. Valor Manuais pode ser atualizado manualmente ou sincronizado com Controlo de Propinas. Status, Valor Recebido e Pendente são automáticos.
A38: Ecole Consulaire du Congo (Brazzaville) de Luanda • Controlo de Manuais por Turma
A40: ▶ PROFESSORES E FUNCIONÁRIOS – VENDA DE MANUAIS (tabela independente dos alunos)
A41: Registo de compras de manuais por professores e funcionários da escola. Não está ligado ao Controlo de Propinas. Amarelo = preencher | Verde = calculado.
A43: Nº | B43: ID / Código | C43: Nome | D43: Categoria | E43: Função | F43: Valor Manuais (KZ) | G43: Comprou? | H43: Data Compra | I43: Forma Pagamento | J43: Nº Recibo | K43: Observações | L43: Status
A44: =IF(C44="","",TEXT(COUNTA($C$44:C44),"000")) -> 001 | B44: FUNC-001 | C44: Leia | D44: Secretaria | E44: Empregada Limpeza | F44: 2000 | G44: Não | H44: 46246 | I44: Transferência | L44: =IF(C44="","",IF(G44="Sim","Pago",IF(OR(F44=0,F44=""),"N/A","Pendente"))) -> Pendente
A45: =IF(C45="","",TEXT(COUNTA($C$44:C45),"000")) | L45: =IF(C45="","",IF(G45="Sim","Pago",IF(OR(F45=0,F45=""),"N/A","Pendente")))
A46: =IF(C46="","",TEXT(COUNTA($C$44:C46),"000")) | L46: =IF(C46="","",IF(G46="Sim","Pago",IF(OR(F46=0,F46=""),"N/A","Pendente")))
A47: =IF(C47="","",TEXT(COUNTA($C$44:C47),"000")) | L47: =IF(C47="","",IF(G47="Sim","Pago",IF(OR(F47=0,F47=""),"N/A","Pendente")))
A48: =IF(C48="","",TEXT(COUNTA($C$44:C48),"000")) | L48: =IF(C48="","",IF(G48="Sim","Pago",IF(OR(F48=0,F48=""),"N/A","Pendente")))
A49: =IF(C49="","",TEXT(COUNTA($C$44:C49),"000")) | L49: =IF(C49="","",IF(G49="Sim","Pago",IF(OR(F49=0,F49=""),"N/A","Pendente")))
A50: =IF(C50="","",TEXT(COUNTA($C$44:C50),"000")) | L50: =IF(C50="","",IF(G50="Sim","Pago",IF(OR(F50=0,F50=""),"N/A","Pendente")))
A51: =IF(C51="","",TEXT(COUNTA($C$44:C51),"000")) | L51: =IF(C51="","",IF(G51="Sim","Pago",IF(OR(F51=0,F51=""),"N/A","Pendente")))
A52: =IF(C52="","",TEXT(COUNTA($C$44:C52),"000")) | L52: =IF(C52="","",IF(G52="Sim","Pago",IF(OR(F52=0,F52=""),"N/A","Pendente")))
A53: =IF(C53="","",TEXT(COUNTA($C$44:C53),"000")) | L53: =IF(C53="","",IF(G53="Sim","Pago",IF(OR(F53=0,F53=""),"N/A","Pendente")))
A54: =IF(C54="","",TEXT(COUNTA($C$44:C54),"000")) | L54: =IF(C54="","",IF(G54="Sim","Pago",IF(OR(F54=0,F54=""),"N/A","Pendente")))
A55: =IF(C55="","",TEXT(COUNTA($C$44:C55),"000")) | L55: =IF(C55="","",IF(G55="Sim","Pago",IF(OR(F55=0,F55=""),"N/A","Pendente")))
A56: =IF(C56="","",TEXT(COUNTA($C$44:C56),"000")) | L56: =IF(C56="","",IF(G56="Sim","Pago",IF(OR(F56=0,F56=""),"N/A","Pendente")))
... A58: =IF(C58="","",TEXT(COUNTA($C$44:C58),"000")) | L58: =IF(C58="","",IF(G58="Sim","Pago",IF(OR(F58=0,F58=""),"N/A","Pendente")))
A60: SUBTOTAL FUNCIONÁRIOS | C60: =COUNTA(C44:C58)&" registos" -> 1 registos | F60: =SUM(F44:F58) -> 2000 | K60: =SUMIF(G44:G58,"Sim",F44:F58) -> 0 | L60: =F60-K60 -> 2000
A62: TOTAL GERAL (Alunos + Funcionários) | F62: =D35+F60 -> 2000 | K62: =K35+K60 -> 0 | L62: =L35+L60 -> 2000
A64: INSTRUÇÕES (Professores/Funcionários): 1) Preencha ID, Nome, Categoria, Função e Valor dos manuais (amarelo). 2) Em "Comprou?" selecione Sim ou Não. 3) Data, Forma de Pagamento, Nº Recibo e Observações são opcionais. 4) Status calcula-se automaticamente (Pago / Pendente / N/A). 5) Esta tabela é independente dos alunos e não altera o Controlo de Propinas. 6) Pode registar desconto em salário como forma de pagamento.
A66: École Consulaire du Congo (Brazzaville) de Luanda • Controlo de Manuais – Alunos e Pessoal

Sheet Lançamentos Contábeis
A1: LANÇAMENTOS CONTÁBEIS
A2: Gerado automaticamente a partir dos pagamentos
A4: INSCRIÇÕES / MATRICULAS
A5: Data | B5: Debito | C5: Credito | D5: Descricao | E5: Valor | F5: ID | G5: Aluno | H5: Ref.
A6: ='Controlo de Propinas'!K4 -> 0 | B6: 41 | C6: 81 | D6: ="Inscricao - "&'Controlo de Propinas'!B4 -> Inscricao - | E6: ='Controlo de Propinas'!N4 -> 0 | F6: ='Controlo de Propinas'!A4 -> ▶ MATERNELLE | G6: ='Controlo de Propinas'!B4 -> 0 | H6: Inscricao
A7: ='Controlo de Propinas'!K5 -> Data Pag. | B7: 41 | C7: 81 | D7: ="Inscricao - "&'Controlo de Propinas'!B5 -> Inscricao - Nome Aluno | E7: ='Controlo de Propinas'!N5 -> Valor c/ Desc. | F7: ='Controlo de Propinas'!A5 -> ID | G7: ='Controlo de Propinas'!B5 -> Nome Aluno | H7: Inscricao
A8: ='Controlo de Propinas'!K6 -> 46229 | B8: 41 | C8: 81 | D8: ="Inscricao - "&'Controlo de Propinas'!B6 -> Inscricao - Hazail Epandi Calei da Costa | E8: ='Controlo de Propinas'!N6 -> 162000 | F8: ='Controlo de Propinas'!A6 -> P1-01 | G8: ='Controlo de Propinas'!B6 -> Hazail Epandi Calei da Costa | H8: Inscricao
A9: ='Controlo de Propinas'!K7 -> 46235 | B9: 41 | C9: 81 | D9: ="Inscricao - "&'Controlo de Propinas'!B7 -> Inscricao - Erick Libânio Sebastião da Silva | E9: ='Controlo de Propinas'!N7 -> 180000 | F9: ='Controlo de Propinas'!A7 -> P1-02 | G9: ='Controlo de Propinas'!B7 -> Erick Libânio Sebastião da Silva | H9: Inscricao
A10: ='Controlo de Propinas'!K8 -> 46235 | B10: 41 | C10: 81 | D10: ="Inscricao - "&'Controlo de Propinas'!B8 -> Inscricao - Eloa Marina Sebastião da Silva | E10: ='Controlo de Propinas'!N8 -> 180000 | F10: ='Controlo de Propinas'!A8 -> P2-03 | G10: ='Controlo de Propinas'!B8 -> Eloa Marina Sebastião da Silva | H10: Inscricao
A11: ='Controlo de Propinas'!K9 -> 46240 | B11: 41 | C11: 81 | D11: ="Inscricao - "&'Controlo de Propinas'!B9 -> Inscricao - Ivander Trindade Bernardo Clementino | E11: ='Controlo de Propinas'!N9 -> 180000 | F11: ='Controlo de Propinas'!A9 -> P2-04 | G11: ='Controlo de Propinas'!B9 -> Ivander Trindade Bernardo Clementino | H11: Inscricao
A12: ='Controlo de Propinas'!K10 -> 46237 | B12: 41 | C12: 81 | D12: ="Inscricao - "&'Controlo de Propinas'!B10 -> Inscricao - Gael Hanji Ventura Quimbundo | E12: ='Controlo de Propinas'!N10 -> 180000 | F12: ='Controlo de Propinas'!A10 -> P3-05 | G12: ='Controlo de Propinas'!B10 -> Gael Hanji Ventura Quimbundo | H12: Inscricao
A13: ='Controlo de Propinas'!K11 -> 46240 | B13: 41 | C13: 81 | D13: ="Inscricao - "&'Controlo de Propinas'!B11 -> Inscricao - Ivanna Chayane Bernardo Clementino | E13: ='Controlo de Propinas'!N11 -> 180000 | F13: ='Controlo de Propinas'!A11 -> P3-06 | G13: ='Controlo de Propinas'!B11 -> Ivanna Chayane Bernardo Clementino | H13: Inscricao
A14: ='Controlo de Propinas'!K12 -> 46232 | B14: 41 | C14: 81 | D14: ="Inscricao - "&'Controlo de Propinas'!B12 -> Inscricao - Wendy Aryanne Chimuco Sabino | E14: ='Controlo de Propinas'!N12 -> 350000 | F14: ='Controlo de Propinas'!A12 -> P3-07 | G14: ='Controlo de Propinas'!B12 -> Wendy Aryanne Chimuco Sabino | H14: Inscricao
A15: ='Controlo de Propinas'!K13 -> 46255 | B15: 41 | C15: 81 | D15: ="Inscricao - "&'Controlo de Propinas'!B13 -> Inscricao - Kesane Aimé Teixeira Correia de Azevedo | E15: ='Controlo de Propinas'!N13 -> 150000 | F15: ='Controlo de Propinas'!A13 -> P1-08 | G15: ='Controlo de Propinas'!B13 -> Kesane Aimé Teixeira Correia de Azevedo | H15: Inscricao
A16: ='Controlo de Propinas'!K14 -> 46245 | B16: 41 | C16: 81 | D16: ="Inscricao - "&'Controlo de Propinas'!B14 -> Inscricao - Kuami Hazael Francisco Venâncio | E16: ='Controlo de Propinas'!N14 -> 150000 | F16: ='Controlo de Propinas'!A14 -> P3-09 | G16: ='Controlo de Propinas'!B14 -> Kuami Hazael Francisco Venâncio | H16: Inscricao
A17: ='Controlo de Propinas'!K15 -> 0 | B17: 41 | C17: 81 | D17: ="Inscricao - "&'Controlo de Propinas'!B15 -> Inscricao - | E17: ='Controlo de Propinas'!N15 | F17: ='Controlo de Propinas'!A15 -> 0 | G17: ='Controlo de Propinas'!B15 -> 0 | H17: Inscricao
... A19: ='Controlo de Propinas'!K17 -> 0 | B19: 41 | C19: 81 | D19: ="Inscricao - "&'Controlo de Propinas'!B17 -> Inscricao - | E19: ='Controlo de Propinas'!N17 | F19: ='Controlo de Propinas'!A17 -> 0 | G19: ='Controlo de Propinas'!B17 -> 0 | H19: Inscricao
D21: TOTAL INSCRICOES | E21: =SUM(E6:E19) -> 1712000
A23: MENSALIDADES (Setembro)
A24: Data | B24: Debito | C24: Credito | D24: Descricao | E24: Valor | F24: ID | G24: Aluno | H24: Ref.
A25: 46270 | B25: 41 | C25: 81 | D25: ="Propina - "&Mensalidades!B6&" Set/26" -> Propina - Hazail Epandi Calei da Costa Set/26 | E25: =IF(Mensalidades!E6>0,Mensalidades!E6,"") | F25: =Mensalidades!A6 -> P1-01 | G25: =Mensalidades!B6 -> Hazail Epandi Calei da Costa | H25: Propina
A26: 46270 | B26: 41 | C26: 81 | D26: ="Propina - "&Mensalidades!B7&" Set/26" -> Propina - Erick Libânio Sebastião da Silva Set/26 | E26: =IF(Mensalidades!E7>0,Mensalidades!E7,"") | F26: =Mensalidades!A7 -> P1-02 | G26: =Mensalidades!B7 -> Erick Libânio Sebastião da Silva | H26: Propina
A27: 46270 | B27: 41 | C27: 81 | D27: ="Propina - "&Mensalidades!B8&" Set/26" -> Propina - Eloa Marina Sebastião da Silva Set/26 | E27: =IF(Mensalidades!E8>0,Mensalidades!E8,"") | F27: =Mensalidades!A8 -> P2-03 | G27: =Mensalidades!B8 -> Eloa Marina Sebastião da Silva | H27: Propina
A28: 46270 | B28: 41 | C28: 81 | D28: ="Propina - "&Mensalidades!B9&" Set/26" -> Propina - Ivander Trindade Bernardo Clementino Set/26 | E28: =IF(Mensalidades!E9>0,Mensalidades!E9,"") | F28: =Mensalidades!A9 -> P2-04 | G28: =Mensalidades!B9 -> Ivander Trindade Bernardo Clementino | H28: Propina
A29: 46270 | B29: 41 | C29: 81 | D29: ="Propina - "&Mensalidades!B10&" Set/26" -> Propina - Gael Hanji Ventura Quimbundo Set/26 | E29: =IF(Mensalidades!E10>0,Mensalidades!E10,"") | F29: =Mensalidades!A10 -> P3-05 | G29: =Mensalidades!B10 -> Gael Hanji Ventura Quimbundo | H29: Propina
A30: 46270 | B30: 41 | C30: 81 | D30: ="Propina - "&Mensalidades!B11&" Set/26" -> Propina - Ivanna Chayane Bernardo Clementino Set/26 | E30: =IF(Mensalidades!E11>0,Mensalidades!E11,"") | F30: =Mensalidades!A11 -> P3-06 | G30: =Mensalidades!B11 -> Ivanna Chayane Bernardo Clementino | H30: Propina
A31: 46270 | B31: 41 | C31: 81 | D31: ="Propina - "&Mensalidades!B12&" Set/26" -> Propina - Wendy Aryanne Chimuco Sabino Set/26 | E31: =IF(Mensalidades!E12>0,Mensalidades!E12,"") | F31: =Mensalidades!A12 -> P3-07 | G31: =Mensalidades!B12 -> Wendy Aryanne Chimuco Sabino | H31: Propina
A32: 46270 | B32: 41 | C32: 81 | D32: ="Propina - "&Mensalidades!B19&" Set/26" -> Propina - Set/26 | E32: =IF(Mensalidades!E19>0,Mensalidades!E19,"") | F32: =Mensalidades!A19 | G32: =Mensalidades!B19 | H32: Propina
A33: 46270 | B33: 41 | C33: 81 | D33: ="Propina - "&Mensalidades!B20&" Set/26" -> Propina - Set/26 | E33: =IF(Mensalidades!E20>0,Mensalidades!E20,"") | F33: =Mensalidades!A20 | G33: =Mensalidades!B20 | H33: Propina
A34: 46270 | B34: 41 | C34: 81 | D34: ="Propina - "&Mensalidades!B25&" Set/26" -> Propina - Set/26 | E34: =IF(Mensalidades!E25>0,Mensalidades!E25,"") | F34: =Mensalidades!A25 | G34: =Mensalidades!B25 | H34: Propina
D40: TOTAL MENSALIDADES | E40: =SUM(E25:E37) -> 0
D42: TOTAL GERAL | E42: =E21+E40 -> 1712000
A44: EMPRÉSTIMO / ADIANTAMENTO DO SÓCIO (Arranque)
A45: Data | B45: Debito | C45: Credito | D45: Descricao | E45: Valor | F45: Ref. | G45: Categoria | H45: Fonte
A46: 46187 | B46: 41 | C46: Empréstimo Sócio | D46: Entrada de capital do sócio (total despesas de arranque) | E46: =E67 -> 4988379.9 | F46: FAT-001 | G46: Empréstimo Sócio | H46: Adiantamentos_Emprestimos
D47: TOTAL EMPRÉSTIMO SÓCIO | E47: =E67 -> 4988379.9
A49: DESPESAS DE ARRANQUE (financiadas pelo empréstimo do sócio)
A50: Data | B50: Debito | C50: Credito | D50: Descricao | E50: Valor | F50: Ref. | G50: Categoria | H50: Fonte
A51: 46218 | B51: Pintura Exterior | C51: 41 | D51: Despesas de arranque – Pintura Exterior | E51: 1093730 | F51: Arranque | G51: Pintura Exterior | H51: Adiantamentos_Emprestimos
A52: 46223 | B52: Serralharia | C52: 41 | D52: Despesas de arranque – Serralharia | E52: 1208000 | F52: Arranque | G52: Serralharia | H52: Adiantamentos_Emprestimos
A53: 46228 | B53: Material Serralharia | C53: 41 | D53: Despesas de arranque – Material Serralharia | E53: 592500 | F53: Arranque | G53: Material Serralharia | H53: Adiantamentos_Emprestimos
A54: 46226 | B54: Mão de Obra | C54: 41 | D54: Despesas de arranque – Mão de Obra | E54: 45000 | F54: Arranque | G54: Mão de Obra | H54: Adiantamentos_Emprestimos
A55: 46218 | B55: Panfletos / Publicidade | C55: 41 | D55: Despesas de arranque – Panfletos / Publicidade | E55: 200000 | F55: Arranque | G55: Panfletos / Publicidade | H55: Adiantamentos_Emprestimos
A56: 46223 | B56: Publicidade Exterior | C56: 41 | D56: Despesas de arranque – Publicidade Exterior | E56: 285200 | F56: Arranque | G56: Publicidade Exterior | H56: Adiantamentos_Emprestimos
A57: 46228 | B57: Material de Escritório | C57: 41 | D57: Despesas de arranque – Material de Escritório | E57: 380566 | F57: Arranque | G57: Material de Escritório | H57: Adiantamentos_Emprestimos
A58: 46223 | B58: Equipamentos | C58: 41 | D58: Despesas de arranque – Equipamentos | E58: 677289.84 | F58: Arranque | G58: Equipamentos | H58: Adiantamentos_Emprestimos
A59: 46234 | B59: Limpeza / Higiene | C59: 41 | D59: Despesas de arranque – Limpeza / Higiene | E59: 2994 | F59: Arranque | G59: Limpeza / Higiene | H59: Adiantamentos_Emprestimos
A60: 46198 | B60: Internet / Telefone | C60: 41 | D60: Despesas de arranque – Internet / Telefone | E60: 213000.04 | F60: Arranque | G60: Internet / Telefone | H60: Adiantamentos_Emprestimos
A61: 46226 | B61: Transporte s/ Fatura | C61: 41 | D61: Despesas de arranque – Transporte s/ Fatura | E61: 9000 | F61: Arranque | G61: Transporte s/ Fatura | H61: Adiantamentos_Emprestimos
A62: 46223 | B62: Outras Despesas | C62: 41 | D62: Despesas de arranque – Outras Despesas | E62: 163100 | F62: Arranque | G62: Outras Despesas | H62: Adiantamentos_Emprestimos
... A64: 46247 | B64: Despesas de Representação | C64: 41 | D64: Despesas de arranque – Almoço de negócio para o colégio | E64: 28000 | F64: FAT-052 | G64: Despesas de Representação | H64: Adiantamentos_Emprestimos
D67: TOTAL DESPESAS ARRANQUE | E67: =SUM(E51:E64) -> 4988379.9

Sheet Fluxo de Caixa
A1: FLUXO DE CAIXA – Ano Letivo 2026/2027
A3: Mês | B3: Entradas Inscrições | C3: Entradas Propinas | D3: Entradas Extras | E3: Entradas Outras | F3: Total Entradas | G3: Saídas | H3: Saldo
A4: 46204 | B4: =SUMIFS('Controlo de Propinas'!N6:N105,'Controlo de Propinas'!K6:K105,">=2026-07-01",'Controlo de Propinas'!K6:K105,"<2026-08-01")+SUMIFS('Controlo de Propinas'!N110:N124,'Controlo de Propinas'!K110:K124,">=2026-07-01",'Controlo de Propinas'!K110:K124,"<2026-08-01")+SUMIFS('Controlo de Propinas'!N129:N187,'Controlo de Propinas'!K129:K187,">=2026-07-01",'Controlo de Propinas'!K129:K187,"<2026-08-01")+SUMIFS('Controlo de Propinas'!N192:N206,'Controlo de Propinas'!K192:K206,">=2026-07-01",'Controlo de Propinas'!K192:K206,"<2026-08-01")+SUMIFS('Controlo de Propinas'!N210:N248,'Controlo de Propinas'!K210:K248,">=2026-07-01",'Controlo de Propinas'!K210:K248,"<2026-08-01")+SUMIFS('Controlo de Propinas'!N253:N292,'Controlo de Propinas'!K253:K292,">=2026-07-01",'Controlo de Propinas'!K253:K292,"<2026-08-01") -> 1168000 | C4: =SUMIFS('Controlo de Propinas'!J6:J105,'Controlo de Propinas'!K6:K105,">=2026-07-01",'Controlo de Propinas'!K6:K105,"<2026-08-01")+SUMIFS('Controlo de Propinas'!J110:J124,'Controlo de Propinas'!K110:K124,">=2026-07-01",'Controlo de Propinas'!K110:K124,"<2026-08-01")+SUMIFS('Controlo de Propinas'!J129:J187,'Controlo de Propinas'!K129:K187,">=2026-07-01",'Controlo de Propinas'!K129:K187,"<2026-08-01")+SUMIFS('Controlo de Propinas'!J192:J206,'Controlo de Propinas'!K192:K206,">=2026-07-01",'Controlo de Propinas'!K192:K206,"<2026-08-01")+SUMIFS('Controlo de Propinas'!J210:J248,'Controlo de Propinas'!K210:K248,">=2026-07-01",'Controlo de Propinas'!K210:K248,"<2026-08-01")+SUMIFS('Controlo de Propinas'!J253:J292,'Controlo de Propinas'!K253:K292,">=2026-07-01",'Controlo de Propinas'!K253:K292,"<2026-08-01") -> 170000 | D4: 0 | E4: 4988379.9 | F4: =B4+C4+D4+E4 -> 6326379.9 | G4: 3500000 | H4: =F4-G4 -> 2826379.9
A5: 46235 | B5: =SUMIFS('Controlo de Propinas'!N6:N105,'Controlo de Propinas'!K6:K105,">=2026-08-01",'Controlo de Propinas'!K6:K105,"<2026-09-01")+SUMIFS('Controlo de Propinas'!N110:N124,'Controlo de Propinas'!K110:K124,">=2026-08-01",'Controlo de Propinas'!K110:K124,"<2026-09-01")+SUMIFS('Controlo de Propinas'!N129:N187,'Controlo de Propinas'!K129:K187,">=2026-08-01",'Controlo de Propinas'!K129:K187,"<2026-09-01")+SUMIFS('Controlo de Propinas'!N192:N206,'Controlo de Propinas'!K192:K206,">=2026-08-01",'Controlo de Propinas'!K192:K206,"<2026-09-01")+SUMIFS('Controlo de Propinas'!N210:N248,'Controlo de Propinas'!K210:K248,">=2026-08-01",'Controlo de Propinas'!K210:K248,"<2026-09-01")+SUMIFS('Controlo de Propinas'!N253:N292,'Controlo de Propinas'!K253:K292,">=2026-08-01",'Controlo de Propinas'!K253:K292,"<2026-09-01") -> 1720000 | C5: =SUMIFS('Controlo de Propinas'!J6:J105,'Controlo de Propinas'!K6:K105,">=2026-08-01",'Controlo de Propinas'!K6:K105,"<2026-09-01")+SUMIFS('Controlo de Propinas'!J110:J124,'Controlo de Propinas'!K110:K124,">=2026-08-01",'Controlo de Propinas'!K110:K124,"<2026-09-01")+SUMIFS('Controlo de Propinas'!J129:J187,'Controlo de Propinas'!K129:K187,">=2026-08-01",'Controlo de Propinas'!K129:K187,"<2026-09-01")+SUMIFS('Controlo de Propinas'!J192:J206,'Controlo de Propinas'!K192:K206,">=2026-08-01",'Controlo de Propinas'!K192:K206,"<2026-09-01")+SUMIFS('Controlo de Propinas'!J210:J248,'Controlo de Propinas'!K210:K248,">=2026-08-01",'Controlo de Propinas'!K210:K248,"<2026-09-01")+SUMIFS('Controlo de Propinas'!J253:J292,'Controlo de Propinas'!K253:K292,">=2026-08-01",'Controlo de Propinas'!K253:K292,"<2026-09-01") -> 0 | D5: 0 | E5: 0 | F5: =B5+C5+D5+E5 -> 1720000 | G5: 1488379.9 | H5: =H4+F5-G5 -> 3058000
A6: 46266 | B6: =SUMIFS('Controlo de Propinas'!N6:N105,'Controlo de Propinas'!K6:K105,">=2026-09-01",'Controlo de Propinas'!K6:K105,"<2026-10-01")+SUMIFS('Controlo de Propinas'!N110:N124,'Controlo de Propinas'!K110:K124,">=2026-09-01",'Controlo de Propinas'!K110:K124,"<2026-10-01")+SUMIFS('Controlo de Propinas'!N129:N187,'Controlo de Propinas'!K129:K187,">=2026-09-01",'Controlo de Propinas'!K129:K187,"<2026-10-01")+SUMIFS('Controlo de Propinas'!N192:N206,'Controlo de Propinas'!K192:K206,">=2026-09-01",'Controlo de Propinas'!K192:K206,"<2026-10-01")+SUMIFS('Controlo de Propinas'!N210:N248,'Controlo de Propinas'!K210:K248,">=2026-09-01",'Controlo de Propinas'!K210:K248,"<2026-10-01")+SUMIFS('Controlo de Propinas'!N253:N292,'Controlo de Propinas'!K253:K292,">=2026-09-01",'Controlo de Propinas'!K253:K292,"<2026-10-01") -> 0 | C6: =SUMIF(Mensalidades!E6:E80,">0")+SUMIF(Mensalidades!E85:E159,">0")+SUMIF(Mensalidades!E164:E238,">0")+SUMIF(Mensalidades!E243:E317,">0") -> 0 | D6: 0 | E6: 0 | F6: =B6+C6+D6+E6 -> 0 | G6: 0 | H6: =H5+F6-G6 -> 3058000
A7: 46296 | B7: 0 | C7: 0 | D7: 0 | E7: 0 | F7: =B7+C7+D7+E7 -> 0 | G7: 0 | H7: =H6+F7-G7 -> 3058000
A8: 46327 | B8: 0 | C8: 0 | D8: 0 | E8: 0 | F8: =B8+C8+D8+E8 -> 0 | G8: 0 | H8: =H7+F8-G8 -> 3058000
A9: 46357 | B9: 0 | C9: 0 | D9: 0 | E9: 0 | F9: =B9+C9+D9+E9 -> 0 | G9: 0 | H9: =H8+F9-G9 -> 3058000
A10: TOTAL | B10: =SUM(B4:B9) -> 2888000 | C10: =SUM(C4:C9) -> 170000 | D10: =SUM(D4:D9) -> 0 | E10: =SUM(E4:E9) -> 4988379.9 | F10: =SUM(F4:F9) -> 8046379.9 | G10: =SUM(G4:G9) -> 4988379.9 | H10: =H9 -> 3058000
A12: Nota: Inscrições calculadas por data de pagamento. Propinas vêm dos totais da planilha Mensalidades. Amarelo = inputs.

Sheet DRE
A1: DEMONSTRAÇÃO DE RESULTADOS (DRE) – Ano Letivo 2026/2027
A3: PROVEITOS
A4: Proveitos de Inscrições / Matrículas | B4: ='Controlo de Propinas'!N295-(SUMIF('Controlo de Propinas'!J6:J105,">0")+SUMIF('Controlo de Propinas'!J110:J124,">0")+SUMIF('Controlo de Propinas'!J129:J187,">0")+SUMIF('Controlo de Propinas'!J192:J206,">0")+SUMIF('Controlo de Propinas'!J210:J248,">0")+SUMIF('Controlo de Propinas'!J253:J292,">0")) -> 3088000
A5: Proveitos de Propinas Mensais | B5: =SUMIF('Controlo de Propinas'!J6:J105,">0")+SUMIF('Controlo de Propinas'!J110:J124,">0")+SUMIF('Controlo de Propinas'!J129:J187,">0")+SUMIF('Controlo de Propinas'!J192:J206,">0")+SUMIF('Controlo de Propinas'!J210:J248,">0")+SUMIF('Controlo de Propinas'!J253:J292,">0")+SUMIF(Mensalidades!E6:E80,">0")+SUMIF(Mensalidades!E85:E159,">0")+SUMIF(Mensalidades!E164:E238,">0")+SUMIF(Mensalidades!E243:E317,">0") -> 170000
A6: Proveitos Atividades Extras | B6: 0
A7: Outros Proveitos | B7: 0
A8: TOTAL PROVEITOS | B8: =SUM(B4:B7) -> 3258000
A10: CUSTOS E DESPESAS
A11: Custo de Pessoal (Salários) | B11: ='Lançamentos Contábeis'!E63 -> 90000
A12: Pintura Exterior | B12: ='Lançamentos Contábeis'!E51 -> 1093730
A13: Serralharia + Material Serralharia | B13: ='Lançamentos Contábeis'!E52+'Lançamentos Contábeis'!E53 -> 1800500
A14: Mão de Obra (outras) | B14: ='Lançamentos Contábeis'!E54 -> 45000
A15: Publicidade (Panfletos + Exterior) | B15: ='Lançamentos Contábeis'!E55+'Lançamentos Contábeis'!E56 -> 485200
A16: Material de Escritório | B16: ='Lançamentos Contábeis'!E57 -> 380566
A17: Equipamentos | B17: ='Lançamentos Contábeis'!E58 -> 677289.84
A18: Internet / Telefone | B18: ='Lançamentos Contábeis'!E60 -> 213000.04
A19: Limpeza / Transporte s/ Fat. / Outras | B19: ='Lançamentos Contábeis'!E59+'Lançamentos Contábeis'!E61+'Lançamentos Contábeis'!E62 -> 175094
A20: Compras / Manuais Escolares | B20: 0
A21: Despesas Atividades Extracurriculares | B21: 0
A22: Despesas de Representação | B22: ='Lançamentos Contábeis'!E64 -> 28000
A23: TOTAL CUSTOS E DESPESAS | B23: =SUM(B11:B22) -> 4988379.9
A25: RESULTADO LÍQUIDO | B25: =B8-B23 -> -1730379.9
A27: Nota: Proveitos de Inscrições = Controlo de Propinas (sem 1ª mensalidade). Propinas = 1ª mensalidade (Wendy) + Mensalidades. Despesas ligadas a Lançamentos Contábeis (arranque). 14 alunos inscritos.

Sheet Balanço Patrimonial
A1: BALANÇO PATRIMONIAL – Simplificado
A3: ATIVO
A4: Bancos (Caixa) | B4: ='Fluxo de Caixa'!H6 -> 3058000
A5: Clientes (Alunos - a receber) | B5: 0
A6: Imobilizações Corpóreas | B6: 0
A7: TOTAL ATIVO | B7: =SUM(B4:B6) -> 3058000
A9: PASSIVO + PATRIMÓNIO LÍQUIDO
A10: Passivo (Fornecedores / Outros) | B10: 0
A11: Resultado Líquido (do DRE) | B11: =DRE!B25 -> -1730379.9
A12: Capital / Outros (saldo) | B12: =B7-B10-B11 -> 4788379.9
A13: TOTAL PASSIVO + PL | B13: =SUM(B10:B12) -> 3058000

Sheet Relatórios
A1: RELATÓRIOS RÁPIDOS
A3: Resumo de Inscrições
A4: Nº de Alunos Inscritos | B4: ='Controlo de Propinas'!B295 -> 17
A5: Total Recebido em Inscrições | B5: ='Controlo de Propinas'!N295 -> 3258000
A7: Resumo Mensalidades
A8: Total Propinas Recebidas | B8: =SUMIF('Controlo de Propinas'!J6:J105,">0")+SUMIF('Controlo de Propinas'!J110:J124,">0")+SUMIF('Controlo de Propinas'!J129:J187,">0")+SUMIF('Controlo de Propinas'!J192:J206,">0")+SUMIF('Controlo de Propinas'!J210:J248,">0")+SUMIF('Controlo de Propinas'!J253:J292,">0")+SUMIF(Mensalidades!E6:E80,">0")+SUMIF(Mensalidades!E85:E159,">0")+SUMIF(Mensalidades!E164:E238,">0")+SUMIF(Mensalidades!E243:E317,">0") -> 170000
A10: Indicadores Globais
A11: Resultado Líquido (DRE) | B11: =DRE!B25 -> -1730379.9
A12: Saldo de Caixa | B12: ='Fluxo de Caixa'!H10 -> 3058000

Sheet Salários
A1: CONTROLO DE SALÁRIOS – 2026/2027
A2: Tabelas separadas: Professores | Administração | Pessoal Geral. Amarelo = input. Verde = calculado. Desconto = (Salário ÷ Dias Úteis) × Dias em Falta.
A4: PROFESSORES
A5: ID | B5: Nome Funcionário | C5: Função | D5: Salário Mensal (KZ) | E5: Mês | F5: Dias Úteis | G5: Dias Trabalhados | H5: Dias em Falta | I5: Desconto Faltas (KZ) | J5: Outros Descontos | K5: Valor Líquido | L5: Data Pagamento
F6: 22 | H6: =IF(OR(F6="",G6=""),"",MAX(0,F6-G6)) | I6: =IF(OR(D6="",F6="",H6=""),"",ROUND((D6/F6)*H6,0)) | J6: 0 | K6: =IF(D6="","",D6-IF(I6="",0,I6)-IF(J6="",0,J6))
F7: 22 | H7: =IF(OR(F7="",G7=""),"",MAX(0,F7-G7)) | I7: =IF(OR(D7="",F7="",H7=""),"",ROUND((D7/F7)*H7,0)) | J7: 0 | K7: =IF(D7="","",D7-IF(I7="",0,I7)-IF(J7="",0,J7))
F8: 22 | H8: =IF(OR(F8="",G8=""),"",MAX(0,F8-G8)) | I8: =IF(OR(D8="",F8="",H8=""),"",ROUND((D8/F8)*H8,0)) | J8: 0 | K8: =IF(D8="","",D8-IF(I8="",0,I8)-IF(J8="",0,J8))
F9: 22 | H9: =IF(OR(F9="",G9=""),"",MAX(0,F9-G9)) | I9: =IF(OR(D9="",F9="",H9=""),"",ROUND((D9/F9)*H9,0)) | J9: 0 | K9: =IF(D9="","",D9-IF(I9="",0,I9)-IF(J9="",0,J9))
F10: 22 | H10: =IF(OR(F10="",G10=""),"",MAX(0,F10-G10)) | I10: =IF(OR(D10="",F10="",H10=""),"",ROUND((D10/F10)*H10,0)) | J10: 0 | K10: =IF(D10="","",D10-IF(I10="",0,I10)-IF(J10="",0,J10))
F11: 22 | H11: =IF(OR(F11="",G11=""),"",MAX(0,F11-G11)) | I11: =IF(OR(D11="",F11="",H11=""),"",ROUND((D11/F11)*H11,0)) | J11: 0 | K11: =IF(D11="","",D11-IF(I11="",0,I11)-IF(J11="",0,J11))
A12: SUBTOTAL | D12: =SUMIF(D6:D11,">0") -> 0 | I12: =SUMIF(I6:I11,">0") -> 0 | J12: =SUMIF(J6:J11,">0") -> 0 | K12: =SUMIF(K6:K11,">0") -> 0
A14: ADMINISTRAÇÃO
A15: ID | B15: Nome Funcionário | C15: Função | D15: Salário Mensal (KZ) | E15: Mês | F15: Dias Úteis | G15: Dias Trabalhados | H15: Dias em Falta | I15: Desconto Faltas (KZ) | J15: Outros Descontos | K15: Valor Líquido | L15: Data Pagamento
F16: 22 | H16: =IF(OR(F16="",G16=""),"",MAX(0,F16-G16)) | I16: =IF(OR(D16="",F16="",H16=""),"",ROUND((D16/F16)*H16,0)) | J16: 0 | K16: =IF(D16="","",D16-IF(I16="",0,I16)-IF(J16="",0,J16))
F17: 22 | H17: =IF(OR(F17="",G17=""),"",MAX(0,F17-G17)) | I17: =IF(OR(D17="",F17="",H17=""),"",ROUND((D17/F17)*H17,0)) | J17: 0 | K17: =IF(D17="","",D17-IF(I17="",0,I17)-IF(J17="",0,J17))
F18: 22 | H18: =IF(OR(F18="",G18=""),"",MAX(0,F18-G18)) | I18: =IF(OR(D18="",F18="",H18=""),"",ROUND((D18/F18)*H18,0)) | J18: 0 | K18: =IF(D18="","",D18-IF(I18="",0,I18)-IF(J18="",0,J18))
F19: 22 | H19: =IF(OR(F19="",G19=""),"",MAX(0,F19-G19)) | I19: =IF(OR(D19="",F19="",H19=""),"",ROUND((D19/F19)*H19,0)) | J19: 0 | K19: =IF(D19="","",D19-IF(I19="",0,I19)-IF(J19="",0,J19))
A20: SUBTOTAL | D20: =SUMIF(D16:D19,">0") -> 0 | I20: =SUMIF(I16:I19,">0") -> 0 | J20: =SUMIF(J16:J19,">0") -> 0 | K20: =SUMIF(K16:K19,">0") -> 0
A22: PESSOAL GERAL
A23: ID | B23: Nome Funcionário | C23: Função | D23: Salário Mensal (KZ) | E23: Mês | F23: Dias Úteis | G23: Dias Trabalhados | H23: Dias em Falta | I23: Desconto Faltas (KZ) | J23: Outros Descontos | K23: Valor Líquido | L23: Data Pagamento
A24: 001 | B24: Adelaide Francisco Caculo | C24: Empregada Limpeza | D24: 90000 | E24: Julho | F24: 22 | G24: 11 | H24: =IF(OR(F24="",G24=""),"",MAX(0,F24-G24)) -> 11 | I24: =IF(OR(D24="",F24="",H24=""),"",ROUND((D24/F24)*H24,0)) -> 45000 | J24: 0 | K24: =IF(D24="","",D24-IF(I24="",0,I24)-IF(J24="",0,J24)) -> 45000 | L24: 46240
A25: 002 | B25: Teresa Nambala | C25: Empregada Limpeza | D25: 90000 | E25: Julho | F25: 22 | G25: 11 | H25: =IF(OR(F25="",G25=""),"",MAX(0,F25-G25)) -> 11 | I25: =IF(OR(D25="",F25="",H25=""),"",ROUND((D25/F25)*H25,0)) -> 45000 | J25: 0 | K25: =IF(D25="","",D25-IF(I25="",0,I25)-IF(J25="",0,J25)) -> 45000 | L25: 46240
F26: 22 | H26: =IF(OR(F26="",G26=""),"",MAX(0,F26-G26)) | I26: =IF(OR(D26="",F26="",H26=""),"",ROUND((D26/F26)*H26,0)) | J26: 0 | K26: =IF(D26="","",D26-IF(I26="",0,I26)-IF(J26="",0,J26))
F27: 22 | H27: =IF(OR(F27="",G27=""),"",MAX(0,F27-G27)) | I27: =IF(OR(D27="",F27="",H27=""),"",ROUND((D27/F27)*H27,0)) | J27: 0 | K27: =IF(D27="","",D27-IF(I27="",0,I27)-IF(J27="",0,J27))
A28: SUBTOTAL | D28: =SUMIF(D24:D27,">0") -> 180000 | I28: =SUMIF(I24:I27,">0") -> 90000 | J28: =SUMIF(J24:J27,">0") -> 0 | K28: =SUMIF(K24:K27,">0") -> 90000
A30: TOTAL GERAL | D30: =D12+D20+D28 -> 180000 | I30: =I12+I20+I28 -> 90000 | J30: =J12+J20+J28 -> 0 | K30: =K12+K20+K28 -> 90000
A32: INSTRUÇÕES: Preencha ID, Nome, Função, Salário, Mês e Dias Trabalhados (amarelo). Dias em Falta, Desconto e Valor Líquido calculam-se automaticamente.
A33: Os adiantamentos registados na planilha "Adiantamentos" devem ser incluídos em "Outros Descontos" no mês de regularização.
A34: École Consulaire du Congo (Brazzaville) de Luanda • Controlo de Salários por categoria

Sheet Recibos de Salário
A2: ÉCOLE CONSULAIRE DU CONGO – LUANDA
A3: Escola consular – Isenta de impostos
A5: RECIBO DE VENCIMENTO / SALÁRIO
A7: ID Funcionário: | B7: 001 | C7: Mês: | D7: Julho
A9: Nº Recibo: | B9: =IF(OR(B7="",D7=""),"","REC-"&B7&"-"&SUBSTITUTE(D7,"/","-")) -> REC-001-Julho | C9: Data Emissão: | D9: =TODAY() -> 46255
A11: DADOS DO FUNCIONÁRIO
A12: ID: | B12: =IF(B7="","",B7) -> 001 | C12: Nome: | D12: =IF(B7="","",IFERROR(INDEX(Salários!B:B,MATCH(B7&"",Salários!A:A,0)),IFERROR(INDEX(Salários!B:B,MATCH(B7,Salários!A:A,0)),"—"))) -> Adelaide Francisco Caculo
A13: Função: | B13: =IF(B7="","",IFERROR(INDEX(Salários!C:C,MATCH(B7&"",Salários!A:A,0)),IFERROR(INDEX(Salários!C:C,MATCH(B7,Salários!A:A,0)),"—"))) -> Empregada Limpeza | D13: Mês Ref.: | E13: =IF(D7="","",D7) -> Julho
A15: CÁLCULO DO VENCIMENTO
A16: Salário Base (Mensal): | C16: =IF(OR(B7="",D7=""),"",IFERROR(SUMIFS(Salários!D:D,Salários!A:A,B7&"",Salários!E:E,D7),IFERROR(SUMIFS(Salários!D:D,Salários!A:A,B7,Salários!E:E,D7),0))) -> 90000
A17: Dias Úteis do Mês: | C17: =IF(OR(B7="",D7=""),"",IFERROR(SUMIFS(Salários!F:F,Salários!A:A,B7&"",Salários!E:E,D7),IFERROR(SUMIFS(Salários!F:F,Salários!A:A,B7,Salários!E:E,D7),0))) -> 22
A18: Dias Trabalhados: | C18: =IF(OR(B7="",D7=""),"",IFERROR(SUMIFS(Salários!G:G,Salários!A:A,B7&"",Salários!E:E,D7),IFERROR(SUMIFS(Salários!G:G,Salários!A:A,B7,Salários!E:E,D7),0))) -> 11
A19: Dias em Falta: | C19: =IF(OR(B7="",D7=""),"",IFERROR(SUMIFS(Salários!H:H,Salários!A:A,B7&"",Salários!E:E,D7),IFERROR(SUMIFS(Salários!H:H,Salários!A:A,B7,Salários!E:E,D7),0))) -> 11
A20: Desconto por Faltas: | C20: =IF(OR(B7="",D7=""),"",IFERROR(SUMIFS(Salários!I:I,Salários!A:A,B7&"",Salários!E:E,D7),IFERROR(SUMIFS(Salários!I:I,Salários!A:A,B7,Salários!E:E,D7),0))) -> 45000
A21: Outros Descontos: | C21: =IF(OR(B7="",D7=""),"",IFERROR(SUMIFS(Salários!J:J,Salários!A:A,B7&"",Salários!E:E,D7),IFERROR(SUMIFS(Salários!J:J,Salários!A:A,B7,Salários!E:E,D7),0))) -> 0
A23: VALOR LÍQUIDO A RECEBER: | C23: =IF(OR(B7="",D7=""),"",IFERROR(SUMIFS(Salários!K:K,Salários!A:A,B7&"",Salários!E:E,D7),IFERROR(SUMIFS(Salários!K:K,Salários!A:A,B7,Salários!E:E,D7),0))) -> 45000
A24: Data de Pagamento: | C24: =IF(OR(B7="",D7=""),"",IFERROR(LOOKUP(2,1/((Salários!A6:A27&""=B7&"")*(Salários!E6:E27=D7)),Salários!L6:L27),"")) -> 46240
A26: ASSINATURAS
A28: O Funcionário | D28: A Direção / Contabilidade
A30: ____________________________ | D30: ____________________________
A31: (Nome e Assinatura) | D31: (Nome e Assinatura)
A34: École Consulaire du Congo (Brazzaville) de Luanda

Sheet Adiantamentos
A1: CONTROLO DE ADIANTAMENTOS A FUNCIONÁRIOS – 2026/2027
A2: Amarelo = input. Verde = calculado. Adiantamentos de dinheiro antes do final do mês. Devem ser descontados no salário (Outros Descontos).
A4: Nº Vale | B4: ID Funcionário | C4: Nome Funcionário | D4: Categoria | E4: Valor (KZ) | F4: Data Pedido | G4: Data Entrega | H4: Mês a Descontar | I4: Motivo / Observações | J4: Status
A5: =IF(B5="","","ADV-"&TEXT(COUNTA($B$5:B5),"000")) | J5: =IF(B5="","",IF(G5="","Pendente","Entregue"))
A6: =IF(B6="","","ADV-"&TEXT(COUNTA($B$5:B6),"000")) | J6: =IF(B6="","",IF(G6="","Pendente","Entregue"))
A7: =IF(B7="","","ADV-"&TEXT(COUNTA($B$5:B7),"000")) | J7: =IF(B7="","",IF(G7="","Pendente","Entregue"))
A8: =IF(B8="","","ADV-"&TEXT(COUNTA($B$5:B8),"000")) | J8: =IF(B8="","",IF(G8="","Pendente","Entregue"))
A9: =IF(B9="","","ADV-"&TEXT(COUNTA($B$5:B9),"000")) | J9: =IF(B9="","",IF(G9="","Pendente","Entregue"))
A10: =IF(B10="","","ADV-"&TEXT(COUNTA($B$5:B10),"000")) | J10: =IF(B10="","",IF(G10="","Pendente","Entregue"))
A11: =IF(B11="","","ADV-"&TEXT(COUNTA($B$5:B11),"000")) | J11: =IF(B11="","",IF(G11="","Pendente","Entregue"))
A12: =IF(B12="","","ADV-"&TEXT(COUNTA($B$5:B12),"000")) | J12: =IF(B12="","",IF(G12="","Pendente","Entregue"))
A13: =IF(B13="","","ADV-"&TEXT(COUNTA($B$5:B13),"000")) | J13: =IF(B13="","",IF(G13="","Pendente","Entregue"))
A14: =IF(B14="","","ADV-"&TEXT(COUNTA($B$5:B14),"000")) | J14: =IF(B14="","",IF(G14="","Pendente","Entregue"))
A15: =IF(B15="","","ADV-"&TEXT(COUNTA($B$5:B15),"000")) | J15: =IF(B15="","",IF(G15="","Pendente","Entregue"))
A16: =IF(B16="","","ADV-"&TEXT(COUNTA($B$5:B16),"000")) | J16: =IF(B16="","",IF(G16="","Pendente","Entregue"))
... A50: =IF(B50="","","ADV-"&TEXT(COUNTA($B$5:B50),"000")) | J50: =IF(B50="","",IF(G50="","Pendente","Entregue"))
A51: TOTAL | E51: =SUMIF(E5:E50,">0") -> 0
A53: INSTRUÇÕES:
A54: 1. Preencha ID, Nome, Categoria, Valor, Datas e Mês a Descontar (células amarelas).
A55: 2. O Nº Vale (ADV-001, ADV-002...) é gerado automaticamente. Status passa a "Entregue" quando preencher Data Entrega.
A56: 3. No mês de desconto, insira o valor do adiantamento em "Outros Descontos" na planilha Salários.
A57: 4. Use a planilha "Vales de Adiantamento": digite o Nº Vale (ex: ADV-001) na célula amarela para gerar o recibo imprimível com data automática.

Sheet Vales de Adiantamento
A2: ÉCOLE CONSULAIRE DU CONGO – LUANDA
A3: Escola consular – Isenta de impostos
A5: VALE DE ADIANTAMENTO DE SALÁRIO
A7: Nº Vale: | C7: ← Digite o Nº Vale (ex: ADV-001)
A9: Data Emissão: | B9: =TODAY() -> 46255
A11: DADOS DO ADIANTAMENTO
A12: Nº Vale: | B12: =IF(B7="","",B7) | C12: ID Funcionário: | D12: =IF(B7="","",IFERROR(INDEX(Adiantamentos!B:B,MATCH(B7,Adiantamentos!A:A,0)),"—"))
A13: Nome: | B13: =IF(B7="","",IFERROR(INDEX(Adiantamentos!C:C,MATCH(B7,Adiantamentos!A:A,0)),"—"))
A14: Categoria: | B14: =IF(B7="","",IFERROR(INDEX(Adiantamentos!D:D,MATCH(B7,Adiantamentos!A:A,0)),"—")) | C14: Mês a Descontar: | D14: =IF(B7="","",IFERROR(INDEX(Adiantamentos!H:H,MATCH(B7,Adiantamentos!A:A,0)),"—"))
A15: Data Pedido: | B15: =IF(B7="","",IFERROR(INDEX(Adiantamentos!F:F,MATCH(B7,Adiantamentos!A:A,0)),"")) | C15: Data Entrega: | D15: =IF(B7="","",IFERROR(INDEX(Adiantamentos!G:G,MATCH(B7,Adiantamentos!A:A,0)),""))
A16: Motivo: | B16: =IF(B7="","",IFERROR(INDEX(Adiantamentos!I:I,MATCH(B7,Adiantamentos!A:A,0)),"—"))
A18: VALOR DO ADIANTAMENTO: | C18: =IF(B7="","",IFERROR(INDEX(Adiantamentos!E:E,MATCH(B7,Adiantamentos!A:A,0)),0))
A19: Status: | B19: =IF(B7="","",IFERROR(INDEX(Adiantamentos!J:J,MATCH(B7,Adiantamentos!A:A,0)),"—"))
A21: DECLARAÇÃO
A22: Declaro ter recebido o valor acima indicado a título de adiantamento de salário, autorizando o respetivo desconto no vencimento do mês indicado. Comprometo-me a regularizar qualquer diferença conforme o regulamento interno da escola.
A25: ASSINATURAS DE AUTORIZAÇÃO
A27: O Funcionário (Recebi) | C27: Responsável / Direção | E27: Contabilidade / Caixa
A29: ________________________ | C29: ________________________ | E29: ________________________
A30: (Nome e Assinatura) | C30: (Nome e Assinatura) | E30: (Nome e Assinatura)
A31: Data: ____/____/________ | C31: Data: ____/____/________ | E31: Data: ____/____/________
A33: INSTRUÇÃO: 1) Na planilha Adiantamentos preencha os dados (Nº Vale gerado automaticamente). 2) Aqui digite o Nº Vale (ex: ADV-001) na célula amarela B7. 3) Data de emissão = hoje (automática). 4) Imprima o vale.
A34: École Consulaire du Congo (Brazzaville) de Luanda
